Workbook

Sheet RESOLUCIONES EPG
A1: ESCUELA DE POSGRADO UNVERSIDAD ANDINA DEL CUSCO
A4: RESOLUCIONES EMITIDAS 2015-2025
A7: N° SOLICITUD | B7: N° SOLICITUD2 | C7: RESOL. N° | D7: FECHA | E7: NOMBRES Y APELLIDOS | F7: CODIGO | G7: TIPO DE RESOLUCION | H7: Obaservaciones | I7: RESOLUCION 2 | J7: RESOLUCION 3 | K7: RESOLUCION 4 | L7: RESOLUCION 5 | M7: RESOLUCION 6 | N7: HOY | O7: Dias de la resolucion
A8: ='RESOLUCIONES 2015'!A5868:H5868 | B8: 44613 | C8: 7 | D8: 42044 | E8: TANIA KARINA ECHEGARAY CASTILLO | G8: NOMBRAMIENTO DE ASESOR | N8: =TODAY() -> 46206 | O8: ='RESOLUCIONES EPG'!$N8-'RESOLUCIONES EPG'!$D8 -> 4162
A9: ='RESOLUCIONES 2015'!A5879:H5879 | B9: 1603 | C9: 18 | D9: 42044 | E9: SHAILI JULIE CAVERO PACHECO | G9: NOMBRAMIENTO DE ASESOR | N9: =TODAY() -> 46206 | O9: ='RESOLUCIONES EPG'!$N9-'RESOLUCIONES EPG'!$D9 -> 4162
A10: ='RESOLUCIONES 2015'!A5864:H5864 | B10: 34309 | C10: 3 | D10: 42044 | E10: PASTORA AYDEEE MOGROVEJO | G10: APTO PARA SUSTENCION DE TESIS | N10: =TODAY() -> 46206 | O10: ='RESOLUCIONES EPG'!$N10-'RESOLUCIONES EPG'!$D10 -> 4162
A11: ='RESOLUCIONES 2015'!A5870:H5870 | B11: 27237 | C11: 9 | D11: 42044 | E11: PAOLA ESTRADA SANCHEZ | G11: APROBAR Y AUTORIZAR INSCRIPCION | N11: =TODAY() -> 46206 | O11: ='RESOLUCIONES EPG'!$N11-'RESOLUCIONES EPG'!$D11 -> 4162
A12: ='RESOLUCIONES 2015'!A5877:H5877 | B12: 44850 | C12: 16 | D12: 42044 | E12: MARIA LILIANA PEÑA FARFAN | G12: NOMBRAMIENTO DE ASESOR | N12: =TODAY() -> 46206 | O12: ='RESOLUCIONES EPG'!$N12-'RESOLUCIONES EPG'!$D12 -> 4162
A13: ='RESOLUCIONES 2015'!A5862:H5862 | B13: 42296 | C13: 1 | D13: 42044 | E13: MARCO FERNANDO CARPIO SANCHEZ | G13: MOFICAR RESOL. 044-2012/EPG-UAC TITULO DE TRABAJO | N13: =TODAY() -> 46206 | O13: ='RESOLUCIONES EPG'!$N13-'RESOLUCIONES EPG'!$D13 -> 4162
A14: ='RESOLUCIONES 2015'!A5865:H5865 | B14: 44228 | C14: 4 | D14: 42044 | E14: LUZ MARIA CAHUANA FERNANDEZ | G14: DESIGNACION DE DICTAMINANTES | N14: =TODAY() -> 46206 | O14: ='RESOLUCIONES EPG'!$N14-'RESOLUCIONES EPG'!$D14 -> 4162
A15: ='RESOLUCIONES 2015'!A5875:H5875 | B15: 44345 | C15: 14 | D15: 42044 | E15: KELLY OLIVERA OJEDA | G15: DESIGNACION DE DICTAMINANTES | N15: =TODAY() -> 46206 | O15: ='RESOLUCIONES EPG'!$N15-'RESOLUCIONES EPG'!$D15 -> 4162
A16: ='RESOLUCIONES 2015'!A5866:H5866 | B16: 43489 | C16: 5 | D16: 42044 | E16: KARLA FERNANDEZ TOHALINO | G16: DESIGNACION DE DICTAMINANTES | N16: =TODAY() -> 46206 | O16: ='RESOLUCIONES EPG'!$N16-'RESOLUCIONES EPG'!$D16 -> 4162
A17: ='RESOLUCIONES 2015'!A5871:H5871 | B17: 44733 | C17: 10 | D17: 42044 | E17: JOSE LUIS ESQUIVEL TAIPE | G17: NOMBRAMIENTO DE ASESOR | N17: =TODAY() -> 46206 | O17: ='RESOLUCIONES EPG'!$N17-'RESOLUCIONES EPG'!$D17 -> 4162
A18: ='RESOLUCIONES 2015'!A5872:H5872 | B18: 44374 | C18: 11 | D18: 42044 | E18: JOSE LUIS ESQUIVEL TAIPE | G18: DESIGNACION DE DICTAMINANTES | N18: =TODAY() -> 46206 | O18: ='RESOLUCIONES EPG'!$N18-'RESOLUCIONES EPG'!$D18 -> 4162
A19: ='RESOLUCIONES 2015'!A5876:H5876 | B19: 44823 | C19: 15 | D19: 42044 | E19: JAVIER ORLANDO CUNZA | G19: NOMBRAMIENTO DE ASESOR | N19: =TODAY() -> 46206 | O19: ='RESOLUCIONES EPG'!$N19-'RESOLUCIONES EPG'!$D19 -> 4162
A20: ='RESOLUCIONES 2015'!A5878:H5878 | B20: 44739 | C20: 17 | D20: 42044 | E20: JACKELINE CECILIA ORQQUE CHACON | G20: NOMBRAMIENTO DE ASESOR | N20: =TODAY() -> 46206 | O20: ='RESOLUCIONES EPG'!$N20-'RESOLUCIONES EPG'!$D20 -> 4162
A21: ='RESOLUCIONES 2015'!A5873:H5873 | B21: 44794 | C21: 12 | D21: 42044 | E21: GLORIA CHACON ORDOÑEZ | G21: DESIGNACION DE DICTAMINANTES | N21: =TODAY() -> 46206 | O21: ='RESOLUCIONES EPG'!$N21-'RESOLUCIONES EPG'!$D21 -> 4162
A22: ='RESOLUCIONES 2015'!A5869:H5869 | B22: 41942 | C22: 8 | D22: 42044 | E22: GISELA GIOVANA PUELLES FOLLANA | G22: DESIGNACION DE DICTAMINANTES | N22: =TODAY() -> 46206 | O22: ='RESOLUCIONES EPG'!$N22-'RESOLUCIONES EPG'!$D22 -> 4162
A23: ='RESOLUCIONES 2015'!A5863:H5863 | B23: 41516 | C23: 2 | D23: 42044 | E23: GIOVANA DUEÑAS PAREJA | G23: FECHA Y HORA DE SUSTENTACION | N23: =TODAY() -> 46206 | O23: ='RESOLUCIONES EPG'!$N23-'RESOLUCIONES EPG'!$D23 -> 4162
A24: ='RESOLUCIONES 2015'!A5874:H5874 | B24: 44346 | C24: 13 | D24: 42044 | E24: DEYRA SORAYA SUAREZ RAMOS | G24: DESIGNACION DE DICTAMINANTES | N24: =TODAY() -> 46206 | O24: ='RESOLUCIONES EPG'!$N24-'RESOLUCIONES EPG'!$D24 -> 4162
A25: ='RESOLUCIONES 2015'!A5880:H5880 | B25: 3470 | C25: 19 | D25: 42046 | E25: RAFAEL AQUIZE ESTRADA | G25: DESIGNACION DE DICTAMINANTES | N25: =TODAY() -> 46206 | O25: ='RESOLUCIONES EPG'!$N25-'RESOLUCIONES EPG'!$D25 -> 4160
A26: ='RESOLUCIONES 2015'!A5883:H5883 | B26: 3307 | C26: 22 | D26: 42046 | E26: LUIS ALBERTO BEJARANO JORDAN | G26: NOMBRAMIENTO DE ASESOR | N26: =TODAY() -> 46206 | O26: ='RESOLUCIONES EPG'!$N26-'RESOLUCIONES EPG'!$D26 -> 4160
A27: ='RESOLUCIONES 2015'!A5885:H5885 | B27: 3307 | C27: 24 | D27: 42046 | E27: LUIS ALBERTO BEJARANO JORDAN | G27: NOMBRAMIENTO DE ASESOR | N27: =TODAY() -> 46206 | O27: ='RESOLUCIONES EPG'!$N27-'RESOLUCIONES EPG'!$D27 -> 4160
A28: ='RESOLUCIONES 2015'!A5881:H5881 | B28: 1509 | C28: 20 | D28: 42046 | E28: CANSAYA ROMAN AYDEE | G28: SUBSANACION | N28: =TODAY() -> 46206 | O28: ='RESOLUCIONES EPG'!$N28-'RESOLUCIONES EPG'!$D28 -> 4160
A29: ='RESOLUCIONES 2015'!A5882:H5882 | B29: 686 | C29: 21 | D29: 42046 | E29: ANGULO CABRERA MARIA LUISA | G29: SUBSANACION | N29: =TODAY() -> 46206 | O29: ='RESOLUCIONES EPG'!$N29-'RESOLUCIONES EPG'!$D29 -> 4160
A30: ='RESOLUCIONES 2015'!A5886:H5886 | B30: 3001 | C30: 25 | D30: 42046 | E30: ANGEL MUÑOZ ARAGON | G30: NOMBRAMIENTO DE ASESOR | N30: =TODAY() -> 46206 | O30: ='RESOLUCIONES EPG'!$N30-'RESOLUCIONES EPG'!$D30 -> 4160
A31: ='RESOLUCIONES 2015'!A5884:H5884 | B31: 38421 | C31: 23 | D31: 42047 | E31: SALAS AYCHO NANCY VIOLETA | G31: SUBSANACION | N31: =TODAY() -> 46206 | O31: ='RESOLUCIONES EPG'!$N31-'RESOLUCIONES EPG'!$D31 -> 4159
A32: ='RESOLUCIONES 2015'!A5890:H5890 | B32: 3007 | C32: 29 | D32: 42047 | E32: RENAN RAMIREZ VARGAS | G32: DESIGNACION DE DICTAMINANTES | N32: =TODAY() -> 46206 | O32: ='RESOLUCIONES EPG'!$N32-'RESOLUCIONES EPG'!$D32 -> 4159
A33: ='RESOLUCIONES 2015'!A5889:H5889 | C33: 28 | D33: 42047 | E33: PROCESO ADMISION | G33: COMISION DEL PROCESO DE ADMISION 2015-1 | N33: =TODAY() -> 46206 | O33: ='RESOLUCIONES EPG'!$N33-'RESOLUCIONES EPG'!$D33 -> 4159
A34: ='RESOLUCIONES 2015'!A5888:H5888 | B34: 27782 | C34: 27 | D34: 42047 | E34: LUIS GHANDY ROJAS ARIAS | G34: INSCRIPCION DE TEMA DE TESIS | N34: =TODAY() -> 46206 | O34: ='RESOLUCIONES EPG'!$N34-'RESOLUCIONES EPG'!$D34 -> 4159
A35: ='RESOLUCIONES 2015'!A5887:H5887 | B35: 4202 | C35: 26 | D35: 42047 | E35: JOSE ANTONIO ALANYA RICALDE | G35: DESIGNACION DE DICTAMINANTES | N35: =TODAY() -> 46206 | O35: ='RESOLUCIONES EPG'!$N35-'RESOLUCIONES EPG'!$D35 -> 4159
A36: ='RESOLUCIONES 2015'!A5892:H5892 | B36: 44824 | C36: 31 | D36: 42048 | E36: JAVIER ORLANDO CUNZA VALDEIGLESIAS | F36: Actualizacion | G36: DESIGNACION DE DICTAMINANTES | N36: =TODAY() -> 46206 | O36: ='RESOLUCIONES EPG'!$N36-'RESOLUCIONES EPG'!$D36 -> 4158
A37: ='RESOLUCIONES 2015'!A5891:H5891 | B37: 27782 | C37: 30 | D37: 42052 | E37: MARIA ROSA GAMIO VEGA CENTENO | G37: DESIGNACION DE DICTAMINANTES | N37: =TODAY() -> 46206 | O37: ='RESOLUCIONES EPG'!$N37-'RESOLUCIONES EPG'!$D37 -> 4154
A38: ='RESOLUCIONES 2015'!A5893:H5893 | B38: 36884 | C38: 32 | D38: 42052 | E38: JOSE LUIS GONZALES AVENDAÑO | G38: MODIFICAR LA RESOLUCION 232-2014/EPG-UAC | N38: =TODAY() -> 46206 | O38: ='RESOLUCIONES EPG'!$N38-'RESOLUCIONES EPG'!$D38 -> 4154
A39: ='RESOLUCIONES 2015'!A5895:H5895 | B39: 3854 | C39: 34 | D39: 42053 | E39: MARIA LILIANA PEÑA FARFAN | G39: DESIGNACION DE DICTAMINANTES | N39: =TODAY() -> 46206 | O39: ='RESOLUCIONES EPG'!$N39-'RESOLUCIONES EPG'!$D39 -> 4153
A40: ='RESOLUCIONES 2015'!A5896:H5896 | B40: 5328 | C40: 35 | D40: 42053 | E40: JUAN DIEGO PALOMINO DELGADO | G40: DESIGNACION DE DICTAMINANTES | N40: =TODAY() -> 46206 | O40: ='RESOLUCIONES EPG'!$N40-'RESOLUCIONES EPG'!$D40 -> 4153
A41: ='RESOLUCIONES 2015'!A5894:H5894 | B41: 3671 | C41: 33 | D41: 42053 | E41: CARLOS ALBERTO VALENCIA MARTINEZ | G41: JURADO DICTAMINADOR PARA SUTENTACION | N41: =TODAY() -> 46206 | O41: ='RESOLUCIONES EPG'!$N41-'RESOLUCIONES EPG'!$D41 -> 4153
A42: ='RESOLUCIONES 2015'!A5897:H5897 | C42: 36 | D42: 42059 | E42: INGRESANTES ADMISION 2015 | G42: INGRESANTES A LA MAESTRIA EN DERECHO CONSTITUCIONAL | N42: =TODAY() -> 46206 | O42: ='RESOLUCIONES EPG'!$N42-'RESOLUCIONES EPG'!$D42 -> 4147
A43: ='RESOLUCIONES 2015'!A5898:H5898 | C43: 37 | D43: 42059 | E43: INGRESANTES ADMISION 2015 | G43: INGRESANTES A LA MAESTRIA EN ADMINISTRACION DE NEGOCIOS | N43: =TODAY() -> 46206 | O43: ='RESOLUCIONES EPG'!$N43-'RESOLUCIONES EPG'!$D43 -> 4147
A44: ='RESOLUCIONES 2015'!A5899:H5899 | C44: 38 | D44: 42059 | E44: INGRESANTES ADMISION 2015 | G44: INGRESANTES A LA MAESTRIA EN ESTADISTICA E INVESTIGACION CIENTIFICA | N44: =TODAY() -> 46206 | O44: ='RESOLUCIONES EPG'!$N44-'RESOLUCIONES EPG'!$D44 -> 4147
A45: ='RESOLUCIONES 2015'!A5900:H5900 | C45: 39 | D45: 42059 | E45: INGRESANTES ADMISION 2015 | G45: INGRESANTES A LA MAESTRIA EN SEGURIDAD INDUSTRIAL Y MEDIO AMBIENTE | N45: =TODAY() -> 46206 | O45: ='RESOLUCIONES EPG'!$N45-'RESOLUCIONES EPG'!$D45 -> 4147
A46: ='RESOLUCIONES 2015'!A5901:H5901 | C46: 40 | D46: 42059 | E46: INGRESANTES ADMISION 2015 | G46: INGRESANTES A LA MAESTRIA EN DERECHO CIVIL Y COMERCIAL | N46: =TODAY() -> 46206 | O46: ='RESOLUCIONES EPG'!$N46-'RESOLUCIONES EPG'!$D46 -> 4147
A47: ='RESOLUCIONES 2015'!A5908:H5908 | B47: 6663 | C47: 47 | D47: 42061 | E47: YANINA ROJAS ANAYA | G47: DESIGNACION DE DICTAMINANTES | N47: =TODAY() -> 46206 | O47: ='RESOLUCIONES EPG'!$N47-'RESOLUCIONES EPG'!$D47 -> 4145
A48: ='RESOLUCIONES 2015'!A5907:H5907 | B48: 6532 | C48: 46 | D48: 42061 | E48: WILFREDO TAPIA QUISPE | G48: NOMBRAMIENTO DE ASESOR | N48: =TODAY() -> 46206 | O48: ='RESOLUCIONES EPG'!$N48-'RESOLUCIONES EPG'!$D48 -> 4145
A49: ='RESOLUCIONES 2015'!A5911:H5911 | B49: 7226 | C49: 50 | D49: 42061 | E49: TANIA KARINA ECHEGARAY CASTILLO | G49: DESIGNACION DE DICTAMINANTES | N49: =TODAY() -> 46206 | O49: ='RESOLUCIONES EPG'!$N49-'RESOLUCIONES EPG'!$D49 -> 4145
A50: ='RESOLUCIONES 2015'!A5918:H5918 | B50: 4153 | C50: 57 | D50: 42061 | E50: PASTORA AYDEEE MOGROVEJO | G50: NOMBRAMIENTO DE JURADO EXAMINDOR SUSTENTACION | N50: =TODAY() -> 46206 | O50: ='RESOLUCIONES EPG'!$N50-'RESOLUCIONES EPG'!$D50 -> 4145
A51: ='RESOLUCIONES 2015'!A5913:H5913 | B51: 26053 | C51: 52 | D51: 42061 | E51: PAREJA QUINTANA EVELIN GUILISA | G51: DECLARAR IMPROCEDENTE SOLICITUD | N51: =TODAY() -> 46206 | O51: ='RESOLUCIONES EPG'!$N51-'RESOLUCIONES EPG'!$D51 -> 4145
A52: ='RESOLUCIONES 2015'!A5904:H5904 | B52: 5474 | C52: 43 | D52: 42061 | E52: MOISES QUISPE SALZAR | G52: NOMBRAMIENTO DE ASESOR | N52: =TODAY() -> 46206 | O52: ='RESOLUCIONES EPG'!$N52-'RESOLUCIONES EPG'!$D52 -> 4145
A53: ='RESOLUCIONES 2015'!A5903:H5903 | B53: 4714 | C53: 42 | D53: 42061 | E53: MARIA ISABEL HUAMANI PEREZ | G53: NOMBRAMIENTO DE ASESOR | N53: =TODAY() -> 46206 | O53: ='RESOLUCIONES EPG'!$N53-'RESOLUCIONES EPG'!$D53 -> 4145
A54: ='RESOLUCIONES 2015'!A5905:H5905 | B54: 5821 | C54: 44 | D54: 42061 | E54: MANUEL E. HIDALGO LEON | G54: NOMBRAMIENTO DE ASESOR | N54: =TODAY() -> 46206 | O54: ='RESOLUCIONES EPG'!$N54-'RESOLUCIONES EPG'!$D54 -> 4145
A55: ='RESOLUCIONES 2015'!A5914:H5914 | B55: 225799 | C55: 53 | D55: 42061 | E55: LOIZA LOVATON MONICA | G55: SUBSANACION | N55: =TODAY() -> 46206 | O55: ='RESOLUCIONES EPG'!$N55-'RESOLUCIONES EPG'!$D55 -> 4145
A56: ='RESOLUCIONES 2015'!A5916:H5916 | B56: 42378 | C56: 55 | D56: 42061 | E56: FUENTES TUPAYACHI CRISTINA | G56: SUBSANACION | N56: =TODAY() -> 46206 | O56: ='RESOLUCIONES EPG'!$N56-'RESOLUCIONES EPG'!$D56 -> 4145
A57: ='RESOLUCIONES 2015'!A5910:H5910 | B57: 6033 | C57: 49 | D57: 42061 | E57: ERICSON DELGADO OTAZU | G57: NOMBRAMIENTO DE ASESOR | N57: =TODAY() -> 46206 | O57: ='RESOLUCIONES EPG'!$N57-'RESOLUCIONES EPG'!$D57 -> 4145
A58: ='RESOLUCIONES 2015'!A5917:H5917 | B58: 21015 | C58: 56 | D58: 42061 | E58: ELVIS EFRAIN MIRANDA CORDOBA | G58: NOMBRAMIENTO DE ASESOR | N58: =TODAY() -> 46206 | O58: ='RESOLUCIONES EPG'!$N58-'RESOLUCIONES EPG'!$D58 -> 4145
A59: ='RESOLUCIONES 2015'!A5902:H5902 | B59: 4737 | C59: 41 | D59: 42061 | E59: CARLOS SANCHEZ BURGOS | G59: DESIGNACION DE DICTAMINANTES | N59: =TODAY() -> 46206 | O59: ='RESOLUCIONES EPG'!$N59-'RESOLUCIONES EPG'!$D59 -> 4145
A60: ='RESOLUCIONES 2015'!A5919:H5919 | B60: 4380 | C60: 58 | D60: 42061 | E60: BENEDICTO BACA ROSADO | G60: DESIGNACION DE DICTAMINANTES | N60: =TODAY() -> 46206 | O60: ='RESOLUCIONES EPG'!$N60-'RESOLUCIONES EPG'!$D60 -> 4145
A61: ='RESOLUCIONES 2015'!A5906:H5906 | B61: 6621 | C61: 45 | D61: 42061 | E61: AQUILES SUYO CAPARO | G61: NOMBRAMIENTO DE ASESOR | N61: =TODAY() -> 46206 | O61: ='RESOLUCIONES EPG'!$N61-'RESOLUCIONES EPG'!$D61 -> 4145
A62: ='RESOLUCIONES 2015'!A5909:H5909 | B62: 6407 | C62: 48 | D62: 42061 | E62: ANTONIO SALAS CALLO | G62: DESIGNACION DE DICTAMINANTES | N62: =TODAY() -> 46206 | O62: ='RESOLUCIONES EPG'!$N62-'RESOLUCIONES EPG'!$D62 -> 4145
A63: ='RESOLUCIONES 2015'!A5915:H5915 | B63: 40286 | C63: 54 | D63: 42061 | E63: ANCCO OROZ MARGARET | G63: SUBSANACION | N63: =TODAY() -> 46206 | O63: ='RESOLUCIONES EPG'!$N63-'RESOLUCIONES EPG'!$D63 -> 4145
A64: ='RESOLUCIONES 2015'!A5912:H5912 | B64: 7076 | C64: 51 | D64: 42061 | E64: ABRAHAM EDGARD CANAHUIRE MONTUFAR | G64: DESIGNACION DE DICTAMINANTES | N64: =TODAY() -> 46206 | O64: ='RESOLUCIONES EPG'!$N64-'RESOLUCIONES EPG'!$D64 -> 4145
A65: ='RESOLUCIONES 2015'!A5925:H5925 | C65: 64 | D65: 42066 | G65: ADMITIR A POSTULANTES A LAS DIFERENTES MAESTRIAS | N65: =TODAY() -> 46206 | O65: ='RESOLUCIONES EPG'!$N65-'RESOLUCIONES EPG'!$D65 -> 4140
A66: ='RESOLUCIONES 2015'!A5921:H5921 | B66: 6747 | C66: 60 | D66: 42068 | E66: WILFREDO TAPIA QUISPE | G66: DESIGNACION DE DICTAMINANTES | N66: =TODAY() -> 46206 | O66: ='RESOLUCIONES EPG'!$N66-'RESOLUCIONES EPG'!$D66 -> 4138
A67: ='RESOLUCIONES 2015'!A5922:H5922 | B67: 7684 | C67: 61 | D67: 42068 | E67: CARLOS RAMON QUISPE ONOFRE | F67: Curso actualizacion | G67: NOMBRAMIENTO DE ASESOR | N67: =TODAY() -> 46206 | O67: ='RESOLUCIONES EPG'!$N67-'RESOLUCIONES EPG'!$D67 -> 4138
A68: ='RESOLUCIONES 2015'!A5920:H5920 | B68: 6622 | C68: 59 | D68: 42068 | E68: AQUILES SUYO CAPARO | G68: DESIGNACION DE DICTAMINANTES | N68: =TODAY() -> 46206 | O68: ='RESOLUCIONES EPG'!$N68-'RESOLUCIONES EPG'!$D68 -> 4138
A69: ='RESOLUCIONES 2015'!A5924:H5924 | C69: 63 | D69: 42072 | E69: INGRESANTES ADMISION 2015 | G69: RECTIFICAR ERROR DE INGRESANTES | N69: =TODAY() -> 46206 | O69: ='RESOLUCIONES EPG'!$N69-'RESOLUCIONES EPG'!$D69 -> 4134
A70: ='RESOLUCIONES 2015'!A5923:H5923 | B70: 7520 | C70: 62 | D70: 42072 | E70: CESAR PANIAGUA CHACON | G70: ELEVAR EXPEDIENTE AL VRAC | H70: Docencia Universitaria | N70: =TODAY() -> 46206 | O70: ='RESOLUCIONES EPG'!$N70-'RESOLUCIONES EPG'!$D70 -> 4134
A71: ='RESOLUCIONES 2015'!A5933:H5933 | B71: 31702 | C71: 72 | D71: 42076 | E71: ROMAN HUGO MEDINA TAPIA | G71: INSCRIPCION DE TEMA DE TESIS | N71: =TODAY() -> 46206 | O71: ='RESOLUCIONES EPG'!$N71-'RESOLUCIONES EPG'!$D71 -> 4130
A72: ='RESOLUCIONES 2015'!A5926:H5926 | B72: 8732 | C72: 65 | D72: 42076 | E72: QUISPE LOVATON RANDI ABEL | F72: 014101604d | G72: NOMBRAMIENTO DE ASESOR | N72: =TODAY() -> 46206 | O72: ='RESOLUCIONES EPG'!$N72-'RESOLUCIONES EPG'!$D72 -> 4130
A73: ='RESOLUCIONES 2015'!A5932:H5932 | B73: 43574 | C73: 71 | D73: 42076 | E73: MARUJA NUÑEZ PACHECO | G73: INSCRIPCION DE TEMA DE TESIS | N73: =TODAY() -> 46206 | O73: ='RESOLUCIONES EPG'!$N73-'RESOLUCIONES EPG'!$D73 -> 4130
A74: ='RESOLUCIONES 2015'!A5927:H5927 | B74: 7943 | C74: 66 | D74: 42076 | E74: MARITA CECILIA GONZALEZ MORALES | F74: 014101472K | G74: NOMBRAMIENTO DE ASESOR | N74: =TODAY() -> 46206 | O74: ='RESOLUCIONES EPG'!$N74-'RESOLUCIONES EPG'!$D74 -> 4130
A75: ='RESOLUCIONES 2015'!A5928:H5928 | B75: 7851 | C75: 67 | D75: 42076 | E75: KATHERINE MONTESINOS VALDIVIA | G75: NOMBRAMIENTO DE ASESOR | N75: =TODAY() -> 46206 | O75: ='RESOLUCIONES EPG'!$N75-'RESOLUCIONES EPG'!$D75 -> 4130
A76: ='RESOLUCIONES 2015'!A5929:H5929 | B76: 8346 | C76: 68 | D76: 42076 | E76: HERNANDO GONZALES ABRILL | G76: ELEVAR EXPEDIENTE AL VRAC | H76: Docencia Universitaria | N76: =TODAY() -> 46206 | O76: ='RESOLUCIONES EPG'!$N76-'RESOLUCIONES EPG'!$D76 -> 4130
A77: ='RESOLUCIONES 2015'!A5931:H5931 | B77: 8653 | C77: 70 | D77: 42076 | E77: HENDERSON NOZART GIBAJA REYES | G77: DESIGNACION DE DICTAMINANTES | N77: =TODAY() -> 46206 | O77: ='RESOLUCIONES EPG'!$N77-'RESOLUCIONES EPG'!$D77 -> 4130
A78: ='RESOLUCIONES 2015'!A5930:H5930 | B78: 8283 | C78: 69 | D78: 42076 | E78: CESAR EDUARDO ESCALANTE | G78: DESIGNACION DE DICTAMINANTES | N78: =TODAY() -> 46206 | O78: ='RESOLUCIONES EPG'!$N78-'RESOLUCIONES EPG'!$D78 -> 4130
A79: ='RESOLUCIONES 2015'!A5934:H5934 | B79: 5160 | C79: 73 | D79: 42080 | E79: CANCAPA MALAGA AUGUSTA | G79: SUBSANACION | N79: =TODAY() -> 46206 | O79: ='RESOLUCIONES EPG'!$N79-'RESOLUCIONES EPG'!$D79 -> 4126
A80: ='RESOLUCIONES 2015'!A5935:H5935 | B80: 9127 | C80: 74 | D80: 42080 | E80: ANGEL MUÑOZ ARAGON | G80: DESIGNACION DE DICTAMINANTES | N80: =TODAY() -> 46206 | O80: ='RESOLUCIONES EPG'!$N80-'RESOLUCIONES EPG'!$D80 -> 4126
A81: ='RESOLUCIONES 2015'!A5936:H5936 | B81: 247 | C81: 75 | D81: 42080 | E81: ALY FELIZ LEON CHARCA | G81: RECONOCER LA CORRESPONDENCIA | N81: =TODAY() -> 46206 | O81: ='RESOLUCIONES EPG'!$N81-'RESOLUCIONES EPG'!$D81 -> 4126
A82: ='RESOLUCIONES 2015'!A5942:H5942 | B82: 9534 | C82: 81 | D82: 42081 | E82: VALENCIA MARTÍNEZ, CARLOS | G82: OTORGAMIENTO DE DIPLOMA | N82: =TODAY() -> 46206 | O82: ='RESOLUCIONES EPG'!$N82-'RESOLUCIONES EPG'!$D82 -> 4125
A83: ='RESOLUCIONES 2015'!A5943:H5943 | B83: 9779 | C83: 82 | D83: 42081 | E83: QUISPE ONOFRE, CARLOS | F83: Curso actualizacion | G83: DESIGNACION DE DICTAMINANTES | N83: =TODAY() -> 46206 | O83: ='RESOLUCIONES EPG'!$N83-'RESOLUCIONES EPG'!$D83 -> 4125
A84: ='RESOLUCIONES 2015'!A5945:H5945 | B84: 44016 | C84: 84 | D84: 42081 | E84: PLETICKOSICH PICÓN, ALEJANDRO | G84: CAMBIO DE DICTAMINANTE | N84: =TODAY() -> 46206 | O84: ='RESOLUCIONES EPG'!$N84-'RESOLUCIONES EPG'!$D84 -> 4125
A85: ='RESOLUCIONES 2015'!A5937:H5937 | B85: 34239 | C85: 76 | D85: 42081 | E85: ORMEÑO AYALA, SANDRA IRMA | G85: SUBSANACIÓN DE ASIGNATURA | N85: =TODAY() -> 46206 | O85: ='RESOLUCIONES EPG'!$N85-'RESOLUCIONES EPG'!$D85 -> 4125
A86: ='RESOLUCIONES 2015'!A5938:H5938 | B86: 9774 | C86: 77 | D86: 42081 | E86: ENCISO VIVANCO, GRACIELA MARICEL | G86: NOMBRAMIENTO DE ASESOR | N86: =TODAY() -> 46206 | O86: ='RESOLUCIONES EPG'!$N86-'RESOLUCIONES EPG'!$D86 -> 4125
A87: ='RESOLUCIONES 2015'!A5939:H5939 | B87: 9714 | C87: 78 | D87: 42081 | E87: CARRASCO GUZMÁN, HENRY | G87: NOMBRAMIENTO DE ASESOR | N87: =TODAY() -> 46206 | O87: ='RESOLUCIONES EPG'!$N87-'RESOLUCIONES EPG'!$D87 -> 4125
A88: ='RESOLUCIONES 2015'!A5940:H5940 | B88: 9622 | C88: 79 | D88: 42081 | E88: ARAGON RAMÍREZ, ENA EVELYN | G88: NOMBRAMIENTO DE ASESOR | N88: =TODAY() -> 46206 | O88: ='RESOLUCIONES EPG'!$N88-'RESOLUCIONES EPG'!$D88 -> 4125
A89: ='RESOLUCIONES 2015'!A5944:H5944 | B89: 9622 | C89: 83 | D89: 42081 | E89: ARAGON RAMÍREZ, ENA EVELYN | G89: DESIGNACION DE DICTAMINANTES | N89: =TODAY() -> 46206 | O89: ='RESOLUCIONES EPG'!$N89-'RESOLUCIONES EPG'!$D89 -> 4125
A90: ='RESOLUCIONES 2015'!A5946:H5946 | B90: 9952 | C90: 85 | D90: 42087 | E90: VALENCIA DELGADO, HÉCTOR RAÚL FERNANDO | G90: DESIGNACION DE DICTAMINANTES | N90: =TODAY() -> 46206 | O90: ='RESOLUCIONES EPG'!$N90-'RESOLUCIONES EPG'!$D90 -> 4119
A91: ='RESOLUCIONES 2015'!A5949:H5949 | B91: 10637 | C91: 88 | D91: 42087 | E91: LECHUGA RENGIFO, RAFAEL | G91: DESIGNACION DE DICTAMINANTES | N91: =TODAY() -> 46206 | O91: ='RESOLUCIONES EPG'!$N91-'RESOLUCIONES EPG'!$D91 -> 4119
A92: ='RESOLUCIONES 2015'!A5947:H5947 | B92: 8283 | C92: 86 | D92: 42087 | E92: ESCALANTE CÁRDENAS, CESAR EDUARDO | G92: CAMBIO DE DICTAMINANTE | N92: =TODAY() -> 46206 | O92: ='RESOLUCIONES EPG'!$N92-'RESOLUCIONES EPG'!$D92 -> 4119
A93: ='RESOLUCIONES 2015'!A5948:H5948 | B93: 10727 | C93: 87 | D93: 42087 | E93: CHAVEZ CAJIGAS, JORGE MANUEL | G93: NOMBRAM. DE ASESOR | N93: =TODAY() -> 46206 | O93: ='RESOLUCIONES EPG'!$N93-'RESOLUCIONES EPG'!$D93 -> 4119
A94: ='RESOLUCIONES 2015'!A5950:H5950 | B94: 10386 | C94: 89 | D94: 42087 | E94: CASILLAS LLERENA, PEDRO JESÚS | G94: AMPLIACIÓN PLAZO ENTREGA DE TESIS | N94: =TODAY() -> 46206 | O94: ='RESOLUCIONES EPG'!$N94-'RESOLUCIONES EPG'!$D94 -> 4119
A95: ='RESOLUCIONES 2015'!A5941:H5941 | B95: 10390 | C95: 80 | D95: 42087 | E95: AMPUERO GONZALES, CHRISTIAN OMAR | G95: AMPLIACIÓN DE PLAZO PARA SOLICITAR DICTAM. DE TESIS. | N95: =TODAY() -> 46206 | O95: ='RESOLUCIONES EPG'!$N95-'RESOLUCIONES EPG'!$D95 -> 4119
A96: ='RESOLUCIONES 2015'!A5951:H5951 | B96: 6407 | C96: 90 | D96: 42089 | E96: SALAS CALLO, ANTONIO | G96: CAMBIO DE DICTAMINANTE | N96: =TODAY() -> 46206 | O96: ='RESOLUCIONES EPG'!$N96-'RESOLUCIONES EPG'!$D96 -> 4117
A97: ='RESOLUCIONES 2015'!A5952:H5952 | B97: 10439 | C97: 91 | D97: 42089 | E97: CASFRANCA VILLACORTA NILTON | G97: DESIGNACION DE DICTAMINANTES | N97: =TODAY() -> 46206 | O97: ='RESOLUCIONES EPG'!$N97-'RESOLUCIONES EPG'!$D97 -> 4117
A98: ='RESOLUCIONES 2015'!A5953:H5953 | B98: 7076 | C98: 92 | D98: 42089 | E98: CANAHUIRE MONTUFAR, ABRHAM EDGARD | G98: APROB. E INSCRIP. PLAN TESIS EN REGISTRO | N98: =TODAY() -> 46206 | O98: ='RESOLUCIONES EPG'!$N98-'RESOLUCIONES EPG'!$D98 -> 4117
A99: ='RESOLUCIONES 2015'!A5954:H5954 | B99: 41942 | C99: 93 | D99: 42090 | E99: PUELLES FOLLANA, YISELA GIOVANA | G99: INSCRIP. DE PROYECTO TESIS EN REGISTRO | N99: =TODAY() -> 46206 | O99: ='RESOLUCIONES EPG'!$N99-'RESOLUCIONES EPG'!$D99 -> 4116
A100: ='RESOLUCIONES 2015'!A5957:H5957 | B100: 34239 | C100: 96 | D100: 42090 | E100: ORMEÑO AYALA, SANDRA IRMA | G100: SUBSANACIÓN DE ASIGNATURA(DERECHO MOBILIARIO) | N100: =TODAY() -> 46206 | O100: ='RESOLUCIONES EPG'!$N100-'RESOLUCIONES EPG'!$D100 -> 4116
A101: ='RESOLUCIONES 2015'!A5955:H5955 | B101: 11183 | C101: 94 | D101: 42090 | E101: LARICO LÓPEZ, ADA LIZBETH | G101: DICTAMEN DE TESIS | N101: =TODAY() -> 46206 | O101: ='RESOLUCIONES EPG'!$N101-'RESOLUCIONES EPG'!$D101 -> 4116
A102: ='RESOLUCIONES 2015'!A5956:H5956 | B102: 11028 | C102: 95 | D102: 42090 | E102: DE LOS RÍOS GUZMÁN, ABRAHAM | G102: DESIGNACION DE DICTAMINANTES | N102: =TODAY() -> 46206 | O102: ='RESOLUCIONES EPG'!$N102-'RESOLUCIONES EPG'!$D102 -> 4116
A103: ='RESOLUCIONES 2015'!A5965:H5965 | B103: 11677 | C103: 104 | D103: 42095 | E103: ROZAS FIGUEROA, WASKAR FRANK | G103: DESIGNACION DE DICTAMINANTES | N103: =TODAY() -> 46206 | O103: ='RESOLUCIONES EPG'!$N103-'RESOLUCIONES EPG'!$D103 -> 4111
A104: ='RESOLUCIONES 2015'!A5959:H5959 | B104: 11300 | C104: 98 | D104: 42095 | E104: RIVASPLATA BECERRA, HÉCTOR SALOMÓN | G104: DESIGNACION DE DICTAMINANTES | N104: =TODAY() -> 46206 | O104: ='RESOLUCIONES EPG'!$N104-'RESOLUCIONES EPG'!$D104 -> 4111
...

Sheet CONSEJO EPG 2025
A1: RESOLUCIONES EMITIDAS CONSEJO DE LA ESCUELA 2025
A2: N° SOLICITUD | B2: RESOL. N° | C2: FECHA | D2: NOMBRES Y APELLIDOS | E2: CODIGO2 | F2: TIPO DE RESOLUCION | G2: Observaciones | H2: RESOLUCION 2
B3: 1 | C3: 45931 | D3: APROBAR las Líneas de Investigación de la Escuela de Posgrado de la Universidad Andina del Cusco | F3: APROBAR las Líneas de Investigación
A4: Enviado | B4: 2 | C4: 45964 | D4: NINATAYPE MAMANI LADISLAO MAURICE | E4: 017200103K | F4: ELEVAR AL VRAC | G4: MAESTRO EN DOCENCIA UNIVERSITARIA
B5: 3
B6: 4 | C6: 45966 | D6: APROBAR el Formato 2: Instrumento de Evaluación de Planes Curriculares de la Escuela de Posgrado
B7: 5 | C7: 45966 | D7: APROBAR la Estructura del Plan Curricular para la Escuela de Posgrado
B8: 6 | C8: 45966 | D8: APROBAR el Perfil de Ingreso a la Escuela de Posgrado de la Universidad Andina del Cusco
B9: 7 | C9: 45966 | D9: APROBAR la implementación piloto del Procedimiento de Evaluación del Desempeño Académico Docente
B10: 8 | C10: 45967 | D10: ESTRADA PANTIA JOSÉ LUIS | E10: 019100007H | F10: ELEVAR AL VRAC | G10: DOCTOR EN CIENCIAS DE LA EDUCACIÓN
A11: Enviado | B11: 9 | C11: 45967 | D11: NEGRON CALVO LISARDO | E11: 45967 | F11: ELEVAR AL VRAC | G11: DOCTOR EN CIENCIAS DE LA EDUCACIÓN
A12: Enviado | B12: 10 | C12: 45967 | D12: MEJIA SURCO JAIME | E12: 018200216I | F12: ELEVAR AL VRAC | G12: MAESTRO EN DERECHO CIVIL Y COMERCIAL
A13: Enviado | B13: 11 | C13: 45967 | D13: VALENZUELA CARRASCO JUAN FRANKS | E13: 021200171J | F13: ELEVAR AL VRAC | G13: MAESTRO EN INGENIERÍA CIVIL CON MENCIÓN EN ESTRUCTURAS | H13: Falta sello
A14: Enviado | B14: 12 | C14: 45967 | D14: TORRE CALDERON EDGAR | E14: 018100026C | F14: ELEVAR AL VRAC | G14: MAESTRO EN DOCENCIA UNIVERSITARIA
A15: Enviado | B15: 13 | C15: 45967 | D15: CORNEJO ROJAS MILENKA | E15: 019300040I | F15: ELEVAR AL VRAC | G15: MAESTRO EN DOCENCIA UNIVERSITARIA
A16: Enviado | B16: 14 | C16: 45967 | D16: MUJICA SANCHEZ RAQUEL LIBERTAD | E16: 019200396F | F16: ELEVAR AL VRAC | G16: MAESTRO EN DOCENCIA UNIVERSITARIA
B17: 15 | C17: 45974 | D17: ESTRADA PANTIA JOSÉ LUIS | E17: 019100007H | F17: ELEVAR AL VRAC | G17: DOCTOR EN CIENCIAS DE LA EDUCACIÓN
A18: Enviado | B18: 16 | C18: 45974 | D18: CUELLAR RADO AMILCAR | E18: 019300009D | F18: ELEVAR AL VRAC | G18: MAESTRO EN DERECHO CONSTITUCIONAL
A19: Enviado | B19: 17 | C19: 45974 | D19: HOLGADO CARDENAS YENY FRANCY | E19: 021300009J | F19: ELEVAR AL VRAC | G19: MAESTRA EN ADMINISTRACIÓN DE NEGOCIOS
A20: Enviado | B20: 18 | C20: 45979 | D20: TTITO LAURA PRISCILIANO | E20: 015101443J | F20: ELEVAR AL VRAC | G20: MAESTRO EN CONTABILIDAD CON MENCIÓN EN AUDITORÍA Y CONTROL INTERNO
B21: 19 | C21: 45989 | D21: cambio de locación administrativa de la Escuela de Posgrado de la Universidad Andina del Cusco, desde la sede ubicada en Av. El Sol
B22: 20 | C22: 45989 | D22: APROBAR la Directiva N.° 001-2025-UAC-EPG | F22: “Implementación del Nuevo Sistema Académico Semestral de la Escuela de Posgrado”
B23: 21 | C23: 45989 | D23: Plantillas de Planes de Estudio para los programas de Maestría y Doctorado | F23: Plantillas de Planes de Estudio
A24: Enviado | B24: 22 | C24: 45994 | D24: CHOQUEVILCA LIRA WALTER FLORENCIO | E24: 015101538K | F24: ELEVAR AL VRAC | G24: DOCTOR EN MEDIO AMBIENTE Y DESARROLLO SOSTENIBLE.
A25: Enviado | B25: 23 | C25: 45994 | D25: CASTILLO ANCHARI LIBIA | E25: 020100005A | F25: ELEVAR AL VRAC | G25: DOCTORA EN CIENCIAS DE LA EDUCACIÓN
A26: Enviado | B26: 24 | C26: 45994 | D26: VARGAS GONZALES REIDY RENZO | E26: 019200213I | F26: ELEVAR AL VRAC | G26: DOCTOR EN CIENCIAS DE LA SALUD
A27: Enviado | B27: 25 | C27: 45994 | D27: PANOCCA MERMA CLAUDIO ZENOBIO | E27: 018100018K | F27: ELEVAR AL VRAC | G27: MAESTRO EN DOCENCIA UNIVERSITARIA
A28: Enviado | B28: 26 | C28: 45994 | D28: CHALCO SUAREZ JESSICA ELIZABETH | E28: 015101349C | F28: ELEVAR AL VRAC | G28: MAESTRA EN ESTADÍSTICA E INVESTIGACIÓN CIENTÍFICA
A29: Enviado | B29: 27 | C29: 45996 | D29: CONDORI PAUCCARA JOSE | E29: 022300033G | F29: ELEVAR AL VRAC | G29: DOCTOR EN CIENCIAS DE LA EDUCACIÓN.
A30: Enviado | B30: 28 | C30: 45996 | D30: VALENZUELA FARFAN RONNY | E30: 023200081I | F30: ELEVAR AL VRAC | G30: MAESTRO EN DOCENCIA UNIVERSITARIA.
A31: Enviado | B31: 29 | C31: 45996 | D31: CAMARENA QUISPE ROLANDO JOSE | E31: 021200033F | F31: ELEVAR AL VRAC | G31: DOCTOR EN DERECHO
B32: 30 | C32: 46002 | D32: 1ER PROGRAMA DE AUDITORÍA INTERNA DE LA ESCUELA DE POSGRADO – ISO 9001:2015
A33: Enviado | B33: 31 | C33: 46007 | D33: APROBAR la Misión y Visión de la Escuela de Posgrado | F33: ELEVAR AL VRAC
A34: Enviado | B34: 32 | C34: 46008 | D34: MANGO RAYME STEFANY BARBARA | E34: 023200065C | F34: ELEVAR AL VRAC | G34: MAESTRA EN DOCENCIA UNIVERSITARIA
B35: 33
B36: 34
B37: 35
B38: 36
B39: 37

Sheet CONSEJO EPG 2026
A1: RESOLUCIONES EMITIDAS CONSEJO DE LA ESCUELA 2025
A2: N° SOLICITUD | B2: RESOL. N° | C2: FECHA | D2: NOMBRES Y APELLIDOS | E2: CODIGO | F2: Observaciones | G2: TIPO DE RESOLUCION | H2: RESOLUCION 2
A3: Enviado | B3: -32 | C3: 46008 | D3: MANGO RAYME STEFANY BARBARA | E3: 023200065C | F3: MAESTRA EN DOCENCIA UNIVERSITARIA | G3: ELEVAR AL VRAC
A4: Enviado | B4: 1 | C4: 46076 | D4: MONGE NAVEROS YUDI | E4: 022300039E | F4: DOCTORA EN CIENCIAS DE LA EDUCACIÓN | G4: ELEVAR AL VRAC
A5: Enviado | B5: 2 | C5: 46076 | D5: CCARITA YUCRA JUVENAL JULIO | E5: 013200914B | F5: MAESTRO EN DERECHO CONSTITUCIONAL | G5: ELEVAR AL VRAC
A6: Enviado | B6: 3 | C6: 46076 | D6: APAZA DURAN ALAN JIMY | E6: 020300035A | F6: DOCTOR EN CIENCIAS DE LA SALUD | G6: ELEVAR AL VRAC
A7: Enviado | B7: 4 | C7: 46076 | D7: CARHUAS CUADROS TESSY | E7: 015101388I | F7: MAESTRA EN SEGURIDAD INDUSTRIAL Y MEDIO AMBIENTE | G7: ELEVAR AL VRAC
A8: Enviado | B8: 5 | C8: 46076 | D8: QUINTANILLA PALOMINO HARRY KEVIN | E8: 018300221D | F8: MAESTRO EN DERECHO CONSTITUCIONAL | G8: ELEVAR AL VRAC
A9: Enviado | B9: 6 | C9: 46076 | D9: TAIPE PILA DAMNA SHAREM | E9: 023200118J | F9: MAESTRA EN SEGURIDAD INDUSTRIAL Y MEDIO AMBIENTE | G9: ELEVAR AL VRAC
A10: Enviado | B10: 7 | C10: 46076 | D10: PALOMINO APARICIO DIANA | E10: 017200127G | F10: MAESTRA EN ADMINISTRACIÓN DE NEGOCIOS | G10: ELEVAR AL VRAC
A11: Enviado | B11: 8 | C11: 46076 | D11: GONZALES HUANCA NANCY | E11: 019200277G | F11: DOCTORA EN ADMINISTRACIÓN | G11: ELEVAR AL VRAC
A12: Enviado | B12: 9 | C12: 46076 | D12: SOTA PULIDO PILAR MARGOT | E12: 019200356D | F12: MAESTRA EN DOCENCIA UNIVERSITARIA | G12: ELEVAR AL VRAC
A13: Enviado | B13: 10 | C13: 46076 | D13: ROJAS BENAVIDES JIMENA ALONDRA | E13: 023200115K | F13: MAESTRA EN SEGURIDAD INDUSTRIAL Y MEDIO AMBIENTE | G13: ELEVAR AL VRAC
A14: Enviado | B14: 11 | C14: 46076 | D14: OLARTE MONTES NESTOR ABEL | E14: 013200949K | F14: MAESTRO EN DERECHO DEL TRABAJO Y DE LA SEGURIDAD SOCIAL | G14: ELEVAR AL VRAC
A15: Enviado | B15: 12 | C15: 46076 | D15: DE LOS RIOS GUZMAN ABRAHAM | E15: 014101616B | F15: MAESTRO EN SEGURIDAD INDUSTRIAL Y MEDIO AMBIENTE | G15: ELEVAR AL VRAC
B16: 13 | C16: 46078 | D16: reconformación del COMITÉ DE CALIDAD DE LA ESCUELA DE POSGRADO
B17: 14 | C17: 46078 | D17: Comité de Evaluación e Innovación Curricular de la EPG
B18: 15
B19: 16
B20: 17
B21: 18 | C21: 46111 | D21: LOAIZA VILCHEZ CINTIA LICETH | E21: 013201057F | F21: MAESTRA EN CIENCIAS ESTOMATOLÓGICAS | G21: ELEVAR AL VRAC
B22: 19 | C22: 46111 | D22: AGUILAR VELARDE LUIS ERNESTO | E22: 017200192C | F22: MAESTRO EN DERECHO REGISTRAL Y NOTARIAL | G22: ELEVAR AL VRAC
B23: 20 | C23: 46111 | D23: SERNAQUE FERNANDEZ PAULA BENANCIA | E23: 023200013C | F23: DOCTORA EN CIENCIAS DE LA EDUCACIÓN | G23: ELEVAR AL VRAC
B24: 21 | C24: 46111 | D24: GAMARRA MONTAÑEZ CARLOS ERNESTO | E24: 019100134J | F24: MAESTRO EN SEGURIDAD INDUSTRIAL Y MEDIO AMBIENTE. | G24: ELEVAR AL VRAC
B25: 22 | C25: 46111 | D25: LLACTA TOVAR SANDRA FAVIOLA | E25: 019300049F | F25: MAESTRA EN DOCENCIA UNIVERSITARIA | G25: ELEVAR AL VRAC
B26: 23 | C26: 46111 | D26: COSIO MUÑOZ JUAN | E26: 020300137I | F26: MAESTRO EN DERECHO CONSTITUCIONAL | G26: ELEVAR AL VRAC
B27: 24 | C27: 46111 | D27: FLOREZ RONDAN VERONIKA STEPHANIE | E27: 025102172H | F27: DOCTORA EN CIENCIAS DE LA SALUD | G27: ELEVAR AL VRAC
B28: 25 | C28: 46111 | D28: MOZO AYMA GABRIEL | E28: 013201094I | F28: DOCTOR EN CIENCIAS DE LA EDUCACIÓN | G28: ELEVAR AL VRAC
B29: 26 | C29: 46111 | D29: MENDOZA VALENZUELA JUBENAL | E29: 020300018J | F29: DOCTOR EN CIENCIAS DE LA EDUCACIÓN | G29: ELEVAR AL VRAC
B30: 27 | C30: 46111 | D30: ROMERO COPACONDORI FIORELA AYDE | E30: 019300166B | F30: MAESTRA EN ADMINISTRACIÓN DE NEGOCIOS | G30: ELEVAR AL VRAC
B31: 28 | C31: 46111 | D31: ALVES CHOQUE EDISON ALAN | E31: 018300039A | F31: DOCTORADO EN CIENCIAS DE LA EDUCACIÓN | G31: ELEVAR AL VRAC
B32: 29 | C32: 46111 | D32: YABAR HERMOZA GUSTAVO ENRIQUE | E32: 019100123H | F32: MAESTRÍA EN DERECHO CONSTITUCIONAL | G32: ELEVAR AL VRAC
... B48: 45 | C48: 46111 | D48: SOTO HERMOZA MIRIAN | E48: 019300072H | F48: MAESTRÍA EN DOCENCIA UNIVERSITARIA | G48: ELEVAR AL VRAC
B49: 46 | C49: 46111 | D49: APROBAR el 'PLAN DE ACTIVIDADES DE MEJORA CONTINUA (PAMC) SEMESTRE ACADÉMICO 2026-I'
B50: 47
B51: 48
B52: 49
B53: 50
B54: 51
B55: 52
B56: 53
B57: 54
B58: 55
B59: 56
B60: 57
B61: 58
B62: 59
A63: Enviado | B63: 60 | C63: 46155 | D63: ARTETA VALDIVIA MARIA DEL CARMEN | E63: 016102128J | F63: MAESTRA EN DERECHO CONSTITUCIONAL | G63: ELEVAR AL VRAC
A64: Enviado | B64: 61 | C64: 46168 | D64: MANCCO CHAUCCA NORMA | E64: 019200352I | F64: MAESTRÍA EN DOCENCIA UNIVERSITARIA | G64: ELEVAR AL VRAC
A65: Enviado | B65: 62 | C65: 46168 | D65: FERNANDEZ TOHALINO KARLA | E65: 017200060J | F65: DOCTORADO EN CIENCIAS DE LA SALUD | G65: ELEVAR AL VRAC
A66: Enviado | B66: 63 | C66: 46168 | D66: LARREA GARCIA CARLOS | E66: 022100047D | F66: MAESTRÍA EN DOCENCIA UNIVERSITARIA | G66: ELEVAR AL VRAC
A67: Enviado | B67: 64 | C67: 46168 | D67: BUSTAMANTE MAMANI JUDITH ROXANA | E67: 021200087I | F67: MAESTRÍA EN DERECHO REGISTRAL Y NOTARIAL | G67: ELEVAR AL VRAC
A68: Enviado | B68: 65 | C68: 46168 | D68: PALACIOS OJEDA DAVID RICARDO | E68: 021100076E | F68: MAESTRÍA EN DOCENCIA UNIVERSITARIA | G68: ELEVAR AL VRAC
A69: Enviado | B69: 66 | C69: 46168 | D69: TELLO RONCAL ANGELA SANDRA | E69: 015101483A | F69: MAESTRÍA EN DOCENCIA UNIVERSITARIA | G69: ELEVAR AL VRAC
A70: Enviado | B70: 67 | C70: 46168 | D70: BARRANTES YUCRA ANGEL | E70: 020100082F | F70: MAESTRÍA EN DOCENCIA UNIVERSITARIA | G70: ELEVAR AL VRAC
A71: Enviado | B71: 68 | C71: 46168 | D71: CARRASCO YARIN MAX LENING | E71: 016102316K | F71: DOCTORADO EN DERECHO | G71: ELEVAR AL VRAC
A72: Enviado | B72: 69 | C72: 46168 | D72: SENDON ALBA JORDAN JOFFRE | E72: 015301252C | F72: MAESTRÍA EN DERECHO CIVIL Y COMERCIAL | G72: ELEVAR AL VRAC
A73: Enviado | B73: 70 | C73: 46168 | D73: MALAGA YLLPA YASSER | E73: 025102187E | F73: DOCTORADO EN CONTABILIDAD | G73: ELEVAR AL VRAC
A74: Enviado | B74: 71 | C74: 46168 | D74: HUAYLLANE BACA ELIZABET | E74: 020300240D | F74: MAESTRÍA EN SEGURIDAD INDUSTRIAL Y MEDIO AMBIENTE | G74: ELEVAR AL VRAC
... A77: Enviado | B77: 74 | C77: 46168 | D77: SARCCO USTO ABEL | E77: 019200031H | F77: DOCTORADO EN MEDIO AMBIENTE Y DESARROLLO SOSTENIBLE | G77: ELEVAR AL VRAC
A78: Dejar sin efecto | B78: 75 | C78: 46168 | D78: CARRASCO YARIN MAX LENING | E78: 016102316K | F78: DOCTORADO EN DERECHO | G78: ELEVAR AL VRAC | H78: Se repite Resolución N°68
A79: Enviado | B79: 76 | C79: 46168 | D79: MENDOZA NINA RENATO HECTOR | E79: 019200144G | F79: DOCTORADO EN MEDIO AMBIENTE Y DESARROLLO SOSTENIBLE | G79: ELEVAR AL VRAC
A80: Enviado | B80: 77 | C80: 46168 | D80: VARGAS LUNA EDUARDO | E80: 017200046G | F80: DOCTORADO EN MEDIO AMBIENTE Y DESARROLLO SOSTENIBLE | G80: ELEVAR AL VRAC
A81: Enviado | B81: 78 | C81: 46168 | D81: MORON DAZA MAGALY SANDRA | E81: 019300058E | F81: MAESTRÍA EN DOCENCIA UNIVERSITARIA | G81: ELEVAR AL VRAC
A82: Enviado | B82: 79 | C82: 46175 | D82: GUZMAN MEDINA ADDERLY ROOSEVELT | E82: 019300125D | F82: MAESTRO EN DERECHO CIVIL Y COMERCIAL | G82: ELEVAR AL VRAC
A83: Enviado | B83: 80 | C83: 46175 | D83: CARDENAS ALCARRAZ GABRIEL | E83: 023300178D | F83: MAESTRO EN DOCENCIA UNIVERSITARIA | G83: ELEVAR AL VRAC
A84: Enviado | B84: 81 | C84: 46175 | D84: PARI PORTILLA ANDERSON JESUS | E84: 011270031D | F84: MAESTRO EN DOCENCIA UNIVERSITARIA | G84: ELEVAR AL VRAC
A85: Enviado | B85: 82 | C85: 46175 | D85: ALVAREZ ARIAS CELINDA | E85: 019200176F | F85: DOCTORA EN MEDIO AMBIENTE Y DESARROLLO SOSTENIBLE | G85: ELEVAR AL VRAC
B86: 83
B87: 84
B88: 85
B89: 86
B90: 87
B91: 88
B92: 89
B93: 90
B94: 91
B95: 92
B96: 93
A97: Enviado | B97: 94 | C97: 46192 | D97: VILLAVICENCIO SUNA PERCY MARCO | E97: 024101452H | F97: DOCTOR EN CIENCIAS DE LA EDUCACIÓN | G97: ELEVAR AL VRAC | J97: ELEVAR AL VRAC
A98: Enviado | B98: 95 | C98: 46192 | D98: VILLAVICENCIO OQUENDO IVANS PERCY | E98: 024101465B | F98: DOCTOR EN CIENCIAS DE LA SALUD | G98: ELEVAR AL VRAC | I98: 14 | J98: MAESTRÍAS
A99: Enviado | B99: 96 | C99: 46192 | D99: RIOS MAYORGA MARIO | E99: 023300012I | F99: DOCTOR EN ADMINISTRACIÓN | G99: ELEVAR AL VRAC | I99: 11 | J99: DOCTORADOS
B100: 97 | C100: 46195 | D100: Plan Curricular Enfoque por Competencias 2027 del programa de posgrado: DOCTORADO EN ADMISNISTRACIÓN – MODALIDAD PRESENCIAL | I100: 25 | J100: TOTAL
B101: 98 | C101: 46195 | D101: Plan Curricular Enfoque por Competencias 2027 del programa de posgrado: DOCTORADO EN CONTABILIDAD – MODALIDAD PRESENCIAL
B102: 99 | C102: 46195 | D102: Plan Curricular Enfoque por Competencias 2027 del programa de posgrado: DOCTORADO EN MEDIO AMBIENTE Y DESARROLLO SOSTENIBLE – MODALIDAD PRESENCIAL
B103: 100 | C103: 46195 | D103: Plan Curricular Enfoque por Competencias 2027 del programa de posgrado: DOCTORADO EN PSICOLOGÍA – MODALIDAD PRESENCIAL
B104: 101 | C104: 46195 | D104: Plan Curricular Enfoque por Competencias 2027 del programa de posgrado: DOCTORADO EN DERECHO – MODALIDAD PRESENCIAL
B105: 102 | C105: 46195 | D105: Plan Curricular Enfoque por Competencias 2027 del programa de posgrado: DOCTORADO EN CIENCIAS DE LA SALUD – MODALIDAD PRESENCIAL
B106: 103 | C106: 46195
B107: 104 | C107: 46195 | D107: Plan Curricular Enfoque por Competencias 2027 del programa de posgrado: DOCTORADO EN ADMISNISTRACIÓN – MODALIDAD SEMIPRESENCIAL
B108: 105 | C108: 46195 | D108: Plan Curricular Enfoque por Competencias 2027 del programa de posgrado: DOCTORADO EN CONTABILIDAD – MODALIDAD SEMIPRESENCIAL
B109: 106 | C109: 46195
B110: 107 | C110: 46195
B111: 108 | C111: 46195
B112: 109 | C112: 46195
B113: 110 | C113: 46195
B114: 111 | C114: 46195
B115: 112 | C115: 46195 | D115: Plan Curricular Enfoque por Competencias 2027 del programa de posgrado: DOCTORADO EN CONTABILIDAD – MODALIDAD A DISTANCIA
B116: 113 | C116: 46195
B117: 114 | C117: 46195 | D117: Plan Curricular Enfoque por Competencias 2027 del programa de posgrado: DOCTORADO EN PSICOLOGÍA – MODALIDAD A DISTANCIA
...

Sheet RESOLUCIONES 2026
A1: RESOLUCIONES EMITIDAS 2026 | J1: CARGOS
A2: N° SOLICITUD | B2: RESOL. N° | C2: FECHA | D2: NOMBRES Y APELLIDOS | E2: CODIGO2 | F2: TIPO DE RESOLUCION | G2: Observaciones | H2: RESOLUCION 2 | I2: Columna1 | J2: Programa | K2: DICTAMEN 2 | L2: CARGO 3 | M2: CARGO 4 | N2: CARGO 5 | O2: CARGO 6 | P2: Columna 1 | Q2: Columna 2 | R2: Columna 3 | S2: Columna 4
A3: Enviado | B3: 1 | C3: 46057 | D3: BUSTAMANTE QUISPE SUSAN KAREN | E3: 017300033D | F3: DICTAMEN DE PROYECTO DE TESIS
A4: Enviado | B4: 2 | C4: 46057 | D4: HUACAC MOSQUEIRA LAURA MILDRED | E4: 014101526C | F4: DICTAMEN DE PROYECTO DE TESIS | G4: PROYECTO ENVIADO MAL
A5: Enviado | B5: 3 | C5: 46057 | D5: GARCÍA CUSIHUALLPA RENATO | E5: 016102217B | F5: DICTAMEN DE PROYECTO DE TESIS
A6: Enviado | B6: 4 | C6: 46057 | D6: ESPINOZA CAÑARI HENRY EDWARD | E6: 014101617I | F6: DICTAMEN DE PROYECTO DE TESIS
A7: Enviado | B7: 5 | C7: 46057 | D7: MEJIA GALICIA WALTER | E7: 016102223B | F7: DICTAMEN DE PROYECTO DE TESIS
A8: Enviado | B8: 6 | C8: 46057 | D8: CARRION ABOLLANEDA RICHARD | E8: 019200338F | F8: INSCRIPCION DE PROYECTO | G8: DE FORMA
A9: Enviado | B9: 7 | C9: 46057 | D9: MAMANI APAZA IGNACIO | E9: 016102370E | F9: INSCRIPCION DE PROYECTO | G9: DE FORMA
A10: Enviado | B10: 8 | C10: 46057 | D10: TAIPE PARDO FREDY | E10: 018100075D | F10: INSCRIPCION DE PROYECTO | G10: DE FORMA
A11: Enviado | B11: 9 | C11: 46057 | D11: VIGURIA SALAZAR MICHAEL | E11: 020300228D | F11: INSCRIPCION DE PROYECTO | G11: DE FORMA
A12: Enviado | B12: 10 | C12: 46057 | D12: ACO CORRALES MARGOT MARITZA | E12: 018300043I | F12: INSCRIPCION DE PROYECTO | G12: ERROR MATERIAL
A13: Enviado | B13: 11 | C13: 46057 | D13: VENERO MORALES JORIEN | E13: 018100050A | F13: INSCRIPCION DE PROYECTO
A14: Enviado | B14: 12 | C14: 46057 | D14: CASTILLO CONTRERAS JESUSA | E14: 018100006B | F14: INSCRIPCION DE PROYECTO
A15: Enviado | B15: 13 | C15: 46057 | D15: CASTRO LOAYZA JAMILY SDENKA | E15: 013201043E | F15: INSCRIPCION DE PROYECTO
A16: Enviado | B16: 14 | C16: 46057 | D16: OLIVARES TAPIA YENY MARLENY | E16: 16201415G | F16: INSCRIPCION DE PROYECTO
A17: Enviado | B17: 15 | C17: 46057 | D17: TINEO TUEROS MIRELLA PAMELA | E17: 017200079B | F17: INSCRIPCION DE PROYECTO
A18: Enviado | B18: 16 | C18: 46057 | D18: PALOMINO OQUENDO WALTER VICENTE | E18: 012200959G | F18: DICTAMEN DE PROYECTO DE TESIS
A19: Enviado | B19: 17 | C19: 46069 | D19: HOLGUIN CURI MILUVSKA JHAKELINNE | E19: 024101486J | F19: DICTAMEN DE PROYECTO DE TESIS
A20: Enviado | B20: 18 | C20: 46069 | D20: BAÑON RAMOS LUCI VIRGINIA | E20: 023200050F | F20: DICTAMEN DE TESIS | G20: CAMBIO DE DICTAMINANTE
A21: Enviado | B21: 19 | C21: 46072 | D21: TRESIERRA PANTIGOZO ABEL | E21: 013201097H | F21: APTO AL GRADO
A22: Enviado | B22: 20 | C22: 46072 | D22: TEVES ARCCATA CIRILA MONICA | E22: 18300059B | F22: INSCRIPCION DE PROYECTO
A23: Enviado | B23: 21 | C23: 46072 | D23: BENITES FERNANDEZ GABRIEL JESUS | E23: 017300191I | F23: INSCRIPCION DE PROYECTO
A24: Enviado | B24: 22 | C24: 46072 | D24: SANTOS SALCEDO RICARDO ALVARO | E24: 019200223D | F24: DICTAMEN DE PROYECTO DE TESIS | G24: CAMBIO DE DICTAMINANTE
A25: Enviado | B25: 23 | C25: 46072 | D25: DURAN QUISPE LUZ BRENDA | E25: 019200310D | F25: DICTAMEN DE PROYECTO DE TESIS | G25: CAMBIO DE DICTAMINANTE
A26: Enviado | B26: 24 | C26: 46072 | D26: CCOA CHALLCO ELOY | E26: 015101348G | F26: DICTAMEN DE PROYECTO DE TESIS
A27: Enviado | B27: 25 | C27: 46072 | D27: ROJAS CESPEDES ROBERTO CARLOS | E27: 017200042A | F27: APTO AL GRADO
A28: Enviado | B28: 26 | C28: 46072 | D28: ARREDONDO GALLEGOS ROY ROGER | E28: 023300076G | F28: APTO AL GRADO
A29: Enviado | B29: 27 | C29: 46072 | D29: ROMERO QUISPE INGA FANNY CAROLINA | E29: 015201395G | F29: DICTAMEN DE PROYECTO DE TESIS
A30: Enviado | B30: 28 | C30: 46072 | D30: DELGADO MARTINEZ GISELY | E30: 018300003G | F30: DICTAMEN DE PROYECTO DE TESIS
A31: Enviado | B31: 29 | C31: 46072 | D31: CAHUASCANCO MONTALVO YHULDER ANTHONY | E31: 020300131k | F31: AMPLIACIÓN DE INSCRIPCIÓN
A32: Enviado | B32: 30 | C32: 46073 | D32: MENDOZA NINA RENATO HECTOR | E32: 019200144G | F32: FIJAR FECHA Y HORA | G32: 27 de febrero de 2026 a 16:00 | H32: Se envia observaciones de sustentacion
A33: Enviado | B33: 31 | C33: 46073 | D33: BARRANTES YUCRA ANGEL | E33: 020100082F | F33: FIJAR FECHA Y HORA | G33: 27 de febrero de 2026 a 18:00 | H33: Se envia observaciones de sustentacion
A34: Enviado | B34: 32 | C34: 46077 | D34: ROJAS VEGA CENTENO GABRIELA INGRID | E34: 023300199A | F34: APTO AL GRADO
B35: 33 | C35: 46077 | D35: JANQUI ESQUIVEL LEONIDAS | E35: 016102185C | F35: APTO AL GRADO | G35: Centro de Idiomas, sin DJ
B36: 34 | C36: 46077 | D36: NUÑEZ RAMIREZ ANGEL | E36: 014101531G | F36: APTO AL GRADO | G36: Centro de Idiomas
A37: Enviado | B37: 35 | C37: 46077 | D37: ALMANZA HUAYLLANI BRENDA XIMENA | E37: 023200016B | F37: APTO AL GRADO
A38: Enviado | B38: 36 | C38: 46077 | D38: FERNANDEZ BACA PAREJA ROMULO MIGUEL | E38: 016201395F | F38: APTO AL GRADO
A39: Enviado | B39: 37 | C39: 46077 | D39: SILVA BELTRAN EDUARDO | E39: 022100051A | F39: APTO AL GRADO
B40: 38 | C40: 46077 | D40: UMERES MENA EDWIN | E40: 015101560F | F40: APTO AL GRADO | G40: Centro de Idiomas
A41: Enviado | B41: 39 | C41: 46077 | D41: VARGAS TAKANA BRANDY JASMINE | E41: 020300121E | F41: APTO AL GRADO
A42: Enviado | B42: 40 | C42: 46077 | D42: FERNANDEZ SALCEDO JOSE LUIS | E42: 023200003H | F42: APTO AL GRADO
B43: 41 | C43: 46077 | D43: MENDOZA LOAYZA IVÁN | E43: 018100066E | F43: APTO AL GRADO | G43: Centro de Idiomas
B44: 42 | C44: 46077 | D44: PUMA HUILLCA CARMEN LUZ | E44: 019300190K | F44: APTO AL GRADO | G44: Centro de Idiomas
A45: Enviado | B45: 43 | C45: 46077 | D45: ASTETE CALDERON GABRIELA | E45: 017200113F | F45: APTO AL GRADO
A46: Enviado | B46: 44 | C46: 46077 | D46: HANCCO CCOPA MAURO | E46: 013201092F | F46: APTO AL GRADO
A47: Enviado | B47: 45 | C47: 46077 | D47: ZUNIGA QUISPE MALUBER | E47: 020200131I | F47: APTO AL GRADO
A48: Enviado | B48: 46 | C48: 46077 | D48: CHAMPI HUALLPA ALBERTO | E48: 018300107G | F48: APTO AL GRADO
A49: Enviado | B49: 47 | C49: 46077 | D49: TUPAYACHI MAR JUSTINO | E49: 019200371C | F49: APTO AL GRADO
A50: Enviado | B50: 48 | C50: 46077 | D50: ROJAS BUSTAMANTE SOFIA | E50: 014101566E | F50: APTO AL GRADO
A51: Enviado | B51: 49 | C51: 46077 | D51: HANCCO OROZ MARGARET GLADYS | E51: 013201005F | F51: APTO AL GRADO
A52: Enviado | B52: 50 | C52: 46077 | D52: CAMPOS DOMINGUEZ MARLENI | E52: 020300008D | F52: APTO AL GRADO
A53: Enviado | B53: 51 | C53: 46077 | D53: PALIZA PAIVA AUSI | E53: 019200420D | F53: APTO AL GRADO
A54: Enviado | B54: 52 | C54: 46077 | D54: VILLAVICENCIO SUNA PERCY MARCO | E54: 024101452H | F54: APTO AL GRADO
A55: Enviado | B55: 53 | C55: 46077 | D55: VILLAVICENCIO OQUENDO IVANS PERCY | E55: 024101465B | F55: APTO AL GRADO
A56: Enviado | B56: 54 | C56: 46077 | D56: GRANDEZ SEMINARIO CLARENCE ISRAEL ROBINSON | E56: 020200116J | F56: APTO AL GRADO
... A58: Enviado | B58: 56 | C58: 46077 | D58: GAMARRA VILLANUEVA WILFREDO | E58: 025102182C | F58: APTO AL GRADO
B59: 57 | C59: 46077 | D59: SOTO ENRIQUEZ MABELY KAREN | E59: 021200107J | F59: APTO AL GRADO | G59: Centro de Idiomas
A60: Enviado | B60: 58 | C60: 46077 | D60: CARRANZA PINEDO ULISES | E60: 020100004E | F60: APTO AL GRADO
A61: Enviado | B61: 59 | C61: 46077 | D61: NÚÑEZ MEDINA RUTH | E61: 017200015D | F61: APTO AL GRADO
A62: Enviado | B62: 60 | C62: 46077 | D62: FERNANDEZ TOHALINO KARLA | E62: 017200060J | F62: FIJAR FECHA Y HORA | G62: 03 de marzo de 2026 a 18:00 | H62: Se envia observaciones de sustentacion
A63: Enviado | B63: 61 | C63: 46077 | D63: MONTES PEDRAZA ROSA MARIA | E63: 019200262J | F63: FIJAR FECHA Y HORA | G63: 03 de marzo de 2026 a 16:00 | H63: Se envia observaciones de sustentacion
B64: 62
A65: Enviado | B65: 63 | C65: 46078 | D65: RIVAS RICALDE MENDEL EDER | E65: 023300198E | F65: CAMBIO NOMBRAMIENTO DE ASESOR | G65: Dra. YANINA ROJAS ANAYA
A66: Enviado | B66: 64 | C66: 46078 | D66: PEDRAZA RAMIREZ VICTOR SEBASTIAN | E66: 021300090A | F66: CAMBIO NOMBRAMIENTO DE ASESOR | G66: Mtro. ROMAN VILLEGAS EIGNER
A67: Enviado | B67: 65 | C67: 46079 | D67: MORALES MENDOZA SIDNEY RANDHI | E67: 019100046c | F67: CAMBIO DICTAMEN DE PROYECTO DE TESIS | G67: Dr. TAMAYO VARGAS CARLOS MAXIMO
A68: Enviado | B68: 66 | C68: 46080 | D68: QUIN GUERRA GERSON | E68: 019300114B | F68: NOMBRAMIENTO ASESOR | G68: Dr. BECERRA INFANTAS GUSTABO ADOLFO
A69: Enviado | B69: 67 | C69: 46083 | D69: ARREDONDO GALLEGOS ROY ROGER | E69: 023300076G | F69: DICTAMEN DE TESIS | G69: Dr. IVAN HERIK HERMOZA ROSELL | H69: Dr. EDWARDS JESÚS AGUIRRE ESPINOZA
A70: Enviado | B70: 68 | C70: 46080 | D70: HUILLCA CURSE TRINIDAD MONICA | E70: 020100014k | F70: CAMBIO DICTAMEN DE TESIS | G70: Dr. CHALCO FERNÁNDEZ JULIO CESAR
A71: Enviado | B71: 69 | C71: 46080 | D71: SENDON ALBA JORDAN JOFFRE | E71: 015301252C | F71: CAMBIO DICTAMEN DE TESIS | G71: Dra. CORONADO GAMARRA LILIANA
B72: 70 | C72: 46086 | D72: Ratificación y reconformación de los Comités de Evaluación e Innovación Curricular | F72: RECONFORMAR los Comités de Evaluación e Innovación Curricular (CEIC)
A73: Enviado | B73: 71 | C73: 46083 | D73: PUENTE DE LA VEGA OVIEDO RINA | E73: 020100021G | F73: NOMBRAMIENTO DE ASESOR | G73: Dr. SUÁREZ SÁNCHEZ RICHARD
B74: 72
A75: Enviado | B75: 73 | C75: 46083 | D75: CASTAÑEDA SORIA LUZBY JANET | E75: 020200002D | F75: NOMBRAMIENTO DE ASESOR | G75: Dr. HERNANDO GONZALES ABRILL
B76: 74 | C76: 46083 | D76: GIRALDO PASTOR YAJAYRA | E76: 015101294D | F76: NOMBRAMIENTO DE ASESOR | G76: Dra. CORONADO GAMARRA LILIANA | H76: resolución anterior vencio en enero de 2026
A77: Enviado | B77: 75 | C77: 46083 | D77: GARCIA ANDRADE KARLO FRANCISCO | E77: 025102093K | F77: NOMBRAMIENTO DE ASESOR | G77: Dr. MAMANI VARGAS ELVIS YURI
A78: Enviado | B78: 76 | C78: 46083 | D78: SALAS FORTON EDSON JULIO | E78: 025300011K | F78: NOMBRAMIENTO DE ASESOR | G78: Dr. CHACÓN SÁNCHEZ VICTOR
A79: Enviado | B79: 77 | C79: 46083 | D79: MONTALVO LOAIZA CLEVER ABELARDO | E79: 025102188A | F79: NOMBRAMIENTO DE ASESOR | G79: Dr. PÉREZ VILLAFUERTE RENNÉ WILFREDO
A80: Enviado | B80: 78 | C80: 46083 | D80: CALDERON PIMENTEL HAROLD ANDRE | E80: 025200257H | F80: NOMBRAMIENTO DE ASESOR | G80: Dra. PINARES PAYNE GABRIELA FERNANDA
A81: Enviado | B81: 79 | C81: 46083 | D81: HERRERA PFUYO CORNELIO | E81: 024200026G | F81: NOMBRAMIENTO DE ASESOR | G81: Dr. DIAZ TORRES JOSE HILDEBRANDO
A82: Enviado | B82: 80 | C82: 46083 | D82: CHAVEZ QUISPE SUSAN XIMENA | E82: 025300009F | F82: NOMBRAMIENTO DE ASESOR | G82: Dra. GARCES PORRAS KAREN MELISSA
A83: Enviado | B83: 81 | C83: 46083 | D83: LOAYZA ENCALADA DARWIN DUHAMEL | E83: 018200008G | F83: NOMBRAMIENTO DE ASESOR | G83: Dr. AGUIRRE ESPINOZA EDWARDS JESUS
A84: Enviado | B84: 82 | C84: 46083 | D84: HUILLCA ESQUIVEL ADAN | E84: 024300136I | F84: NOMBRAMIENTO DE ASESOR | G84: Mgt. POZO ROLDAN CLORINDA
A85: Enviado | B85: 83 | C85: 46083 | D85: YABAR OLARTE EDWAR STIP | E85: 020300071H | F85: NOMBRAMIENTO DE ASESOR | G85: Dra. MERCADO ESPEJO IVONNE
A86: Enviado | B86: 84 | C86: 46083 | D86: QUISPE CALDERÓN RICHARD MARX | E86: 024200029F | F86: NOMBRAMIENTO DE ASESOR | G86: Dr. ZÚÑIGA MARINO MIGUEL ÁNGEL
A87: Enviado | B87: 85 | C87: 46083 | D87: AUCAYLLE COLL ALEJANDRA VICTORIA | E87: 020300109E | F87: NOMBRAMIENTO DE ASESOR | G87: Mgt. CHOQUEHUANCA CONTRERAS TATIANA
A88: Enviado | B88: 86 | C88: 46083 | D88: BALLONA FLORES ELIZABETH | E88: 019200281D | F88: NOMBRAMIENTO DE ASESOR | G88: Dr. AGUIRRE ESPINOZA EDWARDS JESUS
... A98: Enviado | B98: 96 | C98: 46083 | D98: CCARITA YUCRA JUVENAL JULIO | E98: 020300052C | F98: NOMBRAMIENTO DE ASESOR | G98: Dr. WILLIAN QUISPE LAYME
A99: Enviado | B99: 97 | C99: 46083 | D99: PRADA CHUMBES SHEYLA KATHERINE | E99: 019100140J | F99: NOMBRAMIENTO DE ASESOR | G99: Mtro. CHUQUIMIA HURTADO ARTURO | H99: Programa equivocado
A100: Enviado | B100: 98 | C100: 46083 | D100: SOTA PULIDO PILAR MARGOT | E100: 021100013C | F100: NOMBRAMIENTO DE ASESOR | G100: Dr. MELENDREZ VELASCO ELIAS
A101: Enviado | B101: 99 | C101: 46083 | D101: MORALES GUTIERREZ ELODIA | E101: 025200080K | F101: NOMBRAMIENTO DE ASESOR | G101: Dr. RIVERA MUÑOZ JORGE LEONCIO
A102: Enviado | B102: 100 | C102: 46083 | D102: PALOMINO CARDENAS MERY | E102: 021100030E | F102: INSCRIPCION DE PROYECTO
A103: Enviado | B103: 101 | C103: 46083 | D103: LOAIZA VELARDE CHRISTIAM MARTIN | E103: 025102186I | F103: INSCRIPCION DE PROYECTO
A104: Enviado | B104: 102 | C104: 46083 | D104: DIAZ ANCCO FERNANDO | E104: 022300034C | F104: INSCRIPCION DE PROYECTO
A105: Enviado | B105: 103 | C105: 46083 | D105: QUISPE VERA GONZALO JOSUE | E105: 024300062E | F105: INSCRIPCION DE PROYECTO
A106: Enviado | B106: 104 | C106: 46083 | D106: CHAMPI HACHO DINA | E106: 023300146E | F106: INSCRIPCION DE PROYECTO
A107: Enviado | B107: 105 | C107: 46083 | D107: CATUNTA HUAMANI EFRAIN | E107: 21300041K | F107: INSCRIPCION DE PROYECTO
A108: Enviado | B108: 106 | C108: 46083 | D108: MARTINEZ TRUJILLO YOHNY LUZ | E108: 018100065I | F108: INSCRIPCION DE PROYECTO
A109: Enviado | B109: 107 | C109: 46083 | D109: TTUPA CARBAJAL ANABEL TATIANA | E109: 018200246E | F109: INSCRIPCION DE PROYECTO
A110: Enviado | B110: 108 | C110: 46083 | D110: CANDIA TORRES KELY | E110: 019200115G | F110: INSCRIPCION DE PROYECTO
...

Sheet RESOLUCIONES 2025
A1: RESOLUCIONES EMITIDAS 2025 | J1: CARGOS
A2: N° SOLICITUD | B2: RESOL. N° | C2: FECHA | D2: NOMBRES Y APELLIDOS | E2: CODIGO2 | F2: TIPO DE RESOLUCION | G2: Observaciones | H2: RESOLUCION 2 | I2: Columna1 | J2: Programa | K2: DICTAMEN 2 | L2: CARGO 3 | M2: CARGO 4 | N2: CARGO 5 | O2: CARGO 6
B3: =ROW() - ROW('RESOLUCIONES 2025'!$B$2) - 44 -> -43 | C3: 45659 | D3: CCORIMANYA USCA ERIKA ELIZABETH | E3: 024101530I | F3: AUTORIZAR matrícula de curso pendiente
B4: =ROW() - ROW('RESOLUCIONES 2025'!$B$2) - 44 -> -42 | C4: 45659 | D4: JORDAN ZEGARRA RAIKO | E4: 023300114F | F4: AUTORIZAR matrícula de curso pendiente | K4: pro
B5: =ROW() - ROW('RESOLUCIONES 2025'!$B$2) - 44 -> -41 | C5: 45666 | D5: CHRISTIAN JOHNSON CARRASCO AHEN | E5: 025102132F | F5: CONVALIDACION
B6: =ROW() - ROW('RESOLUCIONES 2025'!$B$2) - 44 -> -40 | C6: 45666 | D6: CORDOVA CUSI ALEXANDER ULICES | E6: 025102134i | F6: CONVALIDACION
B7: =ROW() - ROW('RESOLUCIONES 2025'!$B$2) - 44 -> -39 | C7: 45666 | D7: SAENZ PERALTA MARCO ANTONIO | E7: 025102144D | F7: CONVALIDACION
B8: =ROW() - ROW('RESOLUCIONES 2025'!$B$2) - 44 -> -38 | C8: 45666 | D8: DIAZ HUILLCA ISAAC | E8: 025102135e | F8: CONVALIDACION
B9: =ROW() - ROW('RESOLUCIONES 2025'!$B$2) - 44 -> -37 | C9: 45666 | D9: HUALLPA CATUNTA EDILBERTO | E9: 025102136a | F9: CONVALIDACION
B10: =ROW() - ROW('RESOLUCIONES 2025'!$B$2) - 44 -> -36 | C10: 45666 | D10: HUAYLLANI VEGA EDGAR CIRILO | E10: 025102137H | F10: CONVALIDACION
B11: =ROW() - ROW('RESOLUCIONES 2025'!$B$2) - 44 -> -35 | C11: 45666 | D11: QUISPE INFANTES REYNALDO RICARDO | E11: 025102142A | F11: CONVALIDACION
B12: =ROW() - ROW('RESOLUCIONES 2025'!$B$2) - 44 -> -34 | C12: 45666 | D12: SERRANO TRUJILLO NALDA | E12: 025102146g | F12: CONVALIDACION
B13: =ROW() - ROW('RESOLUCIONES 2025'!$B$2) - 44 -> -33 | C13: 45666 | D13: OJEDA ORTEGA ESMERALDA MARIA | E13: 025102140I | F13: CONVALIDACION
B14: =ROW() - ROW('RESOLUCIONES 2025'!$B$2) - 44 -> -32 | C14: 45666 | D14: SÁNCHEZ CÓRDOVA MARIELA | E14: 025102145K | F14: CONVALIDACION
B15: =ROW() - ROW('RESOLUCIONES 2025'!$B$2) - 44 -> -31 | C15: 45666 | D15: VARGAS USCAMAYTA RINA | E15: 025102147C | F15: CONVALIDACION
B16: =ROW() - ROW('RESOLUCIONES 2025'!$B$2) - 44 -> -30 | C16: 45666 | D16: PANDIA YAÑEZ EDWARD JIMMY | E16: 025102190f | F16: CONVALIDACION
... B64: =ROW() - ROW('RESOLUCIONES 2025'!$B$2) - 44 -> 18 | C64: 45677 | D64: CASTILLO ARROSQUIPA GIOVANA | E64: 025102133B | F64: DECLARAR SIN EFECTO
B65: =ROW() - ROW('RESOLUCIONES 2025'!$B$2) - 44 -> 19 | C65: 45678 | D65: HERMOZA APAZA JUAN DIEGO | F65: RECTIFICACIÓN DEL PROMEDIO DE NOTAS | G65: TUPAYACHI SOTOMAYOR JHONNY
B66: =ROW() - ROW('RESOLUCIONES 2025'!$B$2) - 44 -> 20 | C66: 45678 | D66: LIRA APAZA VICTOR RAUL | F66: RECTIFICACIÓN DEL PROMEDIO DE NOTAS | G66: TUPAYACHI SOTOMAYOR JHONNY
B67: =ROW() - ROW('RESOLUCIONES 2025'!$B$2) - 44 -> 21 | C67: 45678 | D67: MELENDEZ PORTAL MARITZA NAYELI | F67: RECTIFICACIÓN DEL PROMEDIO DE NOTAS | G67: TUPAYACHI SOTOMAYOR JHONNY
B68: =ROW() - ROW('RESOLUCIONES 2025'!$B$2) - 44 -> 22 | C68: 45677 | D68: NINA RAMOS EDWIN RIDER | E68: 025101944G | F68: CONVALIDACION
B69: =ROW() - ROW('RESOLUCIONES 2025'!$B$2) - 44 -> 23 | C69: 45677 | D69: GIOVANA CASTILLO ARROSQUIPA | E69: 025102133B | F69: CONVALIDACION
B70: =ROW() - ROW('RESOLUCIONES 2025'!$B$2) - 44 -> 24 | C70: 45677 | D70: GALDOS BERRIO ILBERTO | E70: 025101927E | F70: CONVALIDACION
B71: =ROW() - ROW('RESOLUCIONES 2025'!$B$2) - 44 -> 25 | C71: 45684 | D71: MONTESINOS PALOMINO ARTEMIO | E71: 025102189H | F71: CONVALIDACION
B72: =ROW() - ROW('RESOLUCIONES 2025'!$B$2) - 44 -> 26 | C72: 45684 | D72: RUEDA VERA KATHERING DELFINA | E72: 025102143H | F72: CONVALIDACION
B73: =ROW() - ROW('RESOLUCIONES 2025'!$B$2) - 44 -> 27 | C73: 45684 | D73: PEREYRA SANCHEZ VILMA | E73: 025102141E | F73: CONVALIDACION
B74: =ROW() - ROW('RESOLUCIONES 2025'!$B$2) - 44 -> 28 | C74: 45684 | D74: MONTESINOS PALOMINO ARTEMIO | E74: 025102189H | F74: DEJAR SIN EFECTO RESOLUCIÓN N°00672025/EPG-UAC
B75: =ROW() - ROW('RESOLUCIONES 2025'!$B$2) - 44 -> 29 | C75: 45691 | D75: PARICOTO GARCIA ROXANA | E75: 018200042K | F75: DICTAMEN DE PROYECTO DE TESIS
B76: =ROW() - ROW('RESOLUCIONES 2025'!$B$2) - 44 -> 30 | C76: 45691 | D76: CASTAÑEDA AVENDAÑO OSCAR | E76: 019300035E | F76: DICTAMEN DE PROYECTO DE TESIS
B77: =ROW() - ROW('RESOLUCIONES 2025'!$B$2) - 44 -> 31 | C77: 45691 | D77: BAÑON RAMOS LUCI VIRGINIA | E77: 023200050F | F77: DICTAMEN DE PROYECTO DE TESIS
B78: =ROW() - ROW('RESOLUCIONES 2025'!$B$2) - 44 -> 32 | C78: 45691 | D78: LICONA ARIZABAL CESAR ROLANDO | E78: 015101274C | F78: DICTAMEN DE PROYECTO DE TESIS
B79: =ROW() - ROW('RESOLUCIONES 2025'!$B$2) - 44 -> 33 | C79: 45691 | D79: CUELLAR RADO AMILCAR | E79: 019300009D | F79: DICTAMEN DE PROYECTO DE TESIS
... B88: =ROW() - ROW('RESOLUCIONES 2025'!$B$2) - 44 -> 42 | C88: 45691 | D88: VALER CONTRERAS AIDA | E88: 022100019K | F88: APTO AL GRADO
B89: =ROW() - ROW('RESOLUCIONES 2025'!$B$2) - 44 -> 43 | C89: 45691 | D89: NUÑEZ DEL PRADO COLL ENRIQUE | E89: 020300083F | F89: NOMBRAMIENTO ASESOR | G89: CHACON SANCHEZ VICTOR
B90: =ROW() - ROW('RESOLUCIONES 2025'!$B$2) - 44 -> 44 | C90: 45691 | D90: MASIAS FIGUEROA ROXANA | E90: 018200037G | F90: NOMBRAMIENTO ASESOR | G90: GARETH DEL CASTILLO ESTRADA
B91: =ROW() - ROW('RESOLUCIONES 2025'!$B$2) - 44 -> 45 | C91: 45691 | D91: PEÑA ROSAS SILME | E91: 017300075I | F91: NOMBRAMIENTO ASESOR | G91: BERTOLT FERNANDO OCROS GUEVARA
B92: =ROW() - ROW('RESOLUCIONES 2025'!$B$2) - 44 -> 46 | C92: 45691 | D92: TTUPA CARBAJAL ANABEL TATIANA | E92: 018200246E | F92: NOMBRAMIENTO ASESOR | G92: BERTOLT FERNANDO OCROS GUEVARA
B93: =ROW() - ROW('RESOLUCIONES 2025'!$B$2) - 44 -> 47 | C93: 45691 | D93: VALENCIA GARCIA JULIO CESAR | E93: 017200081G | F93: NOMBRAMIENTO ASESOR | G93: LUIS ALBERTO CHIHUANTITO ABAL
B94: =ROW() - ROW('RESOLUCIONES 2025'!$B$2) - 44 -> 48 | C94: 45691 | D94: VARGAS ESPINOZA SONIA ENEIDA | E94: 018200027A | F94: NOMBRAMIENTO ASESOR | G94: Teodoro Huarhua Chipani
B95: =ROW() - ROW('RESOLUCIONES 2025'!$B$2) - 44 -> 49 | C95: 45691 | D95: MERINO OBESO GLENDA | E95: 023300118A | F95: NOMBRAMIENTO ASESOR | G95: ISAAC ENRIQUE CASTRO CUBA BARINEZA
B96: =ROW() - ROW('RESOLUCIONES 2025'!$B$2) - 44 -> 50 | C96: 45691 | D96: SALAZAR GARATE LISSET KATIUSCA | E96: 023300123E | F96: NOMBRAMIENTO ASESOR | G96: PINARES PAYNE GABRIELA FERNANDA
B97: =ROW() - ROW('RESOLUCIONES 2025'!$B$2) - 44 -> 51 | C97: 45691 | D97: PAYNE MORA ESPERANZA SOLEDAD | E97: 024200081H | F97: NOMBRAMIENTO ASESOR | G97: PAULA PATRICIA LUKSIC GIBAJA
B98: =ROW() - ROW('RESOLUCIONES 2025'!$B$2) - 44 -> 52 | C98: 45691 | D98: MAMANI CONDORI VILMA FELICITAS | E98: 019100012A | F98: NOMBRAMIENTO ASESOR | G98: EDWARDS JESUS AGUIRRE ESPINOZA
B99: =ROW() - ROW('RESOLUCIONES 2025'!$B$2) - 44 -> 53 | C99: 45691 | D99: LOPEZ CASAVERDE DIEGO DANIEL | E99: 023300192G | F99: NOMBRAMIENTO ASESOR | G99: JORGE LEONCIO RIVERA MUÑOZ
B100: =ROW() - ROW('RESOLUCIONES 2025'!$B$2) - 44 -> 54 | C100: 45691 | D100: MERMA PALACIOS RUTH | E100: 020300060F | F100: NOMBRAMIENTO ASESOR | G100: ISAAC ENRIQUE CASTRO CUBA BARINEZA
... B110: =ROW() - ROW('RESOLUCIONES 2025'!$B$2) - 44 -> 64 | C110: 45691 | D110: PINTO ESPINOZA NOHELY VANESSA | E110: 019200052E | F110: NOMBRAMIENTO ASESOR | G110: JUAN ANTONIO BECERRA ROMERO
B111: =ROW() - ROW('RESOLUCIONES 2025'!$B$2) - 44 -> 65 | C111: 45691 | D111: JAYO SILVA CARLOS EDUARDO | E111: 017200035E | F111: DICTAMEN DE PROYECTO DE TESIS
B112: =ROW() - ROW('RESOLUCIONES 2025'!$B$2) - 44 -> 66 | C112: 45691 | D112: CORIMANYA PARICAHUA MIRKO | E112: 021300022F | F112: DICTAMEN DE PROYECTO DE TESIS
B113: =ROW() - ROW('RESOLUCIONES 2025'!$B$2) - 44 -> 67 | C113: 45691 | D113: DE LA QUINTANA SOLIS JORGE LUIS | E113: 021300118C | F113: DICTAMEN DE PROYECTO DE TESIS
B114: =ROW() - ROW('RESOLUCIONES 2025'!$B$2) - 44 -> 68 | C114: 45691 | D114: ESPINOZA VILCA ISABEL | E114: 023300132D | F114: DICTAMEN DE PROYECTO DE TESIS
B115: =ROW() - ROW('RESOLUCIONES 2025'!$B$2) - 44 -> 69 | C115: 45691 | D115: MALAGA YLLPA YASSER | E115: 023300065E | F115: DICTAMEN DE PROYECTO DE TESIS
B116: =ROW() - ROW('RESOLUCIONES 2025'!$B$2) - 44 -> 70 | C116: 45691 | D116: LATORRE MOLINEDO LILIAN SUMMER | E116: 019200150G | F116: DICTAMEN DE PROYECTO DE TESIS
B117: =ROW() - ROW('RESOLUCIONES 2025'!$B$2) - 44 -> 71
B118: =ROW() - ROW('RESOLUCIONES 2025'!$B$2) - 44 -> 72
B119: =ROW() - ROW('RESOLUCIONES 2025'!$B$2) - 44 -> 73
B120: =ROW() - ROW('RESOLUCIONES 2025'!$B$2) - 44 -> 74
B121: =ROW() - ROW('RESOLUCIONES 2025'!$B$2) - 44 -> 75
B122: =ROW() - ROW('RESOLUCIONES 2025'!$B$2) - 44 -> 76
B123: =ROW() - ROW('RESOLUCIONES 2025'!$B$2) - 44 -> 77
B124: =ROW() - ROW('RESOLUCIONES 2025'!$B$2) - 44 -> 78
B125: =ROW() - ROW('RESOLUCIONES 2025'!$B$2) - 44 -> 79
B126: =ROW() - ROW('RESOLUCIONES 2025'!$B$2) - 44 -> 80
B127: =ROW() - ROW('RESOLUCIONES 2025'!$B$2) - 44 -> 81
B128: =ROW() - ROW('RESOLUCIONES 2025'!$B$2) - 44 -> 82
... B136: =ROW() - ROW('RESOLUCIONES 2025'!$B$2) - 44 -> 90
A137: Enviado | B137: =ROW() - ROW('RESOLUCIONES 2025'!$B$2) - 44 -> 91 | C137: 45691 | D137: CUEVA CHAVEZ ELSA | E137: 019200361H | F137: INSCRIPCION DE PROYECTO DE TESIS
A138: Enviado | B138: =ROW() - ROW('RESOLUCIONES 2025'!$B$2) - 44 -> 92 | C138: 45691 | D138: DE LOS RIOS GUZMAN ABRAHAM | E138: 014101616B | F138: INSCRIPCION DE PROYECTO DE TESIS
A139: Enviado | B139: =ROW() - ROW('RESOLUCIONES 2025'!$B$2) - 44 -> 93 | C139: 45691 | D139: ESPEJO ABARCA KAROLA | E139: 018200033A | F139: INSCRIPCION DE PROYECTO DE TESIS
A140: Enviado | B140: =ROW() - ROW('RESOLUCIONES 2025'!$B$2) - 44 -> 94 | C140: 45691 | D140: ROMAN OCHOA SHELANY NAYDE | E140: 018300120C | F140: INSCRIPCION DE PROYECTO DE TESIS
A141: Enviado | B141: =ROW() - ROW('RESOLUCIONES 2025'!$B$2) - 44 -> 95 | C141: 45691 | D141: ANCHARI OBLITAS YULIZA FRANCESCA | E141: 020300034E | F141: INSCRIPCION DE PROYECTO DE TESIS
A142: Enviado | B142: =ROW() - ROW('RESOLUCIONES 2025'!$B$2) - 44 -> 96 | C142: 45691 | D142: MORON DAZA MAGALY SANDRA | E142: 019300058E | F142: INSCRIPCION DE PROYECTO DE TESIS
A143: Enviado | B143: =ROW() - ROW('RESOLUCIONES 2025'!$B$2) - 44 -> 97 | C143: 45691 | D143: OQUENDO CARREÑO PERCY | E143: 021200141C | F143: APTO AL GRADO
A144: Enviado | B144: =ROW() - ROW('RESOLUCIONES 2025'!$B$2) - 44 -> 98 | C144: 45691 | D144: NAVARRO CUSIHUALLPA ELENA | E144: 018300085C | F144: APTO AL GRADO
A145: Enviado | B145: =ROW() - ROW('RESOLUCIONES 2025'!$B$2) - 44 -> 99 | C145: 45691 | D145: VILCAHUAMÁN MEJÍA RICHARD HÉCTOR | E145: 017200134C | F145: APTO AL GRADO
A146: Enviado | B146: =ROW() - ROW('RESOLUCIONES 2025'!$B$2) - 44 -> 100 | C146: 45691 | D146: LLALLA HUAYCHU MARIELA | E146: 016102161G | F146: APTO AL GRADO
A147: Enviado | B147: =ROW() - ROW('RESOLUCIONES 2025'!$B$2) - 44 -> 101 | C147: 45691 | D147: YLLANES CORAHUA EDWIN | E147: 019300169A | F147: APTO AL GRADO
A148: Enviado | B148: =ROW() - ROW('RESOLUCIONES 2025'!$B$2) - 44 -> 102 | C148: 45691 | D148: CORDOVA CUELLAR VANESSA | E148: 019200125B | F148: APTO AL GRADO
A149: Enviado | B149: =ROW() - ROW('RESOLUCIONES 2025'!$B$2) - 44 -> 103 | C149: 45691 | D149: VERA MUÑOZ ESTEFANY LORENA | E149: 020300199D | F149: ELEVAR AL VRAC | G149: MAESTRA EN DOCENCIA UNIVERSITARIA
A150: Enviado | B150: =ROW() - ROW('RESOLUCIONES 2025'!$B$2) - 44 -> 104 | C150: 45692 | D150: VALVERDE MAMANI GRECIA | E150: 019200321F | F150: DICTAMEN DE TESIS | I150: Dr. Edward Anibal Morante Ríos | J150: Dr. PANDO DIAZ WALDO ALEX
A151: Enviado | B151: =ROW() - ROW('RESOLUCIONES 2025'!$B$2) - 44 -> 105 | C151: 45692 | D151: GUZMAN MEDINA ADDERLY ROOSEVELT | E151: 019300125D | F151: DICTAMEN DE TESIS | I151: Mg. CHUQUIMIA HURTADO JOSE | J151: Mg. CAMPANA ZEGARRA SILVIO OSWALDO
A152: Docente Galvan tiene el correo inactivo | B152: =ROW() - ROW('RESOLUCIONES 2025'!$B$2) - 44 -> 106 | C152: 45692 | D152: ZAVALA CACERES ESTER MARIBEL | E152: 020300032B | F152: DICTAMEN DE TESIS | J152: Dra. LUKSIC GIBAJA PAULA PATRICIA
A153: Docente Mg. DELGADO CAMACHO ALEJANDRO VLADIMIR YA NO LABORA EN LA UAC | B153: =ROW() - ROW('RESOLUCIONES 2025'!$B$2) - 44 -> 107 | C153: 45692 | D153: PALOMINO APARICIO DIANA | E153: 017200127G | F153: DICTAMEN DE TESIS | J153: Mg. Ana Cecilia Chávez Chacón
A154: Enviado | B154: =ROW() - ROW('RESOLUCIONES 2025'!$B$2) - 44 -> 108 | C154: 45692 | D154: VELA AREVALO VERONICA | E154: 015101340F | F154: DICTAMEN DE TESIS | I154: Dr. CASTRO CUBA BARINEZA ISAAC ENRIQUE | J154: Dr. ACO CORRALES EDER ARTURO
B155: =ROW() - ROW('RESOLUCIONES 2025'!$B$2) - 44 -> 109 | C155: 45692
B156: =ROW() - ROW('RESOLUCIONES 2025'!$B$2) - 44 -> 110 | C156: 45692
A157: Enviado | B157: =ROW() - ROW('RESOLUCIONES 2025'!$B$2) - 44 -> 111 | C157: 45692 | D157: GAMARRA MONTAÑÉZ CARLOS ERNESTO | E157: 019100134J | F157: APTO AL GRADO
A158: Enviado | B158: =ROW() - ROW('RESOLUCIONES 2025'!$B$2) - 44 -> 112 | C158: 45692 | D158: FELIX FLORES WARNER HANS | E158: 016102095D | F158: APTO AL GRADO
A159: Enviado | B159: =ROW() - ROW('RESOLUCIONES 2025'!$B$2) - 44 -> 113 | C159: 45692 | D159: PALIZA TORRES KARINA LILIANA | E159: 017200246F | F159: APTO AL GRADO
A160: Enviado | B160: =ROW() - ROW('RESOLUCIONES 2025'!$B$2) - 44 -> 114 | C160: 45692 | D160: ENCISO QUISPE CAROLAY FRINETH | E160: 024101443I | F160: NOMBRAMIENTO ASESOR | G160: TELLO YARIN EDDY
A161: Enviado | B161: =ROW() - ROW('RESOLUCIONES 2025'!$B$2) - 44 -> 115 | C161: 45692 | D161: TEJADA AZURIN ANA | E161: 024101450E | F161: NOMBRAMIENTO ASESOR | G161: TELLO YARIN EDDY
A162: Enviado | B162: =ROW() - ROW('RESOLUCIONES 2025'!$B$2) - 44 -> 116 | C162: 45692 | D162: ZUÑIGA CONDORI CAROLINA | E162: 024101454K | F162: NOMBRAMIENTO ASESOR | G162: TELLO YARIN EDDY
A163: Enviado | B163: =ROW() - ROW('RESOLUCIONES 2025'!$B$2) - 44 -> 117 | C163: 45692 | D163: QUISPE QUEZADA LUTHGARDO PASTOR | E163: 020200036F | F163: NOMBRAMIENTO ASESOR | G163: COSIO DUEÑAS, HERBERT
A164: Enviado | B164: =ROW() - ROW('RESOLUCIONES 2025'!$B$2) - 44 -> 118 | C164: 45692 | D164: BARRIENTOS PALOMINO JESSICA GUADALUPE | E164: 024200070F | F164: NOMBRAMIENTO ASESOR | G164: Miluska Frisancho Camero
A165: Enviado | B165: =ROW() - ROW('RESOLUCIONES 2025'!$B$2) - 44 -> 119 | C165: 45692 | D165: CUSIHUAMAN HUAYCHO CELIA | E165: 021200045D | F165: NOMBRAMIENTO ASESOR | G165: Patricia Paredes Valverde
A166: Enviado | B166: =ROW() - ROW('RESOLUCIONES 2025'!$B$2) - 44 -> 120 | C166: 45692 | D166: ARAMBURÚ NAVEDA LENA | E166: 018100052D | F166: DICTAMEN DE PROYECTO DE TESIS | I166: Dra. SHAILI JULIE CAVERO PACHECO | J166: Dra. ALFARO AUCCA CRAYLA
A167: Anulado | B167: =ROW() - ROW('RESOLUCIONES 2025'!$B$2) - 44 -> 121 | C167: 45692 | D167: VEGA CENTENO VILLENA JOSE HUMBERTO | E167: 023300139I | F167: DICTAMEN DE PROYECTO DE TESIS
A168: Anulado | B168: =ROW() - ROW('RESOLUCIONES 2025'!$B$2) - 44 -> 122 | C168: 45692 | D168: LEON BUSTOS OLDRAN BRIZARD | E168: 023200094C | F168: DICTAMEN DE PROYECTO DE TESIS
A169: Enviado | B169: =ROW() - ROW('RESOLUCIONES 2025'!$B$2) - 44 -> 123 | C169: 45692 | D169: TORRES MAMANI WASHINGTON | E169: 023200078H | F169: DICTAMEN DE PROYECTO DE TESIS | I169: Dr. EDWARDS JESUS AGUIRRE ESPINOZA | J169: Dra.PAULA PATRICIA LUKSIC GIBAJA
A170: Enviado | B170: =ROW() - ROW('RESOLUCIONES 2025'!$B$2) - 44 -> 124 | C170: 45692 | D170: CARLOTTO OCAMPO PATRICIA | E170: 025102203K | F170: DICTAMEN DE PROYECTO DE TESIS | I170: PHD ISAAC E. CASTRO CUBA BARINEZA | J170: Dr. VALENCIA VILA JOSE LUIS
A171: Enviado | B171: =ROW() - ROW('RESOLUCIONES 2025'!$B$2) - 44 -> 125 | C171: 45692 | D171: MIRANDA ABARCA KELLY | E171: 021200183H | F171: DICTAMEN DE PROYECTO DE TESIS | I171: Dra. SHAILI JULIE CAVERO PACHECO | J171: Mtro. ARTURO CHUQUMIA HURTADO
...

Sheet RESOLUCIONES 2024
A1: RESOLUCIONES EMITIDAS 2024 | J1: CARGOS
A2: N° SOLICITUD | B2: RESOL. N° | C2: FECHA | D2: NOMBRES Y APELLIDOS | E2: CODIGO2 | F2: TIPO DE RESOLUCION | G2: Obaservaciones | H2: RESOLUCION 2 | I2: Columna1 | J2: HOY | K2: Excede 730 Dias2 | L2: CARGO 3 | M2: CARGO 4 | N2: CARGO 5 | O2: CARGO 6
A3: Enviado | B3: 1 | C3: 45294 | D3: GARCIA CUEVA MIHAIL FERDINAN | E3: 018200004A | F3: INSCRIPCION DE PROYECTO DE TESIS | J3: =TODAY() -> 46206 | K3: ='RESOLUCIONES 2024'!$C3-'RESOLUCIONES 2024'!$J3 -> -912
A4: Enviado | B4: 2 | C4: 45294 | D4: HUILLCA BACA MAURA FANY | E4: 015101433D | F4: INSCRIPCION DE PROYECTO DE TESIS | J4: =TODAY() -> 46206 | K4: ='RESOLUCIONES 2024'!$C4-'RESOLUCIONES 2024'!$J4 -> -912
A5: Enviado | B5: 3 | C5: 45294 | D5: MOZO AYMA GABRIEL | E5: 013201094I | F5: INSCRIPCION DE PROYECTO DE TESIS | J5: =TODAY() -> 46206 | K5: ='RESOLUCIONES 2024'!$C5-'RESOLUCIONES 2024'!$J5 -> -912
A6: Enviado | B6: 4 | C6: 45294 | D6: TAPIA DELGADO BHELU | E6: 017200078F | F6: INSCRIPCION DE PROYECTO DE TESIS | J6: =TODAY() -> 46206 | K6: ='RESOLUCIONES 2024'!$C6-'RESOLUCIONES 2024'!$J6 -> -912
A7: Enviado | B7: 5 | C7: 45295 | D7: TORRES QUISPE EILEEN | E7: 015101484H | F7: INSCRIPCION DE PROYECTO DE TESIS | J7: =TODAY() -> 46206 | K7: ='RESOLUCIONES 2024'!$C7-'RESOLUCIONES 2024'!$J7 -> -911
A8: Enviado | B8: 6 | C8: 45295 | D8: GUZMAN MEDINA ADDERLY ROOSEVELT | E8: 019300125D | F8: INSCRIPCION DE PROYECTO DE TESIS | J8: =TODAY() -> 46206 | K8: ='RESOLUCIONES 2024'!$C8-'RESOLUCIONES 2024'!$J8 -> -911
B9: 7 | C9: 45295 | D9: XV CURSO DE ACTUALIZACIÓN | F9: relación de estudiantes admitidos en el XV CURSO DEACTUALIZACIÓN | J9: =TODAY() -> 46206 | K9: ='RESOLUCIONES 2024'!$C9-'RESOLUCIONES 2024'!$J9 -> -911
A10: Enviado | B10: 8 | C10: 45301 | D10: ALVAREZ ARIAS CELINDA | E10: 019200176F | F10: NOMBRAMIENTO DE ASESOR | G10: AGUIRRE ESPINOZA EDWARDS JESUS | J10: =TODAY() -> 46206 | K10: ='RESOLUCIONES 2024'!$C10-'RESOLUCIONES 2024'!$J10 -> -905
A11: Enviado | B11: 9 | C11: 45301 | D11: ARIZACA CUSICUNA JORGE LUIS | E11: 019100026B | F11: NOMBRAMIENTO DE ASESOR | G11: MORANTE RIOS EDWARD ANIBAL | J11: =TODAY() -> 46206 | K11: ='RESOLUCIONES 2024'!$C11-'RESOLUCIONES 2024'!$J11 -> -905
A12: Enviado | B12: 10 | C12: 45301 | D12: RODRIGUEZ CÁRDENAS FREDDY | E12: 017200310F | F12: NOMBRAMIENTO DE ASESOR | G12: GONZALES CONDORI HARRY YEISON | J12: =TODAY() -> 46206 | K12: ='RESOLUCIONES 2024'!$C12-'RESOLUCIONES 2024'!$J12 -> -905
A13: Enviado | B13: 11 | C13: 45301 | D13: CABALLERO ALEGRIA FLOR MARITZA | E13: 020300130D | F13: NOMBRAMIENTO DE ASESOR | G13: ACO CORRALES EDER ARTURO | J13: =TODAY() -> 46206 | K13: ='RESOLUCIONES 2024'!$C13-'RESOLUCIONES 2024'!$J13 -> -905
A14: Enviado | B14: 12 | C14: 45301 | D14: MEZA FERNANDEZ SANDRA | E14: 018300146B | F14: NOMBRAMIENTO DE ASESOR | G14: ESTRADA SANCHEZ PAOLA | J14: =TODAY() -> 46206 | K14: ='RESOLUCIONES 2024'!$C14-'RESOLUCIONES 2024'!$J14 -> -905
A15: Enviado | B15: 13 | C15: 45301 | D15: ARIAS REINOSO MADELEINE | E15: 020300108I | F15: NOMBRAMIENTO DE ASESOR | G15: ESTRADA SANCHEZ PAOLA | J15: =TODAY() -> 46206 | K15: ='RESOLUCIONES 2024'!$C15-'RESOLUCIONES 2024'!$J15 -> -905
A16: Enviado | B16: 14 | C16: 45301 | D16: FLORES PALOMINO ADRIANA PAOLA | E16: 016102242G | F16: NOMBRAMIENTO DE ASESOR | G16: GONZALES CONDORI HARRY YEISON | J16: =TODAY() -> 46206 | K16: ='RESOLUCIONES 2024'!$C16-'RESOLUCIONES 2024'!$J16 -> -905
A17: Enviado | B17: 15 | C17: 45301 | D17: LLANOS MAMANI JUAN EVER | E17: 018300142G | F17: NOMBRAMIENTO DE ASESOR | G17: DE LA TORRE DUEÑAS CLETO | J17: =TODAY() -> 46206 | K17: ='RESOLUCIONES 2024'!$C17-'RESOLUCIONES 2024'!$J17 -> -905
A18: Enviado | B18: 16 | C18: 45301 | D18: FELIX FLORES WARNER HANS | E18: 016102095D | F18: NOMBRAMIENTO DE ASESOR | G18: DELGADO CAMACHO ALEJANDRO VLADIMIR | J18: =TODAY() -> 46206 | K18: ='RESOLUCIONES 2024'!$C18-'RESOLUCIONES 2024'!$J18 -> -905
A19: Enviado | B19: 17 | C19: 45301 | D19: FERREL SARMIENTO DIOMEDES NAPOLEON | E19: 019200256J | F19: NOMBRAMIENTO DE ASESOR | G19: AGUIRRE ESPINOZA EDWARDS JESUS | J19: =TODAY() -> 46206 | K19: ='RESOLUCIONES 2024'!$C19-'RESOLUCIONES 2024'!$J19 -> -905
A20: Enviado | B20: 18 | C20: 45301 | D20: BARRIENTOS ALVAREZ ELENA ROSA | E20: 019200127E | F20: NOMBRAMIENTO DE ASESOR | G20: ORTIZ DIAZ RENZO GUILLERMO | J20: =TODAY() -> 46206 | K20: ='RESOLUCIONES 2024'!$C20-'RESOLUCIONES 2024'!$J20 -> -905
A21: Enviado | B21: 19 | C21: 45301 | D21: AGUILAR CHACON LISBETH BERENICE | E21: 020100030F | F21: NOMBRAMIENTO DE ASESOR | G21: ESTRADA SANCHEZ PAOLA | J21: =TODAY() -> 46206 | K21: ='RESOLUCIONES 2024'!$C21-'RESOLUCIONES 2024'!$J21 -> -905
... A68: Enviado | B68: 66 | C68: 45309 | D68: FLOREZ OTAZU KARINA FIORELLA | E68: 019200190I | F68: NOMBRAMIENTO DE ASESOR | G68: JAYO SILVA CARLOS EDUARDO | J68: =TODAY() -> 46206 | K68: ='RESOLUCIONES 2024'!$C68-'RESOLUCIONES 2024'!$J68 -> -897
A69: Enviado | B69: 67 | C69: 45309 | D69: VILCAHUAMÁN MEJÍA RICHARD HÉCTOR | E69: 017200134C | F69: INSCRIPCION DE PROYECTO DE TESIS | J69: =TODAY() -> 46206 | K69: ='RESOLUCIONES 2024'!$C69-'RESOLUCIONES 2024'!$J69 -> -897
A70: Enviado | B70: 68 | C70: 45309 | D70: SERNAQUE FERNANDEZ PAULA BENANCIA | E70: 023200013C | F70: NOMBRAMIENTO DE ASESOR | G70: AGUIRRE ESPINOZA EDWARDS JESUS | J70: =TODAY() -> 46206 | K70: ='RESOLUCIONES 2024'!$C70-'RESOLUCIONES 2024'!$J70 -> -897
A71: Enviado | B71: 69 | C71: 45309 | D71: ORMACHEA MEJIA MARIO JESUS | E71: 023200007C | F71: NOMBRAMIENTO DE ASESOR | G71: MELENDREZ VELASCO ELIAS | J71: =TODAY() -> 46206 | K71: ='RESOLUCIONES 2024'!$C71-'RESOLUCIONES 2024'!$J71 -> -897
A72: Enviado | B72: 70 | C72: 45310 | D72: MONTES PEDRAZA ROSA MARIA | E72: 019200262J | F72: INSCRIPCION DE PROYECTO DE TESIS | J72: =TODAY() -> 46206 | K72: ='RESOLUCIONES 2024'!$C72-'RESOLUCIONES 2024'!$J72 -> -896
A73: Enviado | B73: 71 | C73: 45316 | D73: MENDOZA LOAYZA IVAN | E73: 018100066E | F73: NOMBRAMIENTO DE ASESOR | G73: MORANTE RIOS EDWARD ANIBAL | J73: =TODAY() -> 46206 | K73: ='RESOLUCIONES 2024'!$C73-'RESOLUCIONES 2024'!$J73 -> -890
A74: Enviado | B74: 72 | C74: 45316 | D74: LICONA ARIZABAL CESAR ROLANDO | E74: 015101274C | F74: NOMBRAMIENTO DE ASESOR | G74: ALVIZ PAZOS SUSI | J74: =TODAY() -> 46206 | K74: ='RESOLUCIONES 2024'!$C74-'RESOLUCIONES 2024'!$J74 -> -890
A75: Enviado | B75: 73 | C75: 45316 | D75: FERNANDEZ SALCEDO JOSE LUIS | E75: 023200003H | F75: NOMBRAMIENTO DE ASESOR | G75: AGUIRRE ESPINOZA EDWARDS JESUS | J75: =TODAY() -> 46206 | K75: ='RESOLUCIONES 2024'!$C75-'RESOLUCIONES 2024'!$J75 -> -890
A76: Enviado | B76: 74 | C76: 45316 | D76: LASTEROS HOLGADO YOHN AUGUSTO | E76: 023200006G | F76: NOMBRAMIENTO DE ASESOR | G76: AGUIRRE ESPINOZA EDWARDS JESUS | J76: =TODAY() -> 46206 | K76: ='RESOLUCIONES 2024'!$C76-'RESOLUCIONES 2024'!$J76 -> -890
A77: Enviado | B77: 75 | C77: 45316 | D77: QUISPE CHOQQUE CESAR AUGUSTO | E77: 023200009F | F77: NOMBRAMIENTO DE ASESOR | G77: AGUIRRE ESPINOZA EDWARDS JESUS | J77: =TODAY() -> 46206 | K77: ='RESOLUCIONES 2024'!$C77-'RESOLUCIONES 2024'!$J77 -> -890
A78: Enviado | B78: 76 | C78: 45316 | D78: RAMOS CANDIA EUSTAQUIO | E78: 023200010D | F78: NOMBRAMIENTO DE ASESOR | G78: AGUIRRE ESPINOZA EDWARDS JESUS | J78: =TODAY() -> 46206 | K78: ='RESOLUCIONES 2024'!$C78-'RESOLUCIONES 2024'!$J78 -> -890
A79: Enviado | B79: 77 | C79: 45316 | D79: HERMOZA GRANADINO GIOVANNA GIANINA | E79: 015101272K | F79: NOMBRAMIENTO DE ASESOR | G79: ALVIZ PAZOS SUSI | J79: =TODAY() -> 46206 | K79: ='RESOLUCIONES 2024'!$C79-'RESOLUCIONES 2024'!$J79 -> -890
A80: Enviado | B80: 78 | C80: 45316 | D80: CAHUASCANCO MONTALVO YHULDER ANTHONY | E80: 020300131K | F80: INSCRIPCION DE PROYECTO DE TESIS | J80: =TODAY() -> 46206 | K80: ='RESOLUCIONES 2024'!$C80-'RESOLUCIONES 2024'!$J80 -> -890
A81: Enviado | B81: 79 | C81: 45316 | D81: GARCIA ALATRISTA FABIOLA PILAR | E81: 022300049K | F81: DEJAR SIN EFECTO | J81: =TODAY() -> 46206 | K81: ='RESOLUCIONES 2024'!$C81-'RESOLUCIONES 2024'!$J81 -> -890
A82: Enviado | B82: 80 | C82: 45323 | D82: HUMPIRE CASTRO ROY ANDY | E82: 022300007F | F82: DICTAMEN DE PROYECTO DE TESIS | J82: =TODAY() -> 46206 | K82: ='RESOLUCIONES 2024'!$C82-'RESOLUCIONES 2024'!$J82 -> -883
A83: Enviado | B83: 81 | C83: 45323 | D83: ACHAHUANCO CACERES OMAR GERMAIN | E83: 018200281E | F83: DICTAMEN DE PROYECTO DE TESIS | J83: =TODAY() -> 46206 | K83: ='RESOLUCIONES 2024'!$C83-'RESOLUCIONES 2024'!$J83 -> -883
A84: Enviado | B84: 82 | C84: 45323 | D84: ROMERO COPACONDORI FIORELA AYDE | E84: 019300166B | F84: DICTAMEN DE PROYECTO DE TESIS | J84: =TODAY() -> 46206 | K84: ='RESOLUCIONES 2024'!$C84-'RESOLUCIONES 2024'!$J84 -> -883
A85: Enviado | B85: 83 | C85: 45323 | D85: RODRIGUEZ GONZALES KELLY | E85: 022300044I | F85: DICTAMEN DE PROYECTO DE TESIS | J85: =TODAY() -> 46206 | K85: ='RESOLUCIONES 2024'!$C85-'RESOLUCIONES 2024'!$J85 -> -883
A86: Enviado | B86: 84 | C86: 45323 | D86: FUENTES BERNEDO FRIDA ESMERALDA | E86: 022300036F | F86: DICTAMEN DE PROYECTO DE TESIS | J86: =TODAY() -> 46206 | K86: ='RESOLUCIONES 2024'!$C86-'RESOLUCIONES 2024'!$J86 -> -883
A87: Enviado | B87: 85 | C87: 45323 | D87: PEREYRA NINA EDWIN | E87: 014101625A | F87: DICTAMEN DE PROYECTO DE TESIS | J87: =TODAY() -> 46206 | K87: ='RESOLUCIONES 2024'!$C87-'RESOLUCIONES 2024'!$J87 -> -883
A88: Enviado | B88: 86 | C88: 45323 | D88: SALAZAR COBOS TINA KAREN | E88: 018300149A | F88: NOMBRAMIENTO DE ASESOR | G88: QUISPE RAMOS ESTELA | J88: =TODAY() -> 46206 | K88: ='RESOLUCIONES 2024'!$C88-'RESOLUCIONES 2024'!$J88 -> -883
A89: Enviado | B89: 87 | C89: 45323 | D89: ROMERO VARGAS YANET | E89: 015101372E | F89: NOMBRAMIENTO DE ASESOR | G89: COLQUE CANDIA WILBERT | J89: =TODAY() -> 46206 | K89: ='RESOLUCIONES 2024'!$C89-'RESOLUCIONES 2024'!$J89 -> -883
A90: Enviado | B90: 88 | C90: 45323 | D90: GARATE FLORES NILDA TERESA | E90: 017200121I | F90: DICTAMEN DE PROYECTO DE TESIS | J90: =TODAY() -> 46206 | K90: ='RESOLUCIONES 2024'!$C90-'RESOLUCIONES 2024'!$J90 -> -883
A91: Enviado | B91: 89 | C91: 45324 | D91: HUILLCA GARCIA WILBER | E91: 022300038I | F91: DICTAMEN DE PROYECTO DE TESIS | J91: =TODAY() -> 46206 | K91: ='RESOLUCIONES 2024'!$C91-'RESOLUCIONES 2024'!$J91 -> -882
A92: Enviado | B92: 90 | C92: 45324 | D92: SAIRE PUMA HUGO | E92: 022300045E | F92: DICTAMEN DE PROYECTO DE TESIS | J92: =TODAY() -> 46206 | K92: ='RESOLUCIONES 2024'!$C92-'RESOLUCIONES 2024'!$J92 -> -882
A93: Enviado | B93: 91 | C93: 45324 | D93: CHAVEZ BERMUDEZ MABEL IÑAKAPALLA | E93: 022300032K | F93: DICTAMEN DE PROYECTO DE TESIS | J93: =TODAY() -> 46206 | K93: ='RESOLUCIONES 2024'!$C93-'RESOLUCIONES 2024'!$J93 -> -882
A94: Enviado | B94: 92 | C94: 45324 | D94: TELLO TORRES LIZBETT | E94: 022100018D | F94: DICTAMEN DE PROYECTO DE TESIS | J94: =TODAY() -> 46206 | K94: ='RESOLUCIONES 2024'!$C94-'RESOLUCIONES 2024'!$J94 -> -882
A95: Enviado | B95: 93 | C95: 45324 | D95: RODRIGUEZ CASAVERDE AMELIA | E95: 022300043B | F95: DICTAMEN DE PROYECTO DE TESIS | J95: =TODAY() -> 46206 | K95: ='RESOLUCIONES 2024'!$C95-'RESOLUCIONES 2024'!$J95 -> -882
A96: Enviado | B96: 94 | C96: 45324 | D96: PIZARRO PILLCO ELVER | E96: 022300040C | F96: DICTAMEN DE PROYECTO DE TESIS | J96: =TODAY() -> 46206 | K96: ='RESOLUCIONES 2024'!$C96-'RESOLUCIONES 2024'!$J96 -> -882
A97: Enviado | B97: 95 | C97: 45324 | D97: MONGE NAVEROS YUDI | E97: 022300039E | F97: DICTAMEN DE PROYECTO DE TESIS | J97: =TODAY() -> 46206 | K97: ='RESOLUCIONES 2024'!$C97-'RESOLUCIONES 2024'!$J97 -> -882
A98: Enviado | B98: 96 | C98: 45324 | D98: SALAZAR SEGOVIA RUBEN | E98: 019300069G | F98: DICTAMEN DE PROYECTO DE TESIS | J98: =TODAY() -> 46206 | K98: ='RESOLUCIONES 2024'!$C98-'RESOLUCIONES 2024'!$J98 -> -882
A99: Enviado | B99: 97 | C99: 45324 | D99: TERRAZAS DAVILA MILAGRITOS | E99: 018300088B | F99: DICTAMEN DE PROYECTO DE TESIS | J99: =TODAY() -> 46206 | K99: ='RESOLUCIONES 2024'!$C99-'RESOLUCIONES 2024'!$J99 -> -882
A100: Enviado | B100: 98 | C100: 45324 | D100: VERA DIAZ CRISTINA | E100: 021100086K | F100: DICTAMEN DE PROYECTO DE TESIS | J100: =TODAY() -> 46206 | K100: ='RESOLUCIONES 2024'!$C100-'RESOLUCIONES 2024'!$J100 -> -882
A101: Enviado | B101: 99 | C101: 45324 | D101: MANGO RAYME STEFANY BARBARA | E101: 023200065C | F101: DICTAMEN DE PROYECTO DE TESIS | J101: =TODAY() -> 46206 | K101: ='RESOLUCIONES 2024'!$C101-'RESOLUCIONES 2024'!$J101 -> -882
A102: Enviado | B102: 100 | C102: 45324 | D102: CABALLERO ALEGRIA FLOR MARITZA | E102: 020300130D | F102: NOMBRAMIENTO DE ASESOR | G102: BRAVO MELGAR SIDNEY ALEX | J102: =TODAY() -> 46206 | K102: ='RESOLUCIONES 2024'!$C102-'RESOLUCIONES 2024'!$J102 -> -882
A103: Enviado | B103: 101 | C103: 45324 | D103: LAURA GRANDA DULMIS MARIA | E103: 019200266E | F103: DICTAMEN DE TESIS | J103: =TODAY() -> 46206 | K103: ='RESOLUCIONES 2024'!$C103-'RESOLUCIONES 2024'!$J103 -> -882
A104: Enviado | B104: 102 | C104: 45324 | D104: CALLAPIÑA QUISPE LIZ PILAR | E104: 016102384F | F104: NOMBRAMIENTO DE ASESOR | G104: DE LA TORRE DUEÑAS CLETO | J104: =TODAY() -> 46206 | K104: ='RESOLUCIONES 2024'!$C104-'RESOLUCIONES 2024'!$J104 -> -882
A105: Enviado | B105: 103 | C105: 45324 | D105: FARFAN RODRIGUEZ JESSIKA | E105: 013201121F | F105: DICTAMEN DE TESIS | J105: =TODAY() -> 46206 | K105: ='RESOLUCIONES 2024'!$C105-'RESOLUCIONES 2024'!$J105 -> -882
A106: Enviado | B106: 104 | C106: 45324 | D106: VILLENA ASCUE PAUL | E106: 021200194J | F106: DICTAMEN DE TESIS | J106: =TODAY() -> 46206 | K106: ='RESOLUCIONES 2024'!$C106-'RESOLUCIONES 2024'!$J106 -> -882
A107: Enviado | B107: 105 | C107: 45324 | D107: OLIVERA OJEDA KELLY | E107: 013201017D | F107: DICTAMEN DE TESIS | J107: =TODAY() -> 46206 | K107: ='RESOLUCIONES 2024'!$C107-'RESOLUCIONES 2024'!$J107 -> -882
A108: Enviado | B108: 106 | C108: 45324 | D108: GARCES PORRAS KAREN MELISSA | E108: 018200003E | F108: DICTAMEN DE TESIS | J108: =TODAY() -> 46206 | K108: ='RESOLUCIONES 2024'!$C108-'RESOLUCIONES 2024'!$J108 -> -882
A109: Enviado | B109: 107 | C109: 45327 | D109: MAXDEO QUISPE WILFREDO | E109: 015101332C | F109: APTO AL GRADO | J109: =TODAY() -> 46206 | K109: ='RESOLUCIONES 2024'!$C109-'RESOLUCIONES 2024'!$J109 -> -879
A110: Enviado | B110: 108 | C110: 45327 | D110: SALAS BENDEZU MARIA DEL CARMEN | E110: 021200106C | F110: APTO AL GRADO | J110: =TODAY() -> 46206 | K110: ='RESOLUCIONES 2024'!$C110-'RESOLUCIONES 2024'!$J110 -> -879
A111: Enviado | B111: 109 | C111: 45327 | D111: SARMIENTO LUNA SABINO | E111: 020300086E | F111: APTO AL GRADO | J111: =TODAY() -> 46206 | K111: ='RESOLUCIONES 2024'!$C111-'RESOLUCIONES 2024'!$J111 -> -879
A112: Enviado | B112: 110 | C112: 45327 | D112: GUERRA POLANCO GERSON GABRIEL | E112: 019300012E | F112: APTO AL GRADO | J112: =TODAY() -> 46206 | K112: ='RESOLUCIONES 2024'!$C112-'RESOLUCIONES 2024'!$J112 -> -879
A113: Enviado | B113: 111 | C113: 45327 | D113: ACHAHUANCO ACHAHUI GORKI EDUARDO | E113: 014101487H | F113: APTO AL GRADO | J113: =TODAY() -> 46206 | K113: ='RESOLUCIONES 2024'!$C113-'RESOLUCIONES 2024'!$J113 -> -879
A114: Enviado | B114: 112 | C114: 45327 | D114: DELGADO LUNA ANGELA PATRICIA | E114: 016102133C | F114: APTO AL GRADO | J114: =TODAY() -> 46206 | K114: ='RESOLUCIONES 2024'!$C114-'RESOLUCIONES 2024'!$J114 -> -879
A115: Enviado | B115: 113 | C115: 45327 | D115: PALACIOS PILARES KATHERINE | E115: 016102165B | F115: APTO AL GRADO | J115: =TODAY() -> 46206 | K115: ='RESOLUCIONES 2024'!$C115-'RESOLUCIONES 2024'!$J115 -> -879
A116: Enviado | B116: 114 | C116: 45327 | D116: TINTAYA QUISPE JOSE PERCY | E116: 015101373A | F116: ELEVAR AL VRAC | G116: Maestro en Estadística e Investigación Científica. | J116: =TODAY() -> 46206 | K116: ='RESOLUCIONES 2024'!$C116-'RESOLUCIONES 2024'!$J116 -> -879
A117: Enviado | B117: 115 | C117: 45327 | D117: TINTAYA QUISPE MAGALY | E117: 015101374H | F117: ELEVAR AL VRAC | G117: Maestro en Estadística e Investigación Científica. | J117: =TODAY() -> 46206 | K117: ='RESOLUCIONES 2024'!$C117-'RESOLUCIONES 2024'!$J117 -> -879
A118: Enviado | B118: 116 | C118: 45327 | D118: BENITO PANTOJA DEENNIS | E118: 020200041J | F118: ELEVAR AL VRAC | G118: Maestro en Administración de Negocios. | J118: =TODAY() -> 46206 | K118: ='RESOLUCIONES 2024'!$C118-'RESOLUCIONES 2024'!$J118 -> -879
A119: Enviado | B119: 117 | C119: 45327 | D119: CONDORI OSORIO RUBEN | E119: 020300010I | F119: ELEVAR AL VRAC | G119: Doctor en Ciencias de la Educación. | J119: =TODAY() -> 46206 | K119: ='RESOLUCIONES 2024'!$C119-'RESOLUCIONES 2024'!$J119 -> -879
A120: Enviado | B120: 118 | C120: 45327 | D120: MERINO ASCUE ESTHER REYNA | E120: 020200012J | F120: DICTAMEN DE PROYECTO DE TESIS | J120: =TODAY() -> 46206 | K120: ='RESOLUCIONES 2024'!$C120-'RESOLUCIONES 2024'!$J120 -> -879
A121: Enviado | B121: 119 | C121: 45327 | D121: BACA GUTIERREZ NORMA | E121: 020100081J | F121: DICTAMEN DE PROYECTO DE TESIS | J121: =TODAY() -> 46206 | K121: ='RESOLUCIONES 2024'!$C121-'RESOLUCIONES 2024'!$J121 -> -879
A122: Enviado | B122: 120 | C122: 45327 | D122: TACURI QUEJIA GUADALUPE | E122: 020200077D | F122: DICTAMEN DE PROYECTO DE TESIS | J122: =TODAY() -> 46206 | K122: ='RESOLUCIONES 2024'!$C122-'RESOLUCIONES 2024'!$J122 -> -879
A123: Enviado | B123: 121 | C123: 45327 | D123: VILLAFUERTE CABRERA KATHERIN BERTHA | E123: 019200372J | F123: NOMBRAMIENTO DE ASESOR | G123: CORONADO GAMARRA LILIANA | J123: =TODAY() -> 46206 | K123: ='RESOLUCIONES 2024'!$C123-'RESOLUCIONES 2024'!$J123 -> -879
A124: Enviado | B124: 122 | C124: 45327 | D124: REYNAGA ROJAS NICOLAE HARVING | E124: 022300077D | F124: NOMBRAMIENTO DE ASESOR | G124: PANDIA CAYRO EVANDRO ESTEBAN | J124: =TODAY() -> 46206 | K124: ='RESOLUCIONES 2024'!$C124-'RESOLUCIONES 2024'!$J124 -> -879
A125: Enviado | B125: 123 | C125: 45327 | D125: TORRES SALDIVAR PAMELA LUZ | E125: 016102150E | F125: NOMBRAMIENTO DE ASESOR | G125: DIAZ TORRES JOSE HILDEBRANDO | J125: =TODAY() -> 46206 | K125: ='RESOLUCIONES 2024'!$C125-'RESOLUCIONES 2024'!$J125 -> -879
A126: Enviado | B126: 124 | C126: 45327 | D126: ZEVALLOS TAPIA SHIRLEY | E126: 023200014J | F126: NOMBRAMIENTO DE ASESOR | G126: AGUIRRE ESPINOZA EDWARDS JESUS | J126: =TODAY() -> 46206 | K126: ='RESOLUCIONES 2024'!$C126-'RESOLUCIONES 2024'!$J126 -> -879
A127: Enviado | B127: 125 | C127: 45327 | D127: PALOMINO DAVALOS WENDEL ALBERTO | E127: 023200008J | F127: NOMBRAMIENTO DE ASESOR | G127: AGUIRRE ESPINOZA EDWARDS JESUS | J127: =TODAY() -> 46206 | K127: ='RESOLUCIONES 2024'!$C127-'RESOLUCIONES 2024'!$J127 -> -879
A128: Enviado | B128: 126 | C128: 45327 | D128: APAZA CARMONA LIZBET ROCIO | E128: 023200001E | F128: NOMBRAMIENTO DE ASESOR | G128: AGUIRRE ESPINOZA EDWARDS JESUS | J128: =TODAY() -> 46206 | K128: ='RESOLUCIONES 2024'!$C128-'RESOLUCIONES 2024'!$J128 -> -879
A129: Enviado | B129: 127 | C129: 45327 | D129: ROJAS CARRILLO EMERSON ALFREDO | E129: 023200011K | F129: NOMBRAMIENTO DE ASESOR | G129: AGUIRRE ESPINOZA EDWARDS JESUS | J129: =TODAY() -> 46206 | K129: ='RESOLUCIONES 2024'!$C129-'RESOLUCIONES 2024'!$J129 -> -879
A130: Enviado | B130: 128 | C130: 45327 | D130: VASQUEZ CASTILLO MILAGROS | E130: 022100020I | F130: NOMBRAMIENTO DE ASESOR | G130: RIVAS LOAIZA CONNY | J130: =TODAY() -> 46206 | K130: ='RESOLUCIONES 2024'!$C130-'RESOLUCIONES 2024'!$J130 -> -879
A131: Enviado | B131: 129 | C131: 45327 | D131: VILLAGRA QUIN FIDEL | E131: 018100078C | F131: NOMBRAMIENTO DE ASESOR | G131: GONZALES ABRILL HERNANDO | J131: =TODAY() -> 46206 | K131: ='RESOLUCIONES 2024'!$C131-'RESOLUCIONES 2024'!$J131 -> -879
A132: Enviado | B132: 130 | C132: 45327 | D132: ZANABRIA QUILCA LUIS | E132: 016201413D | F132: NOMBRAMIENTO DE ASESOR | G132: AGUIRRE ESPINOZA EDWARDS JESUS | J132: =TODAY() -> 46206 | K132: ='RESOLUCIONES 2024'!$C132-'RESOLUCIONES 2024'!$J132 -> -879
A133: Enviado | B133: 131 | C133: 45329 | D133: ARENAS APUMAITA INDIRA | E133: 011270053H | F133: DICTAMEN DE PROYECTO DE TESIS | J133: =TODAY() -> 46206 | K133: ='RESOLUCIONES 2024'!$C133-'RESOLUCIONES 2024'!$J133 -> -877
A134: Enviado | B134: 132 | C134: 45329 | D134: VELA AREVALO VERONICA | E134: 015101340F | F134: DICTAMEN DE PROYECTO DE TESIS | J134: =TODAY() -> 46206 | K134: ='RESOLUCIONES 2024'!$C134-'RESOLUCIONES 2024'!$J134 -> -877
A135: Enviado | B135: 133 | C135: 45329 | D135: CCORI APAZA JAVIER | E135: 021200132D | F135: DICTAMEN DE PROYECTO DE TESIS | J135: =TODAY() -> 46206 | K135: ='RESOLUCIONES 2024'!$C135-'RESOLUCIONES 2024'!$J135 -> -877
A136: Enviado | B136: 134 | C136: 45329 | D136: CONDORI MAMANI WILIAM | E136: 014101497C | F136: DICTAMEN DE PROYECTO DE TESIS | J136: =TODAY() -> 46206 | K136: ='RESOLUCIONES 2024'!$C136-'RESOLUCIONES 2024'!$J136 -> -877
A137: Enviado | B137: 135 | C137: 45329 | D137: CRUZ LOAIZA JHOSELY FLOR | E137: 015301211E | F137: DICTAMEN DE PROYECTO DE TESIS | J137: =TODAY() -> 46206 | K137: ='RESOLUCIONES 2024'!$C137-'RESOLUCIONES 2024'!$J137 -> -877
A138: Enviado | B138: 136 | C138: 45329 | D138: BENAVIDES BEJAR SHEYLA ALMENDRA | E138: 020300128J | F138: DICTAMEN DE PROYECTO DE TESIS | J138: =TODAY() -> 46206 | K138: ='RESOLUCIONES 2024'!$C138-'RESOLUCIONES 2024'!$J138 -> -877
A139: Enviado | B139: 137 | C139: 45329 | D139: HUAMAN HUISA LUZ MARINA | E139: 018200181K | F139: DICTAMEN DE PROYECTO DE TESIS | J139: =TODAY() -> 46206 | K139: ='RESOLUCIONES 2024'!$C139-'RESOLUCIONES 2024'!$J139 -> -877
A140: Enviado | B140: 138 | C140: 45329 | D140: CJUNO CCALLO SONIA | E140: 019200119B | F140: DICTAMEN DE PROYECTO DE TESIS | J140: =TODAY() -> 46206 | K140: ='RESOLUCIONES 2024'!$C140-'RESOLUCIONES 2024'!$J140 -> -877
A141: Enviado | B141: 139 | C141: 45329 | D141: MOGROVEJO MEZA KADRIA LIVIA | E141: 015301245G | F141: DICTAMEN DE PROYECTO DE TESIS | J141: =TODAY() -> 46206 | K141: ='RESOLUCIONES 2024'!$C141-'RESOLUCIONES 2024'!$J141 -> -877
A142: Enviado | B142: 140 | C142: 45329 | D142: HUARAC CHACCA JUAN CARLOS | E142: 016102184G | F142: DICTAMEN DE PROYECTO DE TESIS | J142: =TODAY() -> 46206 | K142: ='RESOLUCIONES 2024'!$C142-'RESOLUCIONES 2024'!$J142 -> -877
A143: Enviado | B143: 141 | C143: 45329 | D143: ALVAREZ CONCHA ROSSY | E143: 018300130I | F143: DICTAMEN DE PROYECTO DE TESIS | J143: =TODAY() -> 46206 | K143: ='RESOLUCIONES 2024'!$C143-'RESOLUCIONES 2024'!$J143 -> -877
A144: Enviado | B144: 142 | C144: 45329 | D144: ALVAREZ ARIAS CELINDA | E144: 019200176F | F144: DICTAMEN DE PROYECTO DE TESIS | J144: =TODAY() -> 46206 | K144: ='RESOLUCIONES 2024'!$C144-'RESOLUCIONES 2024'!$J144 -> -877
... A162: Enviado | B162: 160 | C162: 45329 | D162: ESTRADA SÁNCHEZ DIEGO | E162: 017200145E | F162: DICTAMEN DE PROYECTO DE TESIS | J162: =TODAY() -> 46206 | K162: ='RESOLUCIONES 2024'!$C162-'RESOLUCIONES 2024'!$J162 -> -877
A163: Enviado | B163: 161 | C163: 45329 | D163: GIBAJA REYES HENDERSON NOZART | E163: 013200967I | F163: NOMBRAMIENTO DE ASESOR | G163: OLARTE SOTOMAYOR MIDWAR | J163: =TODAY() -> 46206 | K163: ='RESOLUCIONES 2024'!$C163-'RESOLUCIONES 2024'!$J163 -> -877
...

Sheet RESOLUCIONES 2023
A1: LAZO HERRERA THONY ABEL | J1: CARGOS
A2: N° SOLICITUD | B2: RESOL. N° | C2: FECHA | D2: NOMBRES Y APELLIDOS | E2: CODIGO2 | F2: TIPO DE RESOLUCION | G2: Obaservaciones | H2: RESOLUCION 2 | I2: Columna1 | J2: HOY | K2: Excede 730 Dias | L2: CARGO 3 | M2: CARGO 4 | N2: CARGO 5 | O2: CARGO 6
A3: Enviado | B3: 1 | C3: 44958 | D3: GUEVARA CANDIA RAFAEL FERNANDO | E3: 016201378D | F3: NOMBRAMIENTO DE ASESOR | J3: =TODAY() -> 46206 | K3: ='RESOLUCIONES 2023'!$C3-'RESOLUCIONES 2023'!$J3 -> -1248
A4: Enviado | B4: 2 | C4: 44958 | D4: OLIVERA ARREDONDO ALEJANDRO URIEL | E4: 019300059A | F4: NOMBRAMIENTO DE ASESOR | J4: =TODAY() -> 46206 | K4: ='RESOLUCIONES 2023'!$C4-'RESOLUCIONES 2023'!$J4 -> -1248
A5: Enviado | B5: 3 | C5: 44958 | D5: LUQUE FLOREZ EDWARD | E5: 018300052H | F5: INSCRIPCION DE PROYECTO DE TESIS | J5: =TODAY() -> 46206 | K5: ='RESOLUCIONES 2023'!$C5-'RESOLUCIONES 2023'!$J5 -> -1248
A6: Enviado | B6: 4 | C6: 44958 | D6: LOAIZA MORALES MAROLI ERNESTINA | E6: 018100040F | F6: INSCRIPCION DE PROYECTO DE TESIS | J6: =TODAY() -> 46206 | K6: ='RESOLUCIONES 2023'!$C6-'RESOLUCIONES 2023'!$J6 -> -1248
A7: Enviado | B7: 5 | C7: 44958 | D7: CORBACHO CARPIO ISABEL | E7: 016102367D | F7: INSCRIPCION DE PROYECTO DE TESIS | J7: =TODAY() -> 46206 | K7: ='RESOLUCIONES 2023'!$C7-'RESOLUCIONES 2023'!$J7 -> -1248
A8: Enviado | B8: 6 | C8: 44958 | D8: AUCCA MARIN EDWIN NILTON | E8: 017300005K | F8: INSCRIPCION DE PROYECTO DE TESIS | J8: =TODAY() -> 46206 | K8: ='RESOLUCIONES 2023'!$C8-'RESOLUCIONES 2023'!$J8 -> -1248
A9: Enviado | B9: 7 | C9: 44958 | D9: FARFAN ESCOBEDO WERNER ADAIR | E9: 017300095J | F9: INSCRIPCION DE PROYECTO DE TESIS | J9: =TODAY() -> 46206 | K9: ='RESOLUCIONES 2023'!$C9-'RESOLUCIONES 2023'!$J9 -> -1248
A10: Enviado | B10: 8 | C10: 44958 | D10: ZAVALA CACERES ESTER MARIBEL | E10: 020300032B | F10: INSCRIPCION DE PROYECTO DE TESIS | J10: =TODAY() -> 46206 | K10: ='RESOLUCIONES 2023'!$C10-'RESOLUCIONES 2023'!$J10 -> -1248
A11: Enviado | B11: 9 | C11: 44958 | D11: CASAFRANCA VILLACORTA NILTON | E11: 013200962G | F11: DICTAMEN DE TESIS | G11: Peña Farfan no labora en la UAC cambio de dictaminante | J11: =TODAY() -> 46206 | K11: ='RESOLUCIONES 2023'!$C11-'RESOLUCIONES 2023'!$J11 -> -1248
A12: Enviado | B12: 10 | C12: 44958 | D12: CCOPA ALEGRE JENNEFER PAOLA | E12: 021100060A | F12: DICTAMEN DE TESIS | J12: =TODAY() -> 46206 | K12: ='RESOLUCIONES 2023'!$C12-'RESOLUCIONES 2023'!$J12 -> -1248
A13: Enviado | B13: 11 | C13: 44958 | D13: VALVERDE VIZCARRA VANESSA MONICA | E13: 015101307I | F13: DICTAMEN DE TESIS | J13: =TODAY() -> 46206 | K13: ='RESOLUCIONES 2023'!$C13-'RESOLUCIONES 2023'!$J13 -> -1248
A14: Enviado | B14: 12 | C14: 44958 | D14: OCROS GUEVARA BERTOLT FERNANDO | E14: 019200354A | F14: DICTAMEN DE TESIS | J14: =TODAY() -> 46206 | K14: ='RESOLUCIONES 2023'!$C14-'RESOLUCIONES 2023'!$J14 -> -1248
A15: Enviado | B15: 13 | C15: 44958 | D15: TRUJILLO TEJADA JUAN CARLOS | E15: 011270075A | F15: DICTAMEN DE TESIS | J15: =TODAY() -> 46206 | K15: ='RESOLUCIONES 2023'!$C15-'RESOLUCIONES 2023'!$J15 -> -1248
A16: Enviado | B16: 14 | C16: 44958 | D16: GUEVARA CANDIA RAFAEL FERNANDO | E16: 016201378D | F16: DICTAMEN DE PROYECTO DE TESIS | J16: =TODAY() -> 46206 | K16: ='RESOLUCIONES 2023'!$C16-'RESOLUCIONES 2023'!$J16 -> -1248
A17: Enviado | B17: 15 | C17: 44958 | D17: CHAVEZ CAJIGAS JHENSS MALKYN | E17: 016201375E | F17: DICTAMEN DE PROYECTO DE TESIS | J17: =TODAY() -> 46206 | K17: ='RESOLUCIONES 2023'!$C17-'RESOLUCIONES 2023'!$J17 -> -1248
A18: Enviado | B18: 16 | C18: 44958 | D18: SERNA SILVA MIRIAN ZULEMA | E18: 019100021K | F18: DICTAMEN DE PROYECTO DE TESIS | J18: =TODAY() -> 46206 | K18: ='RESOLUCIONES 2023'!$C18-'RESOLUCIONES 2023'!$J18 -> -1248
A19: Enviado | B19: 17 | C19: 44958 | D19: FARROÑAN FLORES GABRIEL | E19: 019100098C | F19: DICTAMEN DE PROYECTO DE TESIS | J19: =TODAY() -> 46206 | K19: ='RESOLUCIONES 2023'!$C19-'RESOLUCIONES 2023'!$J19 -> -1248
A20: Enviado | B20: 18 | C20: 44958 | D20: SAYRE GAMARRA JAYNA MIRELIA | E20: 019100114I | F20: DICTAMEN DE PROYECTO DE TESIS | J20: =TODAY() -> 46206 | K20: ='RESOLUCIONES 2023'!$C20-'RESOLUCIONES 2023'!$J20 -> -1248
A21: Enviado | B21: 19 | C21: 44958 | D21: ROMAN BUSTINZA ANGELICA | E21: 017300130J | F21: DICTAMEN DE PROYECTO DE TESIS | J21: =TODAY() -> 46206 | K21: ='RESOLUCIONES 2023'!$C21-'RESOLUCIONES 2023'!$J21 -> -1248
A22: Enviado | B22: 20 | C22: 44964 | D22: MELENDEZ NINA JUAN FRANCISCO | E22: 015101554F | F22: EXPEDIENTE APTO AL GRADO | J22: =TODAY() -> 46206 | K22: ='RESOLUCIONES 2023'!$C22-'RESOLUCIONES 2023'!$J22 -> -1242
A23: Enviado | B23: 21 | C23: 44964 | D23: RAMOS PACHECO BETSY SURI | E23: 018100072E | F23: ELEVAR AL VRAC | G23: Doctor en Medio Ambiente y Desarrollo Sostenible. | J23: =TODAY() -> 46206 | K23: ='RESOLUCIONES 2023'!$C23-'RESOLUCIONES 2023'!$J23 -> -1242
A24: Enviado | B24: 22 | C24: 44964 | D24: TOVAR NINA LILLIBETH | E24: 016102359A | F24: ELEVAR AL VRAC | G24: Maestro en Administración de Negocios. | J24: =TODAY() -> 46206 | K24: ='RESOLUCIONES 2023'!$C24-'RESOLUCIONES 2023'!$J24 -> -1242
A25: Enviado | B25: 23 | C25: 44964 | D25: CALDERÓN SEGURA JUAN CARLOS FIDEL | E25: 017200232E | F25: ELEVAR AL VRAC | G25: Maestro en Seguridad Industrial y Medio Ambiente | J25: =TODAY() -> 46206 | K25: ='RESOLUCIONES 2023'!$C25-'RESOLUCIONES 2023'!$J25 -> -1242
A26: Enviado | B26: 24 | C26: 44964 | D26: CASTRO CERECEDA RUTH | E26: 010200009K | F26: ELEVAR AL VRAC | G26: Maestro en Docencia Universitaria. | J26: =TODAY() -> 46206 | K26: ='RESOLUCIONES 2023'!$C26-'RESOLUCIONES 2023'!$J26 -> -1242
A27: Enviado | B27: 25 | C27: 44965 | D27: LOAYZA BORDA JOSE ALEJANDRO | E27: 018200036K | F27: FIJAR FECHA Y HORA | G27: Se envio observaciones | J27: =TODAY() -> 46206 | K27: ='RESOLUCIONES 2023'!$C27-'RESOLUCIONES 2023'!$J27 -> -1241
A28: Enviado | B28: 26 | C28: 44965 | D28: ZUNIGA ESPINOZA NICO IVAN | E28: 015101447E | F28: FIJAR FECHA Y HORA | G28: Se envio observaciones | J28: =TODAY() -> 46206 | K28: ='RESOLUCIONES 2023'!$C28-'RESOLUCIONES 2023'!$J28 -> -1241
A29: Enviado | B29: 27 | C29: 44965 | D29: BUSTAMANTE JAEN JULIO DANILO | E29: 016102062I | F29: FIJAR FECHA Y HORA | G29: Se envio observaciones | J29: =TODAY() -> 46206 | K29: ='RESOLUCIONES 2023'!$C29-'RESOLUCIONES 2023'!$J29 -> -1241
A30: Enviado | B30: 28 | C30: 44965 | D30: SANJINES PEÑA YASKARA | E30: 016102357I | F30: FIJAR FECHA Y HORA | G30: Se envio observaciones | J30: =TODAY() -> 46206 | K30: ='RESOLUCIONES 2023'!$C30-'RESOLUCIONES 2023'!$J30 -> -1241
A31: Enviado | B31: 29 | C31: 44965 | D31: PANDO DIAZ WALDO MANUEL | E31: 019200285J | F31: FIJAR FECHA Y HORA | G31: Se envio observaciones | J31: =TODAY() -> 46206 | K31: ='RESOLUCIONES 2023'!$C31-'RESOLUCIONES 2023'!$J31 -> -1241
A32: Enviado | B32: 30 | C32: 44965 | D32: ANAYA CAHUA LUIS CARLOS | E32: 014101510J | F32: FIJAR FECHA Y HORA | G32: Se envio observaciones | J32: =TODAY() -> 46206 | K32: ='RESOLUCIONES 2023'!$C32-'RESOLUCIONES 2023'!$J32 -> -1241
A33: Enviado | B33: 31 | C33: 44965 | D33: PEÑA CHAVEZ MANUEL SEYBERLING | E33: 018100071I | F33: FIJAR FECHA Y HORA | G33: Suspendido | J33: =TODAY() -> 46206 | K33: ='RESOLUCIONES 2023'!$C33-'RESOLUCIONES 2023'!$J33 -> -1241
A34: Enviado | B34: 32 | C34: 44965 | D34: CORZO PALOMO ERIKA ELEANA | E34: 018300036B | F34: FIJAR FECHA Y HORA | G34: Se envio observaciones | J34: =TODAY() -> 46206 | K34: ='RESOLUCIONES 2023'!$C34-'RESOLUCIONES 2023'!$J34 -> -1241
... A40: Enviado | B40: 38 | C40: 44967 | D40: CARDENAS FLORES ROCIO MARLENI | E40: 017200026F | F40: FIJAR FECHA Y HORA | G40: Se envio observaciones | J40: =TODAY() -> 46206 | K40: ='RESOLUCIONES 2023'!$C40-'RESOLUCIONES 2023'!$J40 -> -1239
A41: Enviado | B41: 39 | C41: 44967 | D41: TRIGOSO DELGADO JORGE OSCAR | E41: 018200301F | F41: CAMBIO DE TITULO DE PROYECTO | J41: =TODAY() -> 46206 | K41: ='RESOLUCIONES 2023'!$C41-'RESOLUCIONES 2023'!$J41 -> -1239
A42: Enviado | B42: 40 | C42: 44970 | D42: JALIXTO CUYO SOLEDAD | E42: 016102344D | F42: APTO AL GRADO | J42: =TODAY() -> 46206 | K42: ='RESOLUCIONES 2023'!$C42-'RESOLUCIONES 2023'!$J42 -> -1236
A43: Enviado | B43: 41 | C43: 44970 | D43: CHAVEZ YABAR JULIO CESAR | E43: 011270014B | F43: APTO AL GRADO | J43: =TODAY() -> 46206 | K43: ='RESOLUCIONES 2023'!$C43-'RESOLUCIONES 2023'!$J43 -> -1236
A44: Enviado | B44: 42 | C44: 44970 | D44: BALLON VALER YULIANA | E44: 011270005C | F44: APTO AL GRADO | J44: =TODAY() -> 46206 | K44: ='RESOLUCIONES 2023'!$C44-'RESOLUCIONES 2023'!$J44 -> -1236
A45: Enviado | B45: 43 | C45: 44970 | D45: ANAYA CENTENO GUSTAVO | E45: 019200241B | F45: APTO AL GRADO | J45: =TODAY() -> 46206 | K45: ='RESOLUCIONES 2023'!$C45-'RESOLUCIONES 2023'!$J45 -> -1236
A46: Enviado | B46: 44 | C46: 44970 | D46: QUISPE CUSIHUAMAN MARIA ANGELICA | E46: 019300062B | F46: APTO AL GRADO | J46: =TODAY() -> 46206 | K46: ='RESOLUCIONES 2023'!$C46-'RESOLUCIONES 2023'!$J46 -> -1236
A47: Enviado | B47: 45 | C47: 44970 | D47: COSIO MUÑOZ JUAN | E47: 020300137I | F47: APTO AL GRADO | J47: =TODAY() -> 46206 | K47: ='RESOLUCIONES 2023'!$C47-'RESOLUCIONES 2023'!$J47 -> -1236
A48: Enviado | B48: 46 | C48: 44970 | D48: CHALCO SUAREZ JESSICA ELIZABETH | E48: 015101349C | F48: AMPLIACION INSCRIPCION DE PROYECTO | J48: =TODAY() -> 46206 | K48: ='RESOLUCIONES 2023'!$C48-'RESOLUCIONES 2023'!$J48 -> -1236
A49: Enviado | B49: 47 | C49: 44970 | D49: GAMARRA SALAS JONATHAN | E49: 015101318K, | F49: AMPLIACION INSCRIPCION DE PROYECTO | J49: =TODAY() -> 46206 | K49: ='RESOLUCIONES 2023'!$C49-'RESOLUCIONES 2023'!$J49 -> -1236
A50: Enviado | B50: 48 | C50: 44970 | D50: TICONA FLORES TONY GODOFREDO | E50: 013201096A | F50: FIJAR FECHA Y HORA | G50: Se envio observaciones | J50: =TODAY() -> 46206 | K50: ='RESOLUCIONES 2023'!$C50-'RESOLUCIONES 2023'!$J50 -> -1236
A51: Enviado | B51: 49 | C51: 44972 | D51: GARCIA BUSTINZA JAVIER | E51: 021300105I | F51: DICTAMEN DE PROYECTO DE TESIS | J51: =TODAY() -> 46206 | K51: ='RESOLUCIONES 2023'!$C51-'RESOLUCIONES 2023'!$J51 -> -1234
A52: Enviado | B52: 50 | C52: 44972 | D52: CUCHILLO CAYTUIRO MANUEL | E52: 017200294K | F52: DCTAMEN DE TESIS | H52: error en la resolucion, Dr. Chacon es asesor. | J52: =TODAY() -> 46206 | K52: ='RESOLUCIONES 2023'!$C52-'RESOLUCIONES 2023'!$J52 -> -1234
A53: Enviado | B53: 51 | C53: 44972 | D53: ZEVALLOS GUZMAN HERBERT JESUS | E53: 015201393D | F53: FIJAR FECHA Y HORA | G53: Se envio observaciones | J53: =TODAY() -> 46206 | K53: ='RESOLUCIONES 2023'!$C53-'RESOLUCIONES 2023'!$J53 -> -1234
A54: Enviado | B54: 52 | C54: 44972 | D54: TAMAYO VARGAS CARLOS MAXIMO | E54: 019100053J | F54: CAMBIO DE TITULO DE PROYECTO | J54: =TODAY() -> 46206 | K54: ='RESOLUCIONES 2023'!$C54-'RESOLUCIONES 2023'!$J54 -> -1234
A55: Enviado | B55: 53 | C55: 44972 | D55: ORELLANA ECHEGARAY MACX ARTHUR | E55: 015301276J | F55: NOMBRAMIENTO DE ASESOR | G55: ESPINOZA ACURIO ANGELA ROXANA | J55: =TODAY() -> 46206 | K55: ='RESOLUCIONES 2023'!$C55-'RESOLUCIONES 2023'!$J55 -> -1234
A56: Enviado | B56: 54 | C56: 44972 | D56: PAREDES BRUNO ANA KARYNA | E56: 020300064A | F56: NOMBRAMIENTO DE ASESOR | G56: SALAZAR MUJICA ALAN FELIPE | J56: =TODAY() -> 46206 | K56: ='RESOLUCIONES 2023'!$C56-'RESOLUCIONES 2023'!$J56 -> -1234
A57: Enviado | B57: 55 | C57: 44972 | D57: ANDIA CUBA JOSE | E57: 020100076F | F57: NOMBRAMIENTO DE ASESOR | G57: MELENDREZ VELASCO ELIAS, | H57: CAMBIO DE ASESOR | J57: =TODAY() -> 46206 | K57: ='RESOLUCIONES 2023'!$C57-'RESOLUCIONES 2023'!$J57 -> -1234
A58: Enviado | B58: 56 | C58: 44977 | D58: HUAMAN PATIÑO ZENAIDA | E58: 021300108H | F58: DICTAMEN DE PROYECTO DE TESIS | J58: =TODAY() -> 46206 | K58: ='RESOLUCIONES 2023'!$C58-'RESOLUCIONES 2023'!$J58 -> -1229
A59: Enviado | B59: 57 | C59: 44977 | D59: CUNO TUMI SANDRA | E59: 021200095A | F59: DICTAMEN DE PROYECTO DE TESIS | J59: =TODAY() -> 46206 | K59: ='RESOLUCIONES 2023'!$C59-'RESOLUCIONES 2023'!$J59 -> -1229
A60: Enviado | B60: 58 | C60: 44977 | D60: PALAO MAMANI ROSALVA | E60: 018200238B | F60: DICTAMEN DE PROYECTO DE TESIS | J60: =TODAY() -> 46206 | K60: ='RESOLUCIONES 2023'!$C60-'RESOLUCIONES 2023'!$J60 -> -1229
A61: Enviado | B61: 59 | C61: 44978 | D61: RIOS VARGAS JERSON | E61: 019200441A | F61: CAMBIO DE ASESOR | G61: CALDERÓN SUMARRIVA ANA CECILIA | J61: =TODAY() -> 46206 | K61: ='RESOLUCIONES 2023'!$C61-'RESOLUCIONES 2023'!$J61 -> -1228
A62: Enviado | B62: 60 | C62: 44978 | D62: PAULLO DAVALOS RUTH MARIBEL | E62: 021100048A | F62: CAMBIO DE ASESOR | G62: ZUÑIGA MARINO MIGUEL ANGEL | J62: =TODAY() -> 46206 | K62: ='RESOLUCIONES 2023'!$C62-'RESOLUCIONES 2023'!$J62 -> -1228
A63: Enviado | B63: 61 | C63: 44978 | D63: MERINO ASCUE ESTHER REYNA | E63: 020200012J | F63: CAMBIO DE ASESOR | G63: HUARACA APARCO ROSA | J63: =TODAY() -> 46206 | K63: ='RESOLUCIONES 2023'!$C63-'RESOLUCIONES 2023'!$J63 -> -1228
A64: Enviado | B64: 62 | C64: 44978 | D64: ENRIQUEZ OBLITAS ACURIO LEONIDAS | E64: 014101469J | F64: CAMBIO DE ASESOR | G64: FLORES CONTRERAS AYDEE | J64: =TODAY() -> 46206 | K64: ='RESOLUCIONES 2023'!$C64-'RESOLUCIONES 2023'!$J64 -> -1228
A65: Enviado | B65: 63 | C65: 44978 | D65: CHOQUEVILCA LIRA WALTER FLORENCIO | E65: 015101538K | F65: CAMBIO DE ASESOR | G65: CALDERON LA TORRE FELIO | J65: =TODAY() -> 46206 | K65: ='RESOLUCIONES 2023'!$C65-'RESOLUCIONES 2023'!$J65 -> -1228
A66: Enviado | B66: 64 | C66: 44978 | D66: ASCUE RUIZ ROSA NELIDA | E66: 020200001H | F66: CAMBIO DE ASESOR | G66: UARACA APARCO ROSA | J66: =TODAY() -> 46206 | K66: ='RESOLUCIONES 2023'!$C66-'RESOLUCIONES 2023'!$J66 -> -1228
A67: Enviado | B67: 65 | C67: 44978 | D67: NINATAYPE MAMANI LADISLAO MAURICE | E67: 017200103K | F67: CAMBIO DE ASESOR | G67: CONDORI CCAHUA CERAFINA | J67: =TODAY() -> 46206 | K67: ='RESOLUCIONES 2023'!$C67-'RESOLUCIONES 2023'!$J67 -> -1228
A68: Enviado | B68: 66 | C68: 44980 | D68: CUTUCALLA MOLLEHUANCA FREDY GERMAN | E68: 016110273E | F68: CAMBIO DE TITULO DE PROYECTO | J68: =TODAY() -> 46206 | K68: ='RESOLUCIONES 2023'!$C68-'RESOLUCIONES 2023'!$J68 -> -1226
A69: Enviado | B69: 67 | C69: 44980 | D69: VERA MUÑOZ ESTEFANY LORENA | E69: 020300199D | F69: APTO AL GRADO | J69: =TODAY() -> 46206 | K69: ='RESOLUCIONES 2023'!$C69-'RESOLUCIONES 2023'!$J69 -> -1226
A70: Enviado | B70: 68 | C70: 44980 | D70: CHALCO SUAREZ JESSICA ELIZABETH | E70: 015101349C | F70: APTO AL GRADO | J70: =TODAY() -> 46206 | K70: ='RESOLUCIONES 2023'!$C70-'RESOLUCIONES 2023'!$J70 -> -1226
A71: Enviado | B71: 69 | C71: 44980 | D71: ARMUTO QUISPETUPA KATTLIN MILIANA | E71: 019200154B | F71: APTO AL GRADO | J71: =TODAY() -> 46206 | K71: ='RESOLUCIONES 2023'!$C71-'RESOLUCIONES 2023'!$J71 -> -1226
A72: Enviado | B72: 70 | C72: 44981 | D72: MERCADO ESPEJO IVONNE | E72: 018300010C | F72: ELEVAR AL VRAC | G72: Doctorado derecho | J72: =TODAY() -> 46206 | K72: ='RESOLUCIONES 2023'!$C72-'RESOLUCIONES 2023'!$J72 -> -1225
A73: Enviado | B73: 71 | C73: 44981 | D73: LOAYZA ECHEGARAY LUZ GLORIA | E73: 019300132K | F73: ELEVAR AL VRAC | G73: Maestro en Derecho Civil y Comercial. | J73: =TODAY() -> 46206 | K73: ='RESOLUCIONES 2023'!$C73-'RESOLUCIONES 2023'!$J73 -> -1225
A74: Enviado | B74: 72 | C74: 44981 | D74: VALER FIGUEROA WALTER | E74: 011270077D | F74: ANULADO | G74: ANULADO | J74: =TODAY() -> 46206 | K74: ='RESOLUCIONES 2023'!$C74-'RESOLUCIONES 2023'!$J74 -> -1225
A75: Enviado | B75: 73 | C75: 44981 | D75: VERA MALDONADO LEOPOLDO | E75: 019200180C | F75: INSCRIPCION DE PROYECTO DE TESIS | J75: =TODAY() -> 46206 | K75: ='RESOLUCIONES 2023'!$C75-'RESOLUCIONES 2023'!$J75 -> -1225
A76: Enviado | B76: 74 | C76: 44984 | D76: VASQUEZ CERDA DIGNO | E76: 021300053I | F76: INSCRIPCION DE PROYECTO DE TESIS | J76: =TODAY() -> 46206 | K76: ='RESOLUCIONES 2023'!$C76-'RESOLUCIONES 2023'!$J76 -> -1222
A77: Enviado | B77: 75 | C77: 44984 | D77: NINATAYPE MAMANI LADISLAO MAURICE | E77: 017200103K | F77: INSCRIPCION DE PROYECTO DE TESIS | J77: =TODAY() -> 46206 | K77: ='RESOLUCIONES 2023'!$C77-'RESOLUCIONES 2023'!$J77 -> -1222
A78: Enviado | B78: 76 | C78: 44984 | D78: DEZA ALVAREZ KAREM DANIELA | E78: 020300171B | F78: NOMBRAMIENTO DE ASESOR | G78: RIVERA MUÑOZ JORGE LEONCIO | J78: =TODAY() -> 46206 | K78: ='RESOLUCIONES 2023'!$C78-'RESOLUCIONES 2023'!$J78 -> -1222
A79: Enviado | B79: 77 | C79: 44984 | D79: LADRON DE GUEVARA FRANCO ANGELY BEATRIZ | E79: 019300047C | F79: NOMBRAMIENTO DE ASESOR | G79: CASTRO CUBA BARINEZA ISAAC ENRIQUE | J79: =TODAY() -> 46206 | K79: ='RESOLUCIONES 2023'!$C79-'RESOLUCIONES 2023'!$J79 -> -1222
A80: Enviado | B80: 78 | C80: 44984 | D80: CORREA CUBA ODILON | E80: 020200028C | F80: NOMBRAMIENTO DE ASESOR | G80: CHOQUE QUISPE DAVID | J80: =TODAY() -> 46206 | K80: ='RESOLUCIONES 2023'!$C80-'RESOLUCIONES 2023'!$J80 -> -1222
A81: Enviado | B81: 79 | C81: 44984 | D81: FRANCO ASTURIMA MARIA BEATRIZ | E81: 019300044D | F81: NOMBRAMIENTO DE ASESOR | G81: CASTRO CUBA BARINEZA ISAAC ENRIQUE | J81: =TODAY() -> 46206 | K81: ='RESOLUCIONES 2023'!$C81-'RESOLUCIONES 2023'!$J81 -> -1222
A82: Enviado | B82: 80 | C82: 44984 | D82: ARONI SURCO JIMENA | E82: 021300037C | F82: NOMBRAMIENTO DE ASESOR | G82: CORONADO GAMARRA LILIANA | J82: =TODAY() -> 46206 | K82: ='RESOLUCIONES 2023'!$C82-'RESOLUCIONES 2023'!$J82 -> -1222
A83: Enviado | B83: 81 | C83: 44984 | D83: TINEO TUEROS MIRELLA PAMELA | E83: 017200079B | F83: NOMBRAMIENTO DE ASESOR | G83: HERRERA OSORIO ALHI JORDAN | J83: =TODAY() -> 46206 | K83: ='RESOLUCIONES 2023'!$C83-'RESOLUCIONES 2023'!$J83 -> -1222
A84: Enviado | B84: 82 | C84: 44984 | D84: PEREZ TERRAZAS GRACE | E84: 019200198J | F84: NOMBRAMIENTO DE ASESOR | G84: SALAZAR MUJICA ALAN FELIPE | J84: =TODAY() -> 46206 | K84: ='RESOLUCIONES 2023'!$C84-'RESOLUCIONES 2023'!$J84 -> -1222
A85: Enviado | B85: 83 | C85: 44984 | D85: GONZALES HUANCA NANCY | E85: 019200277G | F85: NOMBRAMIENTO DE ASESOR | G85: ACO CORRALES EDER ARTURO | J85: =TODAY() -> 46206 | K85: ='RESOLUCIONES 2023'!$C85-'RESOLUCIONES 2023'!$J85 -> -1222
A86: Enviado | B86: 84 | C86: 44984 | D86: CORNEJO BARRA FIORELLA KATIUSKA | E86: 020100089K | F86: CAMBIO DE ASESOR | G86: RIVERO YNFANTAS FERNANDO | J86: =TODAY() -> 46206 | K86: ='RESOLUCIONES 2023'!$C86-'RESOLUCIONES 2023'!$J86 -> -1222
A87: Enviado | B87: 85 | C87: 44986 | D87: PINARES PAYNE GABRIELA FERNANDA | E87: 019200162E | F87: FIJAR FECHA Y HORA | G87: Se envio observaciones | J87: =TODAY() -> 46206 | K87: ='RESOLUCIONES 2023'!$C87-'RESOLUCIONES 2023'!$J87 -> -1220
A88: Enviado | B88: 86 | C88: 44986 | D88: CUENTAS ROMAÑA YANET | E88: 017200057I | F88: APTO AL GRADO | J88: =TODAY() -> 46206 | K88: ='RESOLUCIONES 2023'!$C88-'RESOLUCIONES 2023'!$J88 -> -1220
A89: Enviado | B89: 87 | C89: 44986 | D89: PANDO DIAZ WALDO ALEX | E89: 019200219G | F89: ELEVAR AL VRAC | G89: Doctor en Administración. | J89: =TODAY() -> 46206 | K89: ='RESOLUCIONES 2023'!$C89-'RESOLUCIONES 2023'!$J89 -> -1220
A90: Enviado | B90: 88 | C90: 44986 | D90: SOTO QUISPE LIDIA TOMASA | E90: 021100014J | F90: APTO AL GRADO | J90: =TODAY() -> 46206 | K90: ='RESOLUCIONES 2023'!$C90-'RESOLUCIONES 2023'!$J90 -> -1220
A91: Enviado | B91: 89 | C91: 44986 | D91: BAYLON TICONA PAVEL RICARDO | E91: A16201456E | F91: ELEVAR AL VRAC | G91: Maestro en Gestión del Turismo Sostenible. | J91: =TODAY() -> 46206 | K91: ='RESOLUCIONES 2023'!$C91-'RESOLUCIONES 2023'!$J91 -> -1220
A92: Enviado | B92: 90 | C92: 44986 | D92: AGUILAR VILLAFUERTE GEORGE LUIS | E92: A16102404G | F92: ELEVAR AL VRAC | G92: Docencia Universitaria | J92: =TODAY() -> 46206 | K92: ='RESOLUCIONES 2023'!$C92-'RESOLUCIONES 2023'!$J92 -> -1220
A93: Enviado | B93: 91 | C93: 44986 | D93: SANCHEZ MOGOLLON DIEGO | E93: 016201366F | F93: ELEVAR AL VRAC | G93: Maestro en Derecho Civil y Comercial. | J93: =TODAY() -> 46206 | K93: ='RESOLUCIONES 2023'!$C93-'RESOLUCIONES 2023'!$J93 -> -1220
A94: Enviado | B94: 92 | C94: 44986 | D94: CRUZ QUIN GEORGINA | E94: 015101353K | F94: ELEVAR AL VRAC | G94: Maestro en Estadística e Investigación Científica. | J94: =TODAY() -> 46206 | K94: ='RESOLUCIONES 2023'!$C94-'RESOLUCIONES 2023'!$J94 -> -1220
A95: Enviado | B95: 93 | C95: 44986 | D95: MEZA SALCEDO ROCIO | E95: 019200186A | F95: ELEVAR AL VRAC | G95: Doctor en Ciencias de la Salud. | J95: =TODAY() -> 46206 | K95: ='RESOLUCIONES 2023'!$C95-'RESOLUCIONES 2023'!$J95 -> -1220
A96: Enviado | B96: 94 | C96: 44991 | D96: JALIXTO CUYO SOLEDAD | E96: 016102344D | F96: DCTAMEN DE TESIS | J96: =TODAY() -> 46206 | K96: ='RESOLUCIONES 2023'!$C96-'RESOLUCIONES 2023'!$J96 -> -1215
A97: Enviado | B97: 95 | C97: 44991 | D97: QUISPE CUSIHUAMAN MARIA ANGELICA | E97: 019300062B | F97: DCTAMEN DE TESIS | J97: =TODAY() -> 46206 | K97: ='RESOLUCIONES 2023'!$C97-'RESOLUCIONES 2023'!$J97 -> -1215
A98: Enviado | B98: 96 | C98: 44991 | D98: ARMUTO QUISPETUPA KATTLIN MILIANA | E98: 019200154B | F98: DCTAMEN DE TESIS | J98: =TODAY() -> 46206 | K98: ='RESOLUCIONES 2023'!$C98-'RESOLUCIONES 2023'!$J98 -> -1215
A99: Enviado | B99: 97 | C99: 44991 | D99: SALAS FORTON EDSON JULIO | E99: 015201388K | F99: DCTAMEN DE TESIS | J99: =TODAY() -> 46206 | K99: ='RESOLUCIONES 2023'!$C99-'RESOLUCIONES 2023'!$J99 -> -1215
A100: Enviado | B100: 98 | C100: 44991 | D100: PEÑA CHAVEZ MANUEL SEYBERLING | E100: 018100071I | F100: FIJAR FECHA Y HORA | G100: Se envio observaciones | J100: =TODAY() -> 46206 | K100: ='RESOLUCIONES 2023'!$C100-'RESOLUCIONES 2023'!$J100 -> -1215
A101: Enviado | B101: 99 | C101: 44991 | D101: VARGAS ACOSTA JACKIE | E101: 012101141F | F101: DCTAMEN DE TESIS | J101: =TODAY() -> 46206 | K101: ='RESOLUCIONES 2023'!$C101-'RESOLUCIONES 2023'!$J101 -> -1215
A102: Enviado | B102: 100 | C102: 44991 | D102: ROJAS ANAYA YANINA | E102: A15201430G | F102: DCTAMEN DE TESIS | J102: =TODAY() -> 46206 | K102: ='RESOLUCIONES 2023'!$C102-'RESOLUCIONES 2023'!$J102 -> -1215
A103: Enviado | B103: 101 | C103: 44992 | D103: CORNEJO SANCHEZ MARILIANA | E103: 019200337J | F103: ELEVAR AL VRAC | G103: Doctor en Derecho. | J103: =TODAY() -> 46206 | K103: ='RESOLUCIONES 2023'!$C103-'RESOLUCIONES 2023'!$J103 -> -1214
A104: Enviado | B104: 102 | C104: 44992 | D104: COAQUIRA CASTILLO ROGER JESUS | E104: 019300084F | F104: ELEVAR AL VRAC | G104: Doctor en Medio Ambiente y Desarrollo Sostenible. | J104: =TODAY() -> 46206 | K104: ='RESOLUCIONES 2023'!$C104-'RESOLUCIONES 2023'!$J104 -> -1214
A105: Enviado | B105: 103 | C105: 44992 | D105: CORDOVA CONGA CARLOS EDUARDO | E105: 014101466K | F105: APTO AL GRADO | J105: =TODAY() -> 46206 | K105: ='RESOLUCIONES 2023'!$C105-'RESOLUCIONES 2023'!$J105 -> -1214
...

Sheet RESOLUCIONES 2022
A1: RESOLUCIONES EMITIDAS 2022 | J1: CARGOS
A2: N° SOLICITUD | B2: RESOL. N° | C2: FECHA | D2: NOMBRES Y APELLIDOS | E2: CODIGO2 | F2: TIPO DE RESOLUCION | G2: Obaservaciones | H2: RESOLUCION 2 | I2: Columna1 | J2: HOY | K2: Excede 730 Dias | L2: CARGO 3 | M2: CARGO 4 | N2: CARGO 5 | O2: CARGO 6
A3: Enviado | B3: 1 | C3: 44572 | D3: BARRANTES OROS ZUNEI BRISHAELLY | E3: 016102383J | F3: DICTAMEN PROYECTO DE TESIS | J3: =TODAY() -> 46206 | K3: ='RESOLUCIONES 2022'!$C3-'RESOLUCIONES 2022'!$J3 -> -1634
A4: Enviado | B4: 2 | C4: 44572 | D4: LOAIZA LIVANO NOELY ESMERALDA | E4: 017300070G | F4: DICTAMEN PROYECTO DE TESIS | J4: =TODAY() -> 46206 | K4: ='RESOLUCIONES 2022'!$C4-'RESOLUCIONES 2022'!$J4 -> -1634
A5: Enviado | B5: 3 | C5: 44572 | D5: OLIVARES TORRE GRETEL ROXANA | E5: 019200033K | F5: DICTAMEN PROYECTO DE TESIS | J5: =TODAY() -> 46206 | K5: ='RESOLUCIONES 2022'!$C5-'RESOLUCIONES 2022'!$J5 -> -1634
A6: Enviado | B6: 4 | C6: 44572 | D6: AQUEPUCHO BELLOTA RUDYARD WILHELM | E6: 019100059H | F6: DICTAMEN PROYECTO DE TESIS | J6: =TODAY() -> 46206 | K6: ='RESOLUCIONES 2022'!$C6-'RESOLUCIONES 2022'!$J6 -> -1634
A7: Enviado | B7: 5 | C7: 44572 | D7: PORCEL HUILLCA IVAN | E7: 019200418J | F7: DICTAMEN PROYECTO DE TESIS | J7: =TODAY() -> 46206 | K7: ='RESOLUCIONES 2022'!$C7-'RESOLUCIONES 2022'!$J7 -> -1634
A8: Enviado | B8: 6 | C8: 44572 | D8: COAQUIRA CASTILLO ROGER JESUS | E8: 019300084F | F8: DICTAMEN PROYECTO DE TESIS | J8: =TODAY() -> 46206 | K8: ='RESOLUCIONES 2022'!$C8-'RESOLUCIONES 2022'!$J8 -> -1634
A9: Enviado | B9: 7 | C9: 44572 | D9: ACHAHUANCO ACHAHUI GORKI EDUARDO | E9: 014101487H | F9: DICTAMEN PROYECTO DE TESIS | J9: =TODAY() -> 46206 | K9: ='RESOLUCIONES 2022'!$C9-'RESOLUCIONES 2022'!$J9 -> -1634
A10: Enviado | B10: 8 | C10: 44572 | D10: GUTIERREZ TUPAYACHI VIRANSHELY MILAGROS | E10: 021100066J | F10: DICTAMEN PROYECTO DE TESIS | J10: =TODAY() -> 46206 | K10: ='RESOLUCIONES 2022'!$C10-'RESOLUCIONES 2022'!$J10 -> -1634
A11: Enviado | B11: 9 | C11: 44572 | D11: QUISPE ESPINOZA ROXANA | E11: 018200012D | F11: DICTAMEN PROYECTO DE TESIS | J11: =TODAY() -> 46206 | K11: ='RESOLUCIONES 2022'!$C11-'RESOLUCIONES 2022'!$J11 -> -1634
A12: Enviado | B12: 10 | C12: 44572 | D12: TACURI QUEJIA GUADALUPE | E12: 020200077D | F12: DICTAMEN PROYECTO DE TESIS | J12: =TODAY() -> 46206 | K12: ='RESOLUCIONES 2022'!$C12-'RESOLUCIONES 2022'!$J12 -> -1634
A13: Enviado | B13: 11 | C13: 44572 | D13: CHILLIHUANI CASA SANDRA | E13: 019300007A | F13: DICTAMEN PROYECTO DE TESIS | J13: =TODAY() -> 46206 | K13: ='RESOLUCIONES 2022'!$C13-'RESOLUCIONES 2022'!$J13 -> -1634
A14: Enviado | B14: 12 | C14: 44575 | D14: VERA MUÑOZ ESTEFANY LORENA | E14: 020300199D | F14: AUTORIZAR LA SUBSANACION | G14: RIVERA MUÑOZ JORGE LEONCIO | J14: =TODAY() -> 46206 | K14: ='RESOLUCIONES 2022'!$C14-'RESOLUCIONES 2022'!$J14 -> -1631
A15: Enviado | B15: 13 | C15: 44589 | D15: QUILCA JIMENEZ JUAN CARLOS | E15: 016201405A | F15: Cambio de Asesor del Proyecto de Tesis | G15: CHACALTANA PISCONTE JULIO GUILLERMO | J15: =TODAY() -> 46206 | K15: ='RESOLUCIONES 2022'!$C15-'RESOLUCIONES 2022'!$J15 -> -1617
A16: Enviado | B16: 14 | C16: 44589 | D16: AQUEPUCHO BELLOTA RUDYARD WILHELM | E16: 019100059H | F16: Cambio de Asesor del Proyecto de Tesis | G16: ESPEJO ABARCA KAROLA | J16: =TODAY() -> 46206 | K16: ='RESOLUCIONES 2022'!$C16-'RESOLUCIONES 2022'!$J16 -> -1617
A17: Enviado | B17: 15 | C17: 44589 | D17: ALVAREZ RIOS CRISTINA | E17: 019100058A | F17: Cambio de Asesor del Proyecto de Tesis | G17: DE LA TORRE DUEÑAS CLETO | J17: =TODAY() -> 46206 | K17: ='RESOLUCIONES 2022'!$C17-'RESOLUCIONES 2022'!$J17 -> -1617
A18: Enviado | B18: 16 | C18: 44592 | D18: GAMARRA SALAS JONATHAN | E18: 015101318K | F18: EXPEDIENTE APTO AL GRADO | J18: =TODAY() -> 46206 | K18: ='RESOLUCIONES 2022'!$C18-'RESOLUCIONES 2022'!$J18 -> -1614
A19: Enviado | B19: 17 | C19: 44592 | D19: MERINO YEPEZ ROBERT MILTON | E19: 015201383I | F19: EXPEDIENTE APTO AL GRADO | J19: =TODAY() -> 46206 | K19: ='RESOLUCIONES 2022'!$C19-'RESOLUCIONES 2022'!$J19 -> -1614
A20: Enviado | B20: 18 | C20: 44592 | D20: BERDEJO GUADALUPE SONIA | E20: 019200333D | F20: EXPEDIENTE APTO AL GRADO | J20: =TODAY() -> 46206 | K20: ='RESOLUCIONES 2022'!$C20-'RESOLUCIONES 2022'!$J20 -> -1614
A21: Enviado | B21: 19 | C21: 44592 | D21: TRIGOSO DELGADO JORGE OSCAR | E21: 018200301F | F21: EXPEDIENTE APTO AL GRADO | J21: =TODAY() -> 46206 | K21: ='RESOLUCIONES 2022'!$C21-'RESOLUCIONES 2022'!$J21 -> -1614
A22: Enviado | B22: 20 | C22: 44592 | D22: ALVAREZ LOPINTA CELIA | E22: 018300038E | F22: EXPEDIENTE APTO AL GRADO | J22: =TODAY() -> 46206 | K22: ='RESOLUCIONES 2022'!$C22-'RESOLUCIONES 2022'!$J22 -> -1614
B23: 21 | C23: 44592 | D23: VERA MUÑOZ ESTEFANY LORENA | E23: 020300199D | F23: RECONOCER NOTA SUBSANACION | G23: RIVERA MUÑOZ JORGE LEONCIO | J23: =TODAY() -> 46206 | K23: ='RESOLUCIONES 2022'!$C23-'RESOLUCIONES 2022'!$J23 -> -1614
B24: 22 | C24: 44592 | D24: TEJEIRA FLORES DANIEL | E24: 020300154K | F24: RECONOCER NOTA SUBSANACION | G24: MURILLO FLORES LUIS FERNANDO | J24: =TODAY() -> 46206 | K24: ='RESOLUCIONES 2022'!$C24-'RESOLUCIONES 2022'!$J24 -> -1614
B25: 23 | C25: 44592 | D25: SEQUEIROS MORALES JOSE LUIS | E25: 019300023G | F25: RECONOCER NOTA SUBSANACION | G25: MURILLO FLORES LUIS FERNANDO | J25: =TODAY() -> 46206 | K25: ='RESOLUCIONES 2022'!$C25-'RESOLUCIONES 2022'!$J25 -> -1614
B26: 24 | C26: 44592 | D26: SANCHEZ ACURIO RUTH MARTHA | E26: 020300152H | F26: RECONOCER NOTA SUBSANACION | G26: MURILLO FLORES LUIS FERNANDO | J26: =TODAY() -> 46206 | K26: ='RESOLUCIONES 2022'!$C26-'RESOLUCIONES 2022'!$J26 -> -1614
B27: 25 | C27: 44592 | D27: QUISPE CHIPA JANETH MILAGROS | E27: 020300150E | F27: RECONOCER NOTA SUBSANACION | G27: MURILLO FLORES LUIS FERNANDO | J27: =TODAY() -> 46206 | K27: ='RESOLUCIONES 2022'!$C27-'RESOLUCIONES 2022'!$J27 -> -1614
B28: 26 | C28: 44592 | D28: PUMA CCAÑIHUA PERCY | E28: 020300149G | F28: RECONOCER NOTA SUBSANACION | G28: MURILLO FLORES LUIS FERNANDO | J28: =TODAY() -> 46206 | K28: ='RESOLUCIONES 2022'!$C28-'RESOLUCIONES 2022'!$J28 -> -1614
B29: 27 | C29: 44592 | D29: PACCO CJURO ZORAIDA | E29: 019300019J | F29: RECONOCER NOTA SUBSANACION | G29: MURILLO FLORES LUIS FERNANDO | J29: =TODAY() -> 46206 | K29: ='RESOLUCIONES 2022'!$C29-'RESOLUCIONES 2022'!$J29 -> -1614
B30: 28 | C30: 44592 | D30: FLOREZ CORIMANYA ANGEL VITALIANO | E30: 020300139A | F30: RECONOCER NOTA SUBSANACION | G30: MURILLO FLORES LUIS FERNANDO | J30: =TODAY() -> 46206 | K30: ='RESOLUCIONES 2022'!$C30-'RESOLUCIONES 2022'!$J30 -> -1614
B31: 29 | C31: 44592 | D31: FLOREZ CORIMANYA ANGEL VITALIANO | E31: 020300139A | F31: RECONOCER NOTA SUBSANACION | G31: MURILLO FLORES LUIS FERNANDO | J31: =TODAY() -> 46206 | K31: ='RESOLUCIONES 2022'!$C31-'RESOLUCIONES 2022'!$J31 -> -1614
B32: 30 | C32: 44592 | D32: SANTA CRUZ QUISPE YONY | E32: 020300153D | F32: RECONOCER NOTA SUBSANACION | G32: MURILLO FLORES LUIS FERNANDO | J32: =TODAY() -> 46206 | K32: ='RESOLUCIONES 2022'!$C32-'RESOLUCIONES 2022'!$J32 -> -1614
B33: 31 | C33: 44592 | D33: BLANCO CUPARA EDERWALDO | E33: 020300129F | F33: RECONOCER NOTA SUBSANACION | G33: MURILLO FLORES LUIS FERNANDO | J33: =TODAY() -> 46206 | K33: ='RESOLUCIONES 2022'!$C33-'RESOLUCIONES 2022'!$J33 -> -1614
B34: 32 | C34: 44592 | D34: ALCCA QUINTE HENRY MICHAEL | E34: 020300127C | F34: RECONOCER NOTA SUBSANACION | G34: MURILLO FLORES LUIS FERNANDO | J34: =TODAY() -> 46206 | K34: ='RESOLUCIONES 2022'!$C34-'RESOLUCIONES 2022'!$J34 -> -1614
... B37: 35 | C37: 44592 | D37: CABRERA CASTILLA EDDY JONATAN | E37: 021300115D | F37: RECONOCER NOTA SUBSANACION | G37: HOLGUIN HERRERA DONNY ALEJANDRO | J37: =TODAY() -> 46206 | K37: ='RESOLUCIONES 2022'!$C37-'RESOLUCIONES 2022'!$J37 -> -1614
A38: Enviado | B38: 36 | C38: 44595 | D38: HUANCAHUIRE ALLENDE YORDAN JESÚS | E38: 018200259J | F38: EXPEDIENTE APTO AL GRADO | J38: =TODAY() -> 46206 | K38: ='RESOLUCIONES 2022'!$C38-'RESOLUCIONES 2022'!$J38 -> -1611
A39: Enviado | B39: 37 | C39: 44595 | D39: HUARANCCA VALDERRAMA ROSA AMALIA | E39: 013201123I | F39: EXPEDIENTE APTO AL GRADO | J39: =TODAY() -> 46206 | K39: ='RESOLUCIONES 2022'!$C39-'RESOLUCIONES 2022'!$J39 -> -1611
A40: Enviado | B40: 38 | C40: 44595 | D40: RIVAS LOAIZA CONNY | E40: 018300033C | F40: EXPEDIENTE APTO AL GRADO | J40: =TODAY() -> 46206 | K40: ='RESOLUCIONES 2022'!$C40-'RESOLUCIONES 2022'!$J40 -> -1611
A41: Enviado | B41: 39 | C41: 44595 | D41: ROJAS PARIONA CARMEN ROSA | E41: 013201095E | F41: EXPEDIENTE APTO AL GRADO | J41: =TODAY() -> 46206 | K41: ='RESOLUCIONES 2022'!$C41-'RESOLUCIONES 2022'!$J41 -> -1611
A42: Enviado | B42: 40 | C42: 44595 | D42: PUMA RIMACHI JHON RONALD | E42: 020300101D | F42: NOMBRAMIENTO DE ASESOR | G42: TRESIERRA PANTIGOZO ABEL | J42: =TODAY() -> 46206 | K42: ='RESOLUCIONES 2022'!$C42-'RESOLUCIONES 2022'!$J42 -> -1611
A43: Enviado | B43: 41 | C43: 44595 | D43: GUEVARA LAZO PEDRO ARTURO | E43: 020300176D | F43: NOMBRAMIENTO DE ASESOR | G43: RIVERA MUÑOZ JORGE LEONCIO | J43: =TODAY() -> 46206 | K43: ='RESOLUCIONES 2022'!$C43-'RESOLUCIONES 2022'!$J43 -> -1611
A44: Enviado | B44: 42 | C44: 44595 | D44: ZEA CONCHA JUAN SEBASTIAN | E44: 020200040C | F44: NOMBRAMIENTO DE ASESOR | G44: CAVERO PACHECO SHAILI JULIE | J44: =TODAY() -> 46206 | K44: ='RESOLUCIONES 2022'!$C44-'RESOLUCIONES 2022'!$J44 -> -1611
A45: Enviado | B45: 43 | C45: 44595 | D45: BERNILLA REYES MILTON | E45: 020200063C | F45: NOMBRAMIENTO DE ASESOR | G45: JUSTO GOMEZ CESAR ALAN | J45: =TODAY() -> 46206 | K45: ='RESOLUCIONES 2022'!$C45-'RESOLUCIONES 2022'!$J45 -> -1611
A46: Enviado | B46: 44 | C46: 44595 | D46: ANDRADE TUPA LIZBETH LUCERO | E46: 020100078I | F46: NOMBRAMIENTO DE ASESOR | G46: SUAREZ SANCHEZ RICHARD | J46: =TODAY() -> 46206 | K46: ='RESOLUCIONES 2022'!$C46-'RESOLUCIONES 2022'!$J46 -> -1611
A47: Enviado | B47: 45 | C47: 44595 | D47: CARPIO PEÑA GUSTAVO GERSON | E47: 019100096K | F47: NOMBRAMIENTO DE ASESOR | G47: JAYO SILVA CARLOS EDUARDO | J47: =TODAY() -> 46206 | K47: ='RESOLUCIONES 2022'!$C47-'RESOLUCIONES 2022'!$J47 -> -1611
A48: Enviado | B48: 46 | C48: 44595 | D48: LOAIZA MORALES MAROLI ERNESTINA | E48: 018100040F | F48: NOMBRAMIENTO DE ASESOR | G48: DELGADO OTAZU ERICSON | J48: =TODAY() -> 46206 | K48: ='RESOLUCIONES 2022'!$C48-'RESOLUCIONES 2022'!$J48 -> -1611
A49: Enviado | B49: 47 | C49: 44595 | D49: GALINDO LUQUE YREMY VANESSA | E49: 020300140J | F49: NOMBRAMIENTO DE ASESOR | G49: ZUÑIGA MARINO MIGUEL ANGEL | J49: =TODAY() -> 46206 | K49: ='RESOLUCIONES 2022'!$C49-'RESOLUCIONES 2022'!$J49 -> -1611
A50: Enviado | B50: 48 | C50: 44595 | D50: MASIAS CONDORI MAURO CRISOSTOMO | E50: 020100017J | F50: NOMBRAMIENTO DE ASESOR | G50: AGUIRRE ESPINOZA EDWARDS JESUS | J50: =TODAY() -> 46206 | K50: ='RESOLUCIONES 2022'!$C50-'RESOLUCIONES 2022'!$J50 -> -1611
A51: Enviado | B51: 49 | C51: 44595 | D51: CUTUCALLA MOLLEHUANCA FREDY GERMAN | E51: 016110273E | F51: DICTAMEN DE TESIS | J51: =TODAY() -> 46206 | K51: ='RESOLUCIONES 2022'!$C51-'RESOLUCIONES 2022'!$J51 -> -1611
A52: Enviado | B52: 50 | C52: 44596 | D52: QUISPE BEJAR JOSE LUIS | E52: 019200357K | F52: DICTAMEN DE PROYECTO | J52: =TODAY() -> 46206 | K52: ='RESOLUCIONES 2022'!$C52-'RESOLUCIONES 2022'!$J52 -> -1610
A53: Enviado | B53: 51 | C53: 44596 | D53: PERALTA ZANABRIA LEONARDO | E53: 016102195I | F53: DICTAMEN DE PROYECTO | J53: =TODAY() -> 46206 | K53: ='RESOLUCIONES 2022'!$C53-'RESOLUCIONES 2022'!$J53 -> -1610
A54: Enviado | B54: 52 | C54: 44596 | D54: HUAYCOCHEA NUÑEZ DE LA TORRE FLOR DE MARIA | E54: 018300025K | F54: DICTAMEN DE PROYECTO | J54: =TODAY() -> 46206 | K54: ='RESOLUCIONES 2022'!$C54-'RESOLUCIONES 2022'!$J54 -> -1610
A55: Enviado | B55: 53 | C55: 44596 | D55: DURAND FLORES YURI ROBINSON | E55: 021100005K | F55: DICTAMEN DE PROYECTO | J55: =TODAY() -> 46206 | K55: ='RESOLUCIONES 2022'!$C55-'RESOLUCIONES 2022'!$J55 -> -1610
A56: Enviado | B56: 54 | C56: 44596 | D56: YARIN PARILLO EUSEBIO HENRY | E56: 018200136E | F56: DICTAMEN DE PROYECTO | J56: =TODAY() -> 46206 | K56: ='RESOLUCIONES 2022'!$C56-'RESOLUCIONES 2022'!$J56 -> -1610
A57: Enviado | B57: 55 | C57: 44596 | D57: DUEÑAS DUEÑAS BERTHA ASUNCION | E57: 019100006A | F57: DICTAMEN DE PROYECTO | J57: =TODAY() -> 46206 | K57: ='RESOLUCIONES 2022'!$C57-'RESOLUCIONES 2022'!$J57 -> -1610
A58: Enviado | B58: 56 | C58: 44596 | D58: HARO CHALLCO GIANFRANCO STEVENS | E58: 018300141K | F58: DICTAMEN DE PROYECTO | J58: =TODAY() -> 46206 | K58: ='RESOLUCIONES 2022'!$C58-'RESOLUCIONES 2022'!$J58 -> -1610
A59: Enviado | B59: 57 | C59: 44596 | D59: HUANCA SOTO JUAN BAUTISTA | E59: 019100009K | F59: DICTAMEN DE PROYECTO | J59: =TODAY() -> 46206 | K59: ='RESOLUCIONES 2022'!$C59-'RESOLUCIONES 2022'!$J59 -> -1610
A60: Enviado | B60: 58 | C60: 44596 | D60: CONTRERAS UMPIRE JULIO CESAR | E60: 019300039K | F60: DICTAMEN DE PROYECTO | J60: =TODAY() -> 46206 | K60: ='RESOLUCIONES 2022'!$C60-'RESOLUCIONES 2022'!$J60 -> -1610
A61: Enviado | B61: 59 | C61: 44596 | D61: PEREZ ANAMPA SHEILA MILAGROS | E61: 020100071D | F61: DICTAMEN DE PROYECTO | J61: =TODAY() -> 46206 | K61: ='RESOLUCIONES 2022'!$C61-'RESOLUCIONES 2022'!$J61 -> -1610
A62: Enviado | B62: 60 | C62: 44596 | D62: FERNANDEZ VILLAFUERTE KAEL STEVEN | E62: 020100091E | F62: DICTAMEN DE PROYECTO | J62: =TODAY() -> 46206 | K62: ='RESOLUCIONES 2022'!$C62-'RESOLUCIONES 2022'!$J62 -> -1610
... A65: Enviado | B65: 63 | C65: 44596 | D65: CCOPA ALEGRE JENNEFER PAOLA | E65: 021100060A | F65: DICTAMEN DE PROYECTO | J65: =TODAY() -> 46206 | K65: ='RESOLUCIONES 2022'!$C65-'RESOLUCIONES 2022'!$J65 -> -1610
A66: Enviado | B66: 64 | C66: 44599 | D66: PANDO DELGADILLO JUAN EDUARDO | E66: 021100077A | F66: NOMBRAMIENTO DE ASESOR | G66: AGUIRRE ESPINOZA EDWARDS JESUS | J66: =TODAY() -> 46206 | K66: ='RESOLUCIONES 2022'!$C66-'RESOLUCIONES 2022'!$J66 -> -1607
A67: Enviado | B67: 65 | C67: 44599 | D67: SILVA HURTADO JULIO ROMMEL | E67: 020100101K | F67: NOMBRAMIENTO DE ASESOR | G67: MELENDREZ VELASCO ELIAS | J67: =TODAY() -> 46206 | K67: ='RESOLUCIONES 2022'!$C67-'RESOLUCIONES 2022'!$J67 -> -1607
A68: Enviado | B68: 66 | C68: 44599 | D68: MAMANI ALEGRIA CARMEN LUCERO | E68: 020100068C | F68: RECTIFICAR NOTA | J68: =TODAY() -> 46206 | K68: ='RESOLUCIONES 2022'!$C68-'RESOLUCIONES 2022'!$J68 -> -1607
A69: Enviado | B69: 67 | C69: 44599 | D69: CARDONA RIVERO ANAHI KARINA | E69: 017200049F | F69: AMPLIACION INSCRIPCION DE PROYECTO | J69: =TODAY() -> 46206 | K69: ='RESOLUCIONES 2022'!$C69-'RESOLUCIONES 2022'!$J69 -> -1607
A70: Enviado | B70: 68 | C70: 44599 | D70: CORDOVA CONGA CARLOS EDUARDO | E70: 014101466K | F70: AMPLIACION INSCRIPCION DE PROYECTO | J70: =TODAY() -> 46206 | K70: ='RESOLUCIONES 2022'!$C70-'RESOLUCIONES 2022'!$J70 -> -1607
A71: Enviado | B71: 69 | C71: 44599 | D71: HUAMAN AFAN JUAN | E71: 017300200H | F71: AMPLIACION INSCRIPCION DE PROYECTO | J71: =TODAY() -> 46206 | K71: ='RESOLUCIONES 2022'!$C71-'RESOLUCIONES 2022'!$J71 -> -1607
A72: Enviado | B72: 70 | C72: 44599 | D72: PIMENTEL ELGUERA MARCELINO | E72: 017300207B | F72: AMPLIACION INSCRIPCION DE PROYECTO | J72: =TODAY() -> 46206 | K72: ='RESOLUCIONES 2022'!$C72-'RESOLUCIONES 2022'!$J72 -> -1607
A73: Enviado | B73: 71 | C73: 44599 | D73: ATAUCHI RAVELO ALMENDRA | E73: 017300086K | F73: INSCRIPCION DE PROYECTO | G73: QUISPE AYALA YESENIA | H73: SALAZAR MUJICA ALAN FELIPE | I73: “CRITERIOS CONSTITUCIONALES ELEMENTALES PARA EL RECONOCIMIENTO DE LOS DERECHOS INNOMINADOS DEL ARTÍCULO 3 DE LA CONSTITUCIÓN POLÍTICA DEL PERÚ DE 1993 DESDE LA PERSPECTIVA DEL PRINCIPIO DE LA DIGNIDAD HUMANA EN LOS PROCESOS DE AMPARO”, | J73: =TODAY() -> 46206 | K73: ='RESOLUCIONES 2022'!$C73-'RESOLUCIONES 2022'!$J73 -> -1607
A74: Enviado | B74: 72 | C74: 44599 | D74: FRISANCHO CAMERO MILUSKA | E74: 019300109I | F74: INSCRIPCION DE PROYECTO | G74: SOTO BRINGAS ROSARIO ISABE | H74: CASTRO CUBA BARINEZA ISAAC ENRIQUE | I74: “EFECTO HEPATOPROTECTOR DEL EXTRACTO ETANÓLICO Y ACUOSO DE HOJAS Y FLORES DE LAVATERA ARBÓREA VAR. SP. (MALVA SILVESTRE) EN RATONES DE LABORATORIO, CUSCO-2021”, | J74: =TODAY() -> 46206 | K74: ='RESOLUCIONES 2022'!$C74-'RESOLUCIONES 2022'!$J74 -> -1607
A75: Enviado | B75: 73 | C75: 44599 | D75: FLOREZ RONDAN VERONIKA STEPHANIE | E75: 021100065C | F75: INSCRIPCION DE PROYECTO | J75: =TODAY() -> 46206 | K75: ='RESOLUCIONES 2022'!$C75-'RESOLUCIONES 2022'!$J75 -> -1607
A76: Enviado | B76: 74 | C76: 44599 | D76: LOAYZA ECHEGARAY LUZ GLORIA | E76: 019300132K | F76: INSCRIPCION DE PROYECTO | J76: =TODAY() -> 46206 | K76: ='RESOLUCIONES 2022'!$C76-'RESOLUCIONES 2022'!$J76 -> -1607
A77: Enviado | B77: 75 | C77: 44599 | D77: VALER FIGUEROA WALTER | E77: 011270077D | F77: INSCRIPCION DE PROYECTO | J77: =TODAY() -> 46206 | K77: ='RESOLUCIONES 2022'!$C77-'RESOLUCIONES 2022'!$J77 -> -1607
A78: Enviado | B78: 76 | C78: 44599 | D78: CHECYA HUANCA NANCY DIANA | E78: 018300001D | F78: INSCRIPCION DE PROYECTO | J78: =TODAY() -> 46206 | K78: ='RESOLUCIONES 2022'!$C78-'RESOLUCIONES 2022'!$J78 -> -1607
A79: Enviado | B79: 77 | C79: 44599 | D79: HIDALGO LEON PILAR VANESSA | E79: 012101117H | F79: INSCRIPCION DE PROYECTO | J79: =TODAY() -> 46206 | K79: ='RESOLUCIONES 2022'!$C79-'RESOLUCIONES 2022'!$J79 -> -1607
A80: Enviado | B80: 78 | C80: 44599 | D80: CARRASCO DELGADO KAREN MICAELA | E80: 020100108E | F80: INSCRIPCION DE PROYECTO | J80: =TODAY() -> 46206 | K80: ='RESOLUCIONES 2022'!$C80-'RESOLUCIONES 2022'!$J80 -> -1607
A81: Enviado | B81: 79 | C81: 44599 | D81: CASAFRANCA BORDA JORGE OMAR | E81: 013200912J | F81: INSCRIPCION DE PROYECTO | J81: =TODAY() -> 46206 | K81: ='RESOLUCIONES 2022'!$C81-'RESOLUCIONES 2022'!$J81 -> -1607
A82: Enviado | B82: 80 | C82: 44599 | D82: JORDAN ALVAREZ DIEGO FRANCISCO | E82: 019300130H | F82: INSCRIPCION DE PROYECTO | J82: =TODAY() -> 46206 | K82: ='RESOLUCIONES 2022'!$C82-'RESOLUCIONES 2022'!$J82 -> -1607
A83: Enviado | B83: 81 | C83: 44601 | D83: ARTETA VALDIVIA MARÍA DEL CARMEN | E83: 018200093D | F83: DICTAMEN DE TESIS | J83: =TODAY() -> 46206 | K83: ='RESOLUCIONES 2022'!$C83-'RESOLUCIONES 2022'!$J83 -> -1605
A84: Enviado | B84: 82 | C84: 44601 | D84: CURIZA VILCA LYLY KARINA | E84: 020200043B | F84: DICTAMEN DE TESIS | J84: =TODAY() -> 46206 | K84: ='RESOLUCIONES 2022'!$C84-'RESOLUCIONES 2022'!$J84 -> -1605
A85: Enviado | B85: 83 | C85: 44601 | D85: ZUÑIGA MORALES OMAR NILO | E85: 018100051H | F85: DICTAMEN DE TESIS | J85: =TODAY() -> 46206 | K85: ='RESOLUCIONES 2022'!$C85-'RESOLUCIONES 2022'!$J85 -> -1605
A86: Enviado | B86: 84 | C86: 44606 | D86: KADAGAND ALVARADO LISSETH | E86: 019300131D | F86: INSCRIPCION DE PROYECTO | J86: =TODAY() -> 46206 | K86: ='RESOLUCIONES 2022'!$C86-'RESOLUCIONES 2022'!$J86 -> -1600
... A91: Enviado | B91: 89 | C91: 44606 | D91: CORNEJO SANCHEZ MARILIANA | E91: 019200337J | F91: INSCRIPCION DE PROYECTO | J91: =TODAY() -> 46206 | K91: ='RESOLUCIONES 2022'!$C91-'RESOLUCIONES 2022'!$J91 -> -1600
A92: Enviado | B92: 90 | C92: 44606 | D92: TEJEIRA FLORES DANIEL | E92: 020300154K | F92: AUTORIZAR LA SUBSANACION | G92: MURILLO FLORES LUIS FERNANDO | J92: =TODAY() -> 46206 | K92: ='RESOLUCIONES 2022'!$C92-'RESOLUCIONES 2022'!$J92 -> -1600
A93: Enviado | B93: 91 | C93: 44608 | D93: ANDRADE TUPA CARMEN PATRICIA | E93: 020100077B | F93: INSCRIPCION DE PROYECTO | J93: =TODAY() -> 46206 | K93: ='RESOLUCIONES 2022'!$C93-'RESOLUCIONES 2022'!$J93 -> -1598
A94: Enviado | B94: 92 | C94: 44608 | D94: UMIYAURI QUIRITA PAOLA JACKELIN | E94: 017300109K | F94: INSCRIPCION DE PROYECTO | J94: =TODAY() -> 46206 | K94: ='RESOLUCIONES 2022'!$C94-'RESOLUCIONES 2022'!$J94 -> -1598
A95: Enviado | B95: 93 | C95: 44608 | D95: CALLIRGOS SOLARI TATIANA TAYANA | E95: 014101462E | F95: AUTORIZAR ENCUESTA | J95: =TODAY() -> 46206 | K95: ='RESOLUCIONES 2022'!$C95-'RESOLUCIONES 2022'!$J95 -> -1598
A96: Enviado | B96: 94 | C96: 44608 | D96: RECONOCIMIENT Y FELICITACION | F96: RECONOCIMIENT Y FELICITACION | J96: =TODAY() -> 46206 | K96: ='RESOLUCIONES 2022'!$C96-'RESOLUCIONES 2022'!$J96 -> -1598
A97: Enviado | B97: 95 | C97: 44609 | D97: APARICIO JURADO DINA LIZBETH | E97: 018200028H | F97: DICTAMEN DE PROYECTO | J97: =TODAY() -> 46206 | K97: ='RESOLUCIONES 2022'!$C97-'RESOLUCIONES 2022'!$J97 -> -1597
A98: Enviado | B98: 96 | C98: 44609 | D98: CARDENAS FLORES ROCIO MARLENI | E98: 017200026F | F98: CAMBIO DE TITULO | J98: =TODAY() -> 46206 | K98: ='RESOLUCIONES 2022'!$C98-'RESOLUCIONES 2022'!$J98 -> -1597
A99: Enviado | B99: 97 | C99: 44609 | D99: SANJINES PEÑA YASKARA | E99: 016102357I | F99: INSCRIPCION DE PROYECTO | J99: =TODAY() -> 46206 | K99: ='RESOLUCIONES 2022'!$C99-'RESOLUCIONES 2022'!$J99 -> -1597
A100: Enviado | B100: 98 | C100: 44609 | D100: CUTIMBO ALFARO DAVID EDUARDO | E100: 017200093E | F100: CAMBIO DE TITULO | J100: =TODAY() -> 46206 | K100: ='RESOLUCIONES 2022'!$C100-'RESOLUCIONES 2022'!$J100 -> -1597
A101: Enviado | B101: 99 | C101: 44609 | D101: CUTIMBO ALFARO DAVID EDUARDO | E101: 017200093E | F101: DICTAMEN DE TESIS | J101: =TODAY() -> 46206 | K101: ='RESOLUCIONES 2022'!$C101-'RESOLUCIONES 2022'!$J101 -> -1597
A102: Enviado | B102: 100 | C102: 44613 | D102: MORALES ARAGON CLAUDIA ISABEL | E102: 012200977E | F102: FIJAR FECHA Y HORA | J102: =TODAY() -> 46206 | K102: ='RESOLUCIONES 2022'!$C102-'RESOLUCIONES 2022'!$J102 -> -1593
A103: Enviado | B103: 101 | C103: 44613 | D103: PEÑA CHAVEZ MANUEL SEYBERLING | E103: 018100071I | F103: EXPEDIENTE APTO AL GRADO | J103: =TODAY() -> 46206 | K103: ='RESOLUCIONES 2022'!$C103-'RESOLUCIONES 2022'!$J103 -> -1593
A104: Enviado | B104: 102 | C104: 44613 | D104: PHOCO TTITO ELVA CAROLINA | E104: 019300188F | F104: EXPEDIENTE APTO AL GRADO | J104: =TODAY() -> 46206 | K104: ='RESOLUCIONES 2022'!$C104-'RESOLUCIONES 2022'!$J104 -> -1593
A105: Enviado | B105: 103 | C105: 44613 | D105: CASTAÑEDA AVENDAÑO OSCAR | E105: 019300035E | F105: NOMBRAMIENTO DE ASESOR | G105: MELENDREZ VELASCO ELIAS | J105: =TODAY() -> 46206 | K105: ='RESOLUCIONES 2022'!$C105-'RESOLUCIONES 2022'!$J105 -> -1593
A106: Enviado | B106: 104 | C106: 44613 | D106: GUERRA POLANCO GERSON GABRIEL | E106: 019300012E | F106: NOMBRAMIENTO DE ASESOR | G106: SALAZAR MUJICA ALAN FELIPE | J106: =TODAY() -> 46206 | K106: ='RESOLUCIONES 2022'!$C106-'RESOLUCIONES 2022'!$J106 -> -1593
A107: Enviado | B107: 105 | C107: 44613 | D107: CORZO PALOMO ERIKA ELEANA | E107: 018300036B | F107: INSCRIPCION DE PROYECTO | J107: =TODAY() -> 46206 | K107: ='RESOLUCIONES 2022'!$C107-'RESOLUCIONES 2022'!$J107 -> -1593
A108: Enviado | B108: 106 | C108: 44613 | D108: OLIVARES TORRE GRETEL ROXANA | E108: 019200033K | F108: INSCRIPCION DE PROYECTO | J108: =TODAY() -> 46206 | K108: ='RESOLUCIONES 2022'!$C108-'RESOLUCIONES 2022'!$J108 -> -1593
...

Sheet RESOLUCIONES 2021
A1: RESOLUCIONES EMITIDAS 2021 | J1: CARGOS
A2: N° SOLICITUD | B2: RESOL. N° | C2: FECHA | D2: NOMBRES Y APELLIDOS | E2: CODIGO2 | F2: TIPO DE RESOLUCION | G2: Obaservaciones | H2: RESOLUCION 2 | I2: Columna1 | J2: DICTAMEN 1 | K2: DICTAMEN 2 | L2: CARGO 3 | M2: CARGO 4 | N2: CARGO 5
A3: Enviado | B3: 1 | C3: 44200 | D3: APAZA CANAZA FELIPE | E3: 019300030C | F3: NOMBRAMIENTO ASESOR | G3: SHAILI JULIE CAVERO PACHECO
A4: Enviado | B4: 2 | C4: 44200 | D4: TELLO TACO BRYAN MANUEL​ | E4: 019300192C | F4: NOMBRAMIENTO ASESOR | G4: CARLOS ALBERTO PASTOR CARRASCO
A5: Enviado | B5: 3 | C5: 44200 | D5: CASTRO VEGA KARLA VERENISSE | E5: 017200265K | F5: NOMBRAMIENTO ASESOR | G5: FERNANDO PHILCO PRADO
A6: Enviado | B6: 4 | C6: 44200 | D6: FLORES MORALES NAY RUTH | E6: 019300181A | F6: NOMBRAMIENTO ASESOR | G6: CARLOS ALBERTO PASTOR CARRASCO,
A7: Enviado | B7: 5 | C7: 44200 | D7: MAGUIÑA APAZA ANNY ISABEL | E7: 018200066G | F7: INSCRIPCION DE PROYECTO
A8: Enviado | B8: 6 | C8: 44200 | D8: ANAYA CAHUA LUIS CARLOS | E8: 014101510J | F8: INSCRIPCION DE PROYECTO
A9: Enviado | B9: 7 | C9: 44200 | D9: BACA UMERES ISELA | E9: 008270004B | F9: INSCRIPCION DE PROYECTO
A10: Enviado | B10: 8 | C10: 44200 | D10: QUISPE RAMOS ESTELA | E10: 018200298E | F10: INSCRIPCION DE PROYECTO
A11: Enviado | B11: 9 | C11: 44200 | D11: FERNANDEZ LARA ALEX | E11: 017200169A | F11: INSCRIPCION DE PROYECTO
A12: Enviado | B12: 10 | C12: 44200 | D12: HUILLCAHUA SIERRA HILBERHT | E12: 019200343J | F12: DICTAMEN DE PROYECTO
A13: Enviado | B13: 11 | C13: 44200 | D13: ​ CHOQQUENAYRA CHOQUENEYRA ZENAIDA SOFIA | E13: 019300203E | F13: DICTAMEN DE PROYECTO
A14: Enviado | B14: 12 | C14: 44200 | D14: GARCIA CUIPA EDER | E14: 019100135F | F14: DICTAMEN DE PROYECTO | J14: Herminia Naveda De Aramburu
A15: Enviado | B15: 13 | C15: 44200 | D15: TRIGOSO DELGADO JORGE OSCAR | E15: 018200301F | F15: DICTAMEN DE PROYECTO
A16: Enviado | B16: 14 | C16: 44200 | D16: MAYHUIRE MONTOYA VICTOR ABRAHAM | E16: 019200153F | F16: DICTAMEN DE PROYECTO
A17: Enviado | B17: 15 | C17: 44200 | D17: GUTIERREZ ACUÑA YENI | E17: 018100060G | F17: CAMBIO DE TITULO DE LA TESIS
B18: 16 | C18: 44200 | D18: MOSQUEIRA VILLALBA TANIA | E18: 016102191C | F18: ELEVAR AL VRAC | G18: SEGURIDAD INDUSTRIAL Y MEDIO AMBIENTE
B19: 17 | C19: 44200 | D19: HIDALGO LEON MANUEL EDUARDO | E19: 014101473G | F19: ELEVAR AL VRAC | G19: DOCENCIA UNIVERSITARIA
B20: 18 | C20: 44200 | D20: RIVERO YNFANTAS FERNANDO | E20: 012200935K | F20: ELEVAR AL VRAC | G20: DOCTORADO EN DERECHO
B21: 19 | C21: 44200 | D21: HUAMAN FARFAN TAHIRI | E21: 43550804 | F21: ELEVAR AL VRAC | G21: MAESTRIA EN ESTOMATOLOGIA
B22: 20
A23: Enviado | B23: 21 | C23: 44238 | D23: CALDERON SEGURA JUAN CARLOS FIDEL | E23: 017200232E | F23: INSCRIPCION DE PROYECTO
A24: Enviado | B24: 22 | C24: 44238 | D24: PUMA HUANCO LIZBETH EVELYN | E24: 019300164J | F24: RECONOCER SUBSANACION | G24: WALTER HERNAN ARAUJO BERRÍO
A25: Enviado | B25: 23 | C25: 44238 | D25: WARTHON CALERO JARIB ANTENOR | E25: 017300111E | F25: AUTORIZAR SUBSANACION | G25: RIOS MAYORGA JULIO TRINIDAD | H25: falta reconocimiento
A26: Enviado | B26: 24 | C26: 44238 | D26: QUISPE CUSIHUAMAN MARIA ANGELICA | E26: 019300062B | F26: NOMBRAMIENTO ASESOR | G26: melendrez velasco elias
A27: Enviado | B27: 25 | C27: 44238 | D27: QUISPE DIAZ JEANETTE | E27: 019300063I | F27: NOMBRAMIENTO ASESOR | G27: melendrez velasco elias
A28: Enviado | B28: 26 | C28: 44238 | D28: NAVARRO GONZALES RAISA PAMELA | E28: 016102193F | F28: NOMBRAMIENTO ASESOR | G28: JHIMI WALTER PIETRI ABARCA
A29: Enviado | B29: 27 | C29: 44238 | D29: MARTINEZ ACURIO ANDREI | E29: 019300054J | F29: NOMBRAMIENTO ASESOR | G29: melendrez velasco elias
A30: Enviado | B30: 28 | C30: 44238 | D30: BUENO ALFEREZ JOSE LUIS | E30: 020100107I | F30: NOMBRAMIENTO ASESOR | G30: SHAILI JULIE CAVERO PACHECO
A31: Enviado | B31: 29 | C31: 44238 | D31: TELLO RONCAL ANGELA SANDRA | E31: 015101483A | F31: NOMBRAMIENTO ASESOR | G31: LUIS ALBERTO CHIHUANTITO ABAL
A32: Enviado | B32: 30 | C32: 44238 | D32: VEGA DUEÑAS KHALIL NASSIB | E32: 018200085A | F32: NOMBRAMIENTO ASESOR | G32: PAULA PATRICIA LUKSIC GIBAJA
A33: Enviado | B33: 31 | C33: 44238 | D33: PEREZ RAMOS JAVIER MAX | E33: 014101561C | F33: NOMBRAMIENTO ASESOR | G33: LILIANA CORONADO GAMARRA
A34: Enviado | B34: 32 | C34: 44238 | D34: ANDRADE TUPA CARMEN PATRICIA | E34: 020100077B | F34: NOMBRAMIENTO ASESOR | G34: PAULA PATRICIA LUKSIC GIBAJA
A35: Enviado | B35: 33 | C35: 44238 | D35: RIVERA ALARCON ELIANA LIA | E35: 020300191C | F35: NOMBRAMIENTO ASESOR | G35: JORGE LEONCIO RIVERA MUÑOZ
A36: Enviado | B36: 34 | C36: 44238 | D36: RAMOS MEZA CARLOS SAMUEL | E36: 018300035F | F36: NOMBRAMIENTO ASESOR | G36: EDWARDS JESUS AGUIRRE ESPINOZA
A37: Enviado | B37: 35 | C37: 44238 | D37: VALDIVIA SEGUNDO MERYL PRYCILA | E37: 019300073D | F37: NOMBRAMIENTO ASESOR | G37: FLORES CHAVEZ RUBEN JORGE
A38: Enviado | B38: 36 | C38: 44238 | D38: PUENTE DE LA VEGA CORONADO DANIEL FABRICIO | E38: 019300061F | F38: NOMBRAMIENTO ASESOR | G38: FLORES CHAVEZ RUBEN JORGE
A39: Enviado | B39: 37 | C39: 44238 | D39: PLETICKOSICH CUBA JHOVISSA | E39: 019300162G | F39: INSCRIPCION DE PROYECTO
A40: Enviado | B40: 38 | C40: 44238 | D40: GAMARRA SALAS JONATHAN | E40: 015101318K | F40: INSCRIPCION DE PROYECTO
A41: Enviado | B41: 39 | C41: 44238 | D41: VALVERDE GAVANCHO BELEN | E41: 016201411A | F41: INSCRIPCION DE PROYECTO
A42: Enviado | B42: 40 | C42: 44238 | D42: JORDAN CHILLITUPA NINOSKA JOYCE | E42: 019200279J | F42: INSCRIPCION DE PROYECTO
A43: Enviado | B43: 41 | C43: 44238 | D43: TERRAZAS GONZALES DUNIA VICTORIA | E43: 019200199F | F43: INSCRIPCION DE PROYECTO | G43: Doctor en Derecho
A44: Enviado | B44: 42 | C44: 44238 | D44: MOLERO DELGADO IVAN | E44: 014101641G | F44: EXPEDIENTE APTO AL GRADO | G44: MAESTRO EN INGENIERIA DE SISTEMAS CON MENCION EN ING. DE SOFTWARE
A45: Enviado | B45: 43 | C45: 44238 | D45: CALDERON CACERES RICHARD MARINO | E45: 012200966C | F45: EXPEDIENTE APTO AL GRADO | G45: MAESTRO EN ADMINISTRACIÓN DE NEGOCIOS
A46: Enviado | B46: 44 | C46: 44238 | D46: HUANCA POLIAR MARIA CLEOFE | E46: 016102099j | F46: EXPEDIENTE APTO AL GRADO | G46: MAESTRO EN DOCENCIA UNIVERSITARIA
A47: Enviado | B47: 45 | C47: 44238 | D47: RIOS QUISPICHO ZAIDINA | E47: 010200036H | F47: EXPEDIENTE APTO AL GRADO | G47: MAESTRIO EN DOCENCIA UNIVERSITARIA
A48: Enviado | B48: 46 | C48: 44238 | D48: GUTIERREZ ACUÑA YENI | E48: 018100060G | F48: EXPEDIENTE APTO AL GRADO | G48: DOCTOR EN MEDIO AMBIENTE Y DESARROLLO SOSTENIBLE
A49: Enviado | B49: 47 | C49: 44238 | D49: MAGUIÑA APAZA ANNY ISABEL | E49: 018200066G | F49: EXPEDIENTE APTO AL GRADO | G49: MAESTRO EN DOCENCIA UNIVERSITARIA
A50: Enviado | B50: 48 | C50: 44238 | D50: VALDEIGLESIAS MOSCOSO TOMIKO KARLA | E50: 018200082B | F50: EXPEDIENTE APTO AL GRADO | G50: MAESTRIO EN DOCENCIA UNIVERSITARIA
A51: Enviado | B51: 49 | C51: 44238 | D51: BACA GARCIA KEVIN | E51: 018200055E | F51: EXPEDIENTE APTO AL GRADO | G51: MAESTRIO EN DOCENCIA UNIVERSITARIA
A52: Enviado | B52: 50 | C52: 44238 | D52: MAMANI PARI DONATO | E52: 018100064B | F52: EXPEDIENTE APTO AL GRADO | G52: DOCTOR EN MEDIO AMBIENTE Y DESARROLLO SOSTENIBLE
A53: Enviado | B53: 51 | C53: 44238 | D53: MOINA HUARANCCA VICTORIANO | E53: 018100012B | F53: EXPEDIENTE APTO AL GRADO | G53: MAESTRO EN DOCENCIA UNIVERSITARIA
A54: Enviado | B54: 52 | C54: 44238 | D54: MORALES ARAGON CLAUDIA ISABEL | E54: 012200977E | F54: DICTAMEN DE TESIS
A55: Enviado | B55: 53 | C55: 44238 | D55: HURTADO CAHUANA LADY LIZBETH | E55: 015301262I | F55: DICTAMEN DE TESIS | J55: CLETO DE LA TORRE
A56: Enviado | B56: 54 | C56: 44238 | D56: CONDORHUAMAN YAURI ELLENKA LI | E56: 015301288H | F56: DICTAMEN DE TESIS
A57: Enviado | B57: 55 | C57: 44238 | D57: HUAMAN CUSIHUAMAN JULIO CESAR | E57: 015101410D | F57: DICTAMEN DE TESIS
A58: Enviado | B58: 56 | C58: 44238 | D58: ROJAS ZANABRIA MANUEL VALERIANO | E58: 016110262C | F58: DICTAMEN DE TESIS | J58: Elias Melendrez | K58: Carmen Rosa Araoz
A59: Enviado | B59: 57 | C59: 44238 | D59: MALPARTIDA OVIEDO DAYAN INGRID | E59: 017300020J | F59: DICTAMEN DE TESIS | K59: Elias Melendrez Velasco
A60: Enviado | B60: 58 | C60: 44245 | D60: ANCHARI OBLITAS YULIZA FRANCESCA | E60: 020300034E | F60: NOMBRAMIENTO ASESOR | G60: CLETO DE LA TORRE DUEÑAS
A61: Enviado | B61: 59 | C61: 44245 | D61: DELGADO CANDIA SONIA SOFIA | E61: 018200002I | F61: NOMBRAMIENTO ASESOR | G61: PAREDES GORDON TITO LIVIO
A62: Enviado | B62: 60 | C62: 44245 | D62: CAMACHO DELGADO MARCO SAMIR | E62: 017300035G | F62: NOMBRAMIENTO ASESOR | G62: PAREDES GORDON TITO LIVIO
A63: Enviado | B63: 61 | C63: 44245 | D63: FARFAN ESCOBEDO WERNER ADAIR | E63: 017300095J | F63: NOMBRAMIENTO ASESOR | G63: SILVIA ELENA AGUIRRE ABARCA
A64: Enviado | B64: 62 | C64: 44245 | D64: CALDERON CORDOVA KATHERINE​ | E64: 020300162C | F64: NOMBRAMIENTO ASESOR | G64: JORGE LEONCIO RIVERA MUÑOZ
A65: Enviado | B65: 63 | C65: 44245 | D65: HUALLPAYUNCA BACA JUAN CARLOS | E65: 019200170H | F65: NOMBRAMIENTO ASESOR | G65: LILIANA CORONADO GAMARRA
A66: Enviado | B66: 64 | C66: 44245 | D66: ORELLANA ECHEGARAY MACX ARTHUR | E66: 015301276J | F66: NOMBRAMIENTO ASESOR | G66: ROSMERY SILVA MINAURO
A67: Enviado | B67: 65 | C67: 44245 | D67: JARA BACA HILDA LAURA | E67: 019200439G​ | F67: NOMBRAMIENTO ASESOR | G67: EDWARDS JESUS AGUIRRE ESPINOZA
A68: Enviado | B68: 66 | C68: 44245 | D68: PAULETT SILVA KORI | E68: 019200014F | F68: DICTAMEN DE PROYECTO DE TESIS | G68: dispensa doctor Hildebrando
A69: Enviado | B69: 67 | C69: 44245 | D69: CHAVEZ SALAS DE ESTRADA SHIRLEY | E69: 017200140C | F69: DICTAMEN DE PROYECTO DE TESIS
A70: Enviado | B70: 68 | C70: 44245 | D70: ROMAN OCHOA SHELANY NAYDE | E70: 018300120C | F70: DICTAMEN DE PROYECTO DE TESIS | K70: Ricardo Sanchez Garrafa
A71: Enviado | B71: 69 | C71: 44245 | D71: CALSINA ACUÑA CARLA | E71: 019300033B | F71: DICTAMEN DE PROYECTO DE TESIS
A72: Enviado | B72: 70 | C72: 44245 | D72: CORONADO GAMARRA LILIANA | E72: 019200027K | F72: DICTAMEN DE PROYECTO DE TESIS
A73: Enviado | B73: 71 | C73: 44245 | D73: FUENTES HUAMANI JOHN ROSS | E73: 019300110G | F73: DICTAMEN DE PROYECTO DE TESIS
A74: Enviado | B74: 72 | C74: 44245 | D74: APAZA CANAZA FELIPE | E74: 019300030C | F74: DICTAMEN DE PROYECTO DE TESIS
A75: Enviado | B75: 73 | C75: 44245 | D75: SOTA PULIDO PILAR MARGOT | E75: 019200356D | F75: DICTAMEN DE PROYECTO DE TESIS
A76: Enviado | B76: 74 | C76: 44245 | D76: CHACHAIMA PUELLES DENIS | E76: 018300022A | F76: DICTAMEN DE PROYECTO DE TESIS
A77: Enviado | B77: 75 | C77: 44245 | D77: VERA MUÑOZ ESTEFANY LORENA | E77: 020300199D | F77: DICTAMEN DE PROYECTO DE TESIS | K77: Elias Melendrez Velasco
A78: Enviado | B78: 76 | C78: 44245 | D78: CRUZ LLERENA PAOLA MARILIA | E78: 019200250A | F78: DICTAMEN DE PROYECTO DE TESIS
A79: Enviado | B79: 77 | C79: 44245 | D79: NAVARRO GONZALES RAISA PAMELA | E79: 016102193F | F79: DICTAMEN DE PROYECTO DE TESIS
A80: Enviado | B80: 78 | C80: 44245 | D80: FLORES MORALES NAY RUTH | E80: 019300181A | F80: DICTAMEN DE PROYECTO DE TESIS
A81: Enviado | B81: 79 | C81: 44245 | D81: VERA MALDONADO LEOPOLDO | E81: 019200180C | F81: DICTAMEN DE PROYECTO DE TESIS
A82: Enviado | B82: 80 | C82: 44245 | D82: ARMUTO QUISPETUPA KATTLIN MILIANA | E82: 019200154B | F82: DICTAMEN DE PROYECTO DE TESIS
A83: Enviado | B83: 81 | C83: 44245 | D83: LUQUE FLOREZ DANY | E83: 017200273C | F83: DICTAMEN DE TESIS
A84: Enviado | B84: 82 | C84: 44245 | D84: PEÑA CHAVEZ MANUEL SEYBERLING | E84: 018100071I | F84: DICTAMEN DE PROYECTO DE TESIS
A85: Enviado | B85: 83 | C85: 44245 | D85: MADRID JIMÉNEZ DE ZAVALETA MARIA DEL ROSARIO | E85: ​ 008170044B | F85: DICTAMEN DE TESIS
A86: Enviado | B86: 84 | C86: 44245 | D86: VARGAS AÑAMACO LUIS ALBERTO | E86: ​ 008170073B | F86: DICTAMEN DE TESIS
A87: Enviado | B87: 85 | C87: 44245 | D87: DURAND GONZALES MIRIAM | E87: 008170028G | F87: DICTAMEN DE TESIS
A88: Enviado | B88: 86 | C88: 44245 | D88: MIRANDA SOLIS FRANKLIN | E88: 016102108I | F88: DICTAMEN DE PROYECTO DE TESIS
A89: Enviado | B89: 87 | C89: 44245 | D89: MAMANI CHOQUEHUAYTA MARTHA NANCY | E89: 008170045I | F89: DICTAMEN DE TESIS
B90: 88 | C90: 44245 | D90: RAMOS MEZA CARLOS SAMUEL | E90: 018300035F | F90: resolucion repetida
A91: Enviado | B91: 89 | C91: 44245 | D91: MIRANDA SOLIS FRANKLIN | E91: 019200034G | F91: NOMBRAMIENTO ASESOR | G91: William Senen Sarmiento Herrera
A92: Enviado | B92: 90 | C92: 44245 | D92: ALVAREZ CRUZ KATIA | E92: 017300084H | F92: NOMBRAMIENTO ASESOR | G92: LILIANA CORONADO GAMARRA
A93: Enviado | B93: 91 | C93: 44245 | D93: JARA BACA HILDA LAURA | E93: 019200439G | F93: NOMBRAMIENTO ASESOR | G93: EDWARDS JESUS AGUIRRE ESPINOZA
A94: Enviado | B94: 92 | C94: 44245 | D94: CARMONA CALLAÑAUPA JIMMY | E94: 017200263H | F94: NOMBRAMIENTO ASESOR | G94: CARLOS ALBERTO PASTOR CARRASCO
A95: Enviado | B95: 93 | C95: 44245 | D95: REYES PEÑA FRANKLIN ANDRES | E95: 020300045G | F95: NOMBRAMIENTO ASESOR | G95: ACO CORRALES, EDER ARTURO
A96: Enviado | B96: 94 | C96: 44245 | D96: MENDOZA RAMOS KATIA LISET | E96: 020300184G | F96: DICTAMEN DE PROYECTO DE TESIS
A97: Enviado | B97: 95 | C97: 44245 | D97: DELGADO SUAÑA GLORIA MARIA | E97: 020300170F | F97: DICTAMEN DE PROYECTO DE TESIS
A98: Enviado | B98: 96 | C98: 44245 | D98: AROSTE AMAO VICTOR | E98: 019100126G | F98: INSCRIPCION DE PROYECTO
A99: Enviado | B99: 97 | C99: 44245 | D99: AGUILAR ROJAS ELIAS | E99: 017200001C | F99: EXPEDIENTE APTO AL GRADO
A100: Enviado | B100: 98 | C100: 44245 | D100: MESTAS TELLO YOHANA YASHAYRA | E100: ACTUALIZACION | F100: EXPEDIENTE APTO AL GRADO
...

Sheet RESOLUCIONES 2020
A1: RESOLUCIONES EMITIDAS 2020 | J1: CARGOS
A2: N° SOLICITUD | B2: RESOL. N° | C2: FECHA | D2: NOMBRES Y APELLIDOS | E2: CODIGO | F2: TIPO DE RESOLUCION | G2: Obaservaciones | H2: RESOLUCION 2 | I2: RESOLUCION 3 | J2: CARGO 1 | K2: CARGO 2 | L2: CARGO 3 | M2: CARGO 4 | N2: CARGO 5
B3: 1
B4: 2
B5: 3 | C5: 43864 | D5: INDIRA ARENAS APUMAITA | F5: DICTAMEN DE PROYECTO | H5: ..\RESOLUCIONES 2020 PDF\03.pdf | J5: ..\RESOLUCIONES 2020 PDF\CARGOS\003 cargo 1.pdf | K5: ..\RESOLUCIONES 2020 PDF\CARGOS\003 cargo 2.pdf
B6: 4 | C6: 43864 | D6: FRANKLIN ANDRES REYES PEÑA | F6: DICTAMEN DE PROYECTO | H6: ..\RESOLUCIONES 2020 PDF\04.pdf | J6: ..\RESOLUCIONES 2020 PDF\CARGOS\004 cargo 1.pdf | K6: ..\RESOLUCIONES 2020 PDF\CARGOS\004 cargo 2.pdf
B7: PROVEIDO 32 | C7: 43864 | D7: ALEXANDER ELMER QUISPE HUILLCA | F7: PROVEIDO
B8: PROVEIDO 14 | C8: 43864 | D8: TEODORO HUARHUA CHIPANI | F8: PROVEIDO
B9: PROVEIDO 26 | C9: 43864 | D9: GUSTAVO GERSON CARPIO PEÑA | F9: PROVEIDO
B10: PROVEIDO 25 | C10: 43864 | D10: CARLOS HUMBERTO VELARDE DALGUER | F10: PROVEIDO
B11: PROVEIDO 21 | C11: 43864 | D11: EMMA NADIA LUNA ROZAS | F11: PROVEIDO
B12: PROVEIDO 16 | C12: 43864 | D12: IBBETH BERIOSVKA HUAMANTICA PEÑA | F12: PROVEIDO
B13: PROVEIDO 15 | C13: 43864 | D13: ELITA LEIDY SUMARRIVA ORTIZ | F13: PROVEIDO
B14: PROVEIDO 23 | C14: 43864 | D14: JANET CHAPARRO VELASQUEZ | F14: PROVEIDO
B15: PROVEIDO 24 | C15: 43864 | D15: GABRIELA NOALCCA LOAIZA | F15: PROVEIDO
B16: PROVEIDO 30 | C16: 43864 | D16: GLORIA CHACON ORDOÑEZ | F16: PROVEIDO
B17: PROVEIDO 29 | C17: 43864 | D17: GERSON QUIN GUERRA | F17: PROVEIDO | G17: Dictamen tesis
B18: PROVEIDO 28 | C18: 43864 | D18: BERTHA HUAMANGA GAMARRA | F18: PROVEIDO
B19: PROVEIDO 27 | C19: 43864 | D19: MARCOS AVELINO VIZCARRA MENDIVIL | F19: PROVEIDO
B20: PROVEIDO 12 | C20: 43864 | D20: ROSA HUARACA APARCO | F20: PROVEIDO
B21: PROVEIDO 17 | C21: 43864 | D21: BERCIN ALCCACONDORI ALATA | F21: PROVEIDO
B22: PROVEIDO 11 | C22: 43864 | D22: JACKIE VARGAS ACOSTA | F22: PROVEIDO
B23: PROVEIDO 10 | C23: 43864 | D23: ROJAS ANAYA YANINA | F23: PROVEIDO
B24: PROVEIDO 01 | C24: 43864 | D24: LUNA VALENZUELA ROXANA | F24: PROVEIDO
B25: PROVEIDO 02 | C25: 43864 | D25: GARCIA PEÑA WILLIAM | F25: PROVEIDO
B26: PROVEIDO 03 | C26: 43864 | D26: FARROÑAN FLORES GABRIEL | F26: PROVEIDO
B27: PROVEIDO 04 | C27: 43864 | D27: GUZMAN CORONADO VICKY ROBERTA | F27: PROVEIDO
B28: PROVEIDO 05 | C28: 43864 | D28: JOVE CARCAUSTO JILARI CARLA | F28: PROVEIDO
B29: PROVEIDO 06 | C29: 43864 | D29: CRUZ NINA YONI | F29: PROVEIDO
... B32: PROVEIDO 09 | C32: 43864 | D32: MERCADO ZEGARRA BETHSY | F32: PROVEIDO
B33: PROVEIDO 33 | C33: 43864 | D33: MALDONADO ORTEGA SANDRA CAROLA | F33: PROVEIDO | J33: ..\RESOLUCIONES 2019 PDF\CARGOS 2019\33 PROVEIDO CARGO 1.pdf | L33: ..\RESOLUCIONES 2019 PDF\CARGOS 2019\33 PROVEIDO CARGO 3.pdf
B34: PROVEIDO 31 | C34: 43864 | D34: SANCHEZ MOGOLLON DIEGO | E34: 016201366f | F34: PROVEIDO | K34: ..\RESOLUCIONES 2019 PDF\CARGOS 2019\31 PROVEIDO CARGO 2.pdf
B35: PROVEIDO 36 | C35: 43873 | D35: CONDORI CAUCHA JOSE ABEL | F35: PROVEIDO
B36: PROVEIDO 34 | C36: 43873 | D36: ROJAS ANAYA YANINA | F36: PROVEIDO
B37: PROVEIDO 36 | C37: 43873 | D37: CONDORI CAUCHA JOSE ABEL | F37: PROVEIDO
B38: PROVEIDO 37 | C38: 43878 | D38: RONNY WILLIAN MUNDACA QUISPE | F38: PROVEIDO
B39: PROVEIDO 38 | C39: 43878 | D39: MARCO ANTONIO GUILLEN CCALA | F39: PROVEIDO
B40: PROVEIDO 39 | C40: 43878 | D40: SOLIS TITO EDITH MARY | F40: PROVEIDO
B41: PROVEIDO 40 | C41: 43878 | D41: CALDERON SEGURA JUAN CARLOS FIDEL | E41: 017200232E | F41: PROVEIDO
B42: PROVEIDO 42 D | C42: 43878 | D42: SANJINES PEÑA YASKARA | F42: PROVEIDO | J42: ..\RESOLUCIONES 2020 PDF\CARGOS\042 PROVEIDO CARGO 1.pdf | K42: ..\RESOLUCIONES 2020 PDF\CARGOS\042 PROVEIDO CARGO 2.pdf
B43: PROVEIDO 44 | C43: 43882 | D43: COLQUE CANDIA WILBERT | F43: PROVEIDO
B44: PROVEIDO 45 | C44: 43882 | D44: CHAVEZ CHACON ANA CECILIA | F44: PROVEIDO
B45: PROVEIDO 46 | C45: 43887 | D45: HUACAC CARRILLO MIRIAN | F45: PROVEIDO
B46: PROVEIDO 45 | C46: 43882 | D46: CHAVEZ CHACON ANA CECILIA | F46: PROVEIDO
B47: PROVEIDO 44 | C47: 43882 | D47: COLQUE CANDIA WILBERT | F47: PROVEIDO
B48: PROVEIDO 46 | C48: 43887 | D48: HUACAC CARRILLO MIRIAN | F48: PROVEIDO
B49: 5 | C49: 43864 | D49: ROCIO MARLENI CARDENAS FLORES | F49: EXPEDIENTE APTO AL GRADO
B50: 6 | C50: 43864 | D50: JULIO CESAR HUAMAN CUSIHUAMAN | F50: EXPEDIENTE APTO AL GRADO
B51: 7 | C51: 43864 | D51: KARLA VELASQUEZ ZARATE | F51: DICTAMEN DE PROYECTO | H51: ..\RESOLUCIONES 2020 PDF\07.pdf | K51: ..\RESOLUCIONES 2020 PDF\CARGOS\007 cargo 2 .pdf
B52: 8 | C52: 43869 | D52: PEREZ SANCHEZ VILMA | F52: CAMBIO DE DICTAMINATE | H52: ..\RESOLUCIONES 2020 PDF\08.pdf | J52: ..\RESOLUCIONES 2020 PDF\CARGOS\08 CARGO 1.pdf
B53: 9 | C53: 43864 | D53: RUBEN TITO MARIÑO LOAIZA | E53: 018200291k | F53: DICTAMEN DE PROYECTO | H53: ..\RESOLUCIONES 2020 PDF\09.pdf | J53: ..\RESOLUCIONES 2020 PDF\CARGOS\009 cargo 1.pdf | K53: ..\RESOLUCIONES 2020 PDF\CARGOS\009cargo 2.pdf
B54: 10 | C54: 43864 | D54: ESTELA QUISPE RAMOS | F54: DICTAMEN DE PROYECTO | H54: ..\RESOLUCIONES 2020 PDF\010 .pdf | J54: ..\RESOLUCIONES 2020 PDF\CARGOS\010 cargo 1.pdf | K54: ..\RESOLUCIONES 2020 PDF\CARGOS\010 cargo 2.pdf
B55: 11 | C55: 43864 | D55: CARLOS ALBERTO BENAVIDES PALOMINO | F55: DICTAMEN DE PROYECTO | H55: ..\RESOLUCIONES 2020 PDF\011.pdf | J55: ..\RESOLUCIONES 2020 PDF\CARGOS\11 cargo 1.pdf | K55: ..\RESOLUCIONES 2020 PDF\CARGOS\011 cargo 2.pdf
B56: 12 | C56: 43864 | D56: DELISIA CACERES LOPEZ | F56: DICTAMEN DE PROYECTO | H56: ..\RESOLUCIONES 2020 PDF\012.pdf | J56: ..\RESOLUCIONES 2020 PDF\CARGOS\012 cargo 1.pdf
B57: 13 | C57: 43864 | D57: CRISTINA ALVARES RIOS | F57: DICTAMEN DE PROYECTO | H57: ..\RESOLUCIONES 2020 PDF\013.pdf | J57: ..\RESOLUCIONES 2020 PDF\CARGOS\013 cargo1.pdf | K57: ..\RESOLUCIONES 2020 PDF\CARGOS\013 cargo 2.pdf
B58: 14 | C58: 43864 | D58: SDENKA OMAIRA MONTESINOS ZAVALA | F58: DICTAMEN DE PROYECTO | H58: ..\RESOLUCIONES 2020 PDF\014.pdf | J58: ..\RESOLUCIONES 2020 PDF\CARGOS\014 cargo 1.pdf | K58: ..\RESOLUCIONES 2020 PDF\CARGOS\014 cargo 2.pdf
B59: 15 | C59: 43864 | D59: MERY JANETH PALOMINO PINTO | F59: DICTAMEN DE PROYECTO | H59: ..\RESOLUCIONES 2020 PDF\015.pdf | J59: ..\RESOLUCIONES 2020 PDF\CARGOS\015 cargo 1.pdf | K59: ..\RESOLUCIONES 2020 PDF\CARGOS\015 cargo 2.pdf
B60: 16 | C60: 43864 | D60: AILANG LIU BUSTINZA BEJAR | F60: DICTAMEN DE PROYECTO | H60: ..\RESOLUCIONES 2020 PDF\016.pdf | J60: ..\RESOLUCIONES 2020 PDF\CARGOS\016 cargo 1.pdf | K60: ..\RESOLUCIONES 2020 PDF\CARGOS\016 cargo 2.pdf
B61: PROVEIDO 41 | C61: 43878 | D61: NINA ASTO CHRISTIAN MITCHELL | F61: PROVEIDO
B62: PROVEIDO 43 | C62: 43879 | D62: FUENTES HUAMANI JOHN ROSS | F62: PROVEIDO
B63: 17 | C63: 43868 | D63: SUMARRIVA ORTIZ ELITA LEIDY | F63: NOMBRAMIENTO ASESOR | G63: OSWALDO LUIZAR OBREGÓ | H63: ..\RESOLUCIONES 2020 PDF\017.pdf
B64: 18 | C64: 43868 | D64: NONTESINOS CERVANTES JOSE ALBERTO | F64: NOMBRAMIENTO ASESOR | G64: FELIO CALDERÓN LA TORRE | H64: ..\RESOLUCIONES 2020 PDF\018.pdf
B65: 19 | C65: 43868 | D65: MAGUIÑA APAZA ANNY ISABEL | F65: NOMBRAMIENTO ASESOR | G65: EDWARDS JESÚS AGUIRRE ESPINOZA | H65: ..\RESOLUCIONES 2020 PDF\019.pdf
B66: 20 | C66: 43868 | D66: FRISANCHO CAMERO MILUSKA | F66: NOMBRAMIENTO ASESOR | G66: ,UAN CARLOS VALENCIA MARTÍNEZ | H66: ..\RESOLUCIONES 2020 PDF\020.pdf
B67: 21 | C67: 43868 | D67: ORIHUELA ROCHA EUFEMIA | F67: NOMBRAMIENTO ASESOR | G67: JORGE RAMON SILVA SIERRA | H67: ..\RESOLUCIONES 2020 PDF\021.pdf
B68: 22 | C68: 43868 | D68: PEARI PANCORBO JHOSERIN LIDIA | F68: NOMBRAMIENTO ASESOR | G68: ANSELMO DIAZ SILVA | H68: ..\RESOLUCIONES 2020 PDF\022.pdf
B69: 23 | C69: 43868 | D69: USCAMAYTA MAQQUE GIULIANA VALERIANA | F69: NOMBRAMIENTO ASESOR | G69: JORGE RAMON SILVA SIERRA | H69: ..\RESOLUCIONES 2020 PDF\023.pdf
B70: 24 | C70: 43868 | D70: DAVALOS QUISPE FRANCISCO | F70: NOMBRAMIENTO ASESOR | G70: Dr. JORGE RAMON SILVA SIERRA, | H70: ..\RESOLUCIONES 2020 PDF\024.pdf
B71: 25 | C71: 43868 | D71: FUENTES HUAMANI JOHN ROSS | F71: NOMBRAMIENTO ASESOR | G71: TATIANA DEL CASTILLO DE LOAVZ | H71: ..\RESOLUCIONES 2020 PDF\025.pdf
B72: 26 | C72: 43868 | D72: QUISPE LUQUE NAPOLEON SOCRATES | F72: NOMBRAMIENTO ASESOR | G72: CLETO DE LA TORRE DUEÑA | H72: ..\RESOLUCIONES 2020 PDF\026.pdf
B73: 27 | C73: 43868 | D73: CARPIO AGUILAR KATIUSKA | F73: NOMBRAMIENTO ASESOR | G73: CLETO DE LA TORRE DUEÑAS | H73: ..\RESOLUCIONES 2020 PDF\027.pdf
B74: 28 | C74: 43868 | D74: CARPIO AGUILAR ERIKA | F74: NOMBRAMIENTO ASESOR | G74: CLETO DE LA TORRE DUEÑAS | H74: ..\RESOLUCIONES 2020 PDF\028.pdf
B75: 29 | C75: 43868 | D75: AQUEPUCHO BELLOTA RUDYARD WILHELM | F75: NOMBRAMIENTO ASESOR | G75: CLETO DE LA TORRE DUEÑAS | H75: ..\RESOLUCIONES 2020 PDF\029.pdf
B76: 30 | C76: 43868 | D76: CHIPANA SUYO DAFNE EVONNE | E76: 017200116E | F76: NOMBRAMIENTO ASESOR | G76: EDITH VERÓNICA YUCRAMAMANI | H76: ..\RESOLUCIONES 2020 PDF\030.pdf
B77: 31 | C77: 43868 | D77: ROBERT LUIS | F77: NOMBRAMIENTO ASESOR | G77: EDWARDS JESÚS AGUIRRE ESPINOZA | H77: ..\RESOLUCIONES 2020 PDF\031.pdf
B78: 32
B79: 33
B80: 34 | C80: 43868 | D80: BARRIAL LUJAN ABEL ISAIAS | F80: INSCRIPCION DE PROYECTO | H80: ..\RESOLUCIONES 2020 PDF\034.pdf
B81: 35 | C81: 43868 | D81: ANGULO AEDO MERIA JESUS | F81: INSCRIPCION DE PROYECTO | H81: ..\RESOLUCIONES 2020 PDF\035 .pdf
B82: 36 | C82: 43868 | D82: MATTOS CASTILLO YOJHAN MIJAIL | F82: INSCRIPCION DE PROYECTO | H82: ..\RESOLUCIONES 2020 PDF\036.pdf
B83: 37
B84: 38 | C84: 43864 | D84: FELIPE MUÑIZ TAPIA | F84: FIJAR FECHA Y HORA | G84: 43875 | H84: ..\RESOLUCIONES 2020 PDF\038.pdf | J84: ..\RESOLUCIONES 2020 PDF\CARGOS\038 cargo interesado.pdf | K84: ..\RESOLUCIONES 2020 PDF\CARGOS\0038 CARGO 2.pdf | N84: ..\RESOLUCIONES 2020 PDF\CARGOS\0038 CARGO 5.pdf
B85: 39 | C85: 43864 | D85: SAYDA MAGALY ARRAYAN BONETT | F85: FIJAR FECHA Y HORA | G85: 43875 | H85: ..\RESOLUCIONES 2020 PDF\039.pdf | K85: ..\RESOLUCIONES 2020 PDF\CARGOS\0039 CARGO 02.pdf | L85: ..\RESOLUCIONES 2020 PDF\CARGOS\39 cargo 3.pdf | M85: ..\RESOLUCIONES 2020 PDF\CARGOS\0039 CARGO 4.pdf
B86: 40 | C86: 43864 | D86: VLADIMIR KRISTIAM OBLITAS CUBA | F86: DICTAMEN DE PROYECTO | H86: ..\RESOLUCIONES 2020 PDF\040.pdf | J86: ..\RESOLUCIONES 2020 PDF\CARGOS\040 cargo 1.pdf | K86: ..\RESOLUCIONES 2020 PDF\CARGOS\040 cargo 2.pdf
B87: 41 | C87: 43864 | D87: MANUEL EDUARDO HIDALGO LEON | F87: FIJAR FECHA Y HORA | G87: 43882 | H87: ..\RESOLUCIONES 2020 PDF\41.pdf | K87: ..\RESOLUCIONES 2020 PDF\CARGOS\041 cargo 2.pdf | L87: ..\RESOLUCIONES 2020 PDF\CARGOS\041 cargo 3.pdf | M87: ..\RESOLUCIONES 2020 PDF\CARGOS\041 cargo 4.pdf | N87: ..\RESOLUCIONES 2020 PDF\CARGOS\041 cargo 5.pdf
B88: 42 | C88: 43864 | D88: YISELA GIOVANA PUELLES FOLLANA | F88: PRORROGA DE UN AÑO | H88: ..\RESOLUCIONES 2020 PDF\042 .pdf
B89: 43 | C89: 43871 | D89: LONGA RAMOS EDUARDO JOSE | F89: ELEVAR AL VRAC | G89: DOCTOR EN CIENCIAS DE LA SALUD | H89: ..\RESOLUCIONES 2020 PDF\043.pdf
B90: 44 | C90: 43871 | D90: MOGROVEJO DELGADO SAMUEL | F90: ELEVAR AL VRAC | G90: DOCTOR EN CIENCIAS DE LA EDUCACION | H90: ..\RESOLUCIONES 2020 PDF\044.pdf
B91: 45 | C91: 43871 | D91: PINTO LEON JUAN | F91: ELEVAR AL VRAC | G91: DOCTOR MEDIO AMBIENTE | H91: ..\RESOLUCIONES 2020 PDF\045.pdf
B92: 46 | C92: 43865 | D92: GERMAN HEBER CORREA NUÑEZ | F92: FIJA FECHA Y HORA | G92: 43882 | H92: ..\RESOLUCIONES 2020 PDF\046 .pdf | K92: ..\RESOLUCIONES 2020 PDF\CARGOS\046 cargo 2.pdf | L92: ..\RESOLUCIONES 2020 PDF\CARGOS\046 cargo 3 .pdf | M92: ..\RESOLUCIONES 2020 PDF\CARGOS\046 cargo 4.pdf | N92: ..\RESOLUCIONES 2020 PDF\CARGOS\046-CARGO 5.pdf
B93: 47 | C93: 43871 | D93: DEL POZO AEDO MITZY | F93: ELEVAR AL VRAC | G93: DOCENCIA UNIVERSITARIA | H93: ..\RESOLUCIONES 2020 PDF\047.pdf
B94: 48 | C94: 43871 | D94: ALFARO AUCCA CRAYLA | F94: ELEVAR AL VRAC | G94: DOCTOR EN CIENCIAS DE LA EDUCACION | H94: ..\RESOLUCIONES 2020 PDF\048.pdf
B95: 49 | C95: 43871 | D95: CANCAPA MALAGA AUGUSTA | F95: ELEVAR AL VRAC | G95: MAESTRIA CONTABILIDAD | H95: ..\RESOLUCIONES 2020 PDF\049.pdf
B96: 50 | C96: 43871 | D96: ARROYO POLANCO FRANCISCO | F96: ELEVAR AL VRAC | G96: DOCTORADO ADMINISTRACION | H96: ..\RESOLUCIONES 2020 PDF\050.pdf
B97: 51 | C97: 43871 | D97: LUNA ROZAS EMMA NADIA | F97: ELEVAR AL VRAC | G97: DOCENCIA UNIVERSITARIA | H97: ..\RESOLUCIONES 2020 PDF\051.pdf
B98: 52 | C98: 43871 | D98: QUISPE FLOREZ MERCEDES MARITZA | F98: ELEVAR AL VRAC | G98: DOCENCIA UNIVERSITARIA | H98: ..\RESOLUCIONES 2020 PDF\052.pdf
B99: 53 | C99: 43873 | D99: TELLO TACO BRYAN MANUEL | F99: DICTAMEN DE PROYECTO | H99: ..\RESOLUCIONES 2020 PDF\053.pdf | J99: ..\RESOLUCIONES 2020 PDF\CARGOS\053 CARGO 1.pdf | K99: ..\RESOLUCIONES 2020 PDF\CARGOS\053 CARGO 2.pdf
B100: 54 | C100: 43873 | D100: VARGAS ACOSTA JACKIE | F100: DICTAMEN DE PROYECTO | H100: ..\RESOLUCIONES 2020 PDF\054.pdf | J100: ..\RESOLUCIONES 2020 PDF\CARGOS\054 CARGO 1.pdf | K100: ..\RESOLUCIONES 2020 PDF\CARGOS\54 cargo 2.pdf
B101: 55 | C101: 43873 | D101: CHALCO SUAREZ JESSICA ELIZABETH | F101: DICTAMEN DE PROYECTO | H101: ..\RESOLUCIONES 2020 PDF\055.pdf | J101: ..\RESOLUCIONES 2020 PDF\CARGOS\055 CARGO 1.pdf | K101: ..\RESOLUCIONES 2020 PDF\CARGOS\055 CARGO 2.pdf
B102: 56 | C102: 43874 | D102: MONTESINOS SOTOMAYOR SUSAN MILENKA | F102: INSCRIPCION DE PROYECTO | H102: ..\RESOLUCIONES 2020 PDF\056.pdf
...

Sheet RESOLUCIONES 2019
A1: RESOLUCIONES EMITIDAS 2019 | J1: CARGOS
A2: N° SOLICITUD | B2: RESOL. N° | C2: FECHA | D2: NOMBRES Y APELLIDOS | E2: CODIGO | F2: TIPO DE RESOLUCION | G2: Obaservaciones | H2: RESOLUCION 2 | J2: CARGO 1 | K2: CARGO 2 | L2: CARGO 3 | M2: CARGO 4 | N2: CARGO 5
A3: ENVIADO | B3: 1 | C3: 43501 | D3: QUISPE TISOC ELIANA | F3: AUTORIZAR SUBSANACION | H3: ..\RESOLUCIONES 2019 PDF\0001.pdf
A4: ENVIADO | B4: 2 | C4: 43501 | D4: PAREDES SANCA RUBI GERALDINE | F4: AUTORIZAR SUBSANACION | H4: ..\RESOLUCIONES 2019 PDF\0002.pdf | J4: ..\RESOLUCIONES 2019 PDF\CARGOS 2019\0002-CARGO.pdf
A5: ENVIADO | B5: 3 | C5: 43501 | D5: ATAUCHI RAVELO ALMENDRA | F5: AUTORIZAR SUBSANACION | H5: ..\RESOLUCIONES 2019 PDF\0003.pdf | J5: ..\RESOLUCIONES 2019 PDF\CARGOS 2019\0003-CARGO.pdf
A6: ENVIADO | B6: 4 | C6: 43501 | D6: UMIYAURI QUIRITA PAOLA JACKELIN | F6: AUTORIZAR SUBSANACION | H6: ..\RESOLUCIONES 2019 PDF\0004.pdf | J6: ..\RESOLUCIONES 2019 PDF\CARGOS 2019\0004-CARGO.pdf
A7: ENVIADO | B7: 5 | C7: 43501 | D7: CCALLO HUIRSE YOBANA | E7: 017300091D | F7: AUTORIZAR SUBSANACION | H7: ..\RESOLUCIONES 2019 PDF\0005.pdf | J7: ..\RESOLUCIONES 2019 PDF\CARGOS 2019\0005-CARGO.pdf
A8: ENVIADO | B8: 6 | C8: 43795 | D8: SUMALAVE PALOMINO ROBERTH PEJOREF | F8: AUTORIZAR SUBSANACION | H8: ..\RESOLUCIONES 2019 PDF\0006.pdf
B9: 7 | C9: 43570 | D9: PALOMINO OQUENDO WALTER VICENTE | F9: PROVEIDO
A10: ENVIADO | B10: 7 | C10: 43501 | D10: QUISPE ESPINOZA ROXANA | F10: AUTORIZAR SUBSANACION | H10: ..\RESOLUCIONES 2019 PDF\0007.pdf
A11: ENVIADO | B11: 8 | C11: 43501 | D11: LOAYZA ENCALADA DARWIN DUHAMEL | F11: AUTORIZAR SUBSANACION | H11: ..\RESOLUCIONES 2019 PDF\0008.pdf
A12: ENVIADO | B12: 9 | C12: 43501 | D12: VALDERRAMA VIZCARRA FRINE | F12: AUTORIZAR SUBSANACION | H12: ..\RESOLUCIONES 2019 PDF\0009.pdf
A13: ENVIADO | B13: 10 | C13: 43501 | D13: VALENZUELA HUAMAN CESAR JOE | F13: NOMBRAMIENTO DE ASESOR | H13: ..\RESOLUCIONES 2019 PDF\0010.pdf
A14: ENVIADO | B14: 11 | C14: 43501 | D14: CASTRO OCAMPO DANIEL ALFREDO | F14: NOMBRAMIENTO DE ASESOR | H14: ..\RESOLUCIONES 2019 PDF\00011.pdf
B15: 12 | C15: 43501 | D15: VELASQUEZ ZARATE KARLA | F15: NOMBRAMIENTO DE ASESOR | H15: ..\RESOLUCIONES 2019 PDF\00012.pdf
B16: 13 | C16: 43501 | D16: BILLOTA HUARCAYA DIEGO JESUS | F16: NOMBRAMIENTO DE ASESOR | H16: ..\RESOLUCIONES 2019 PDF\00013.pdf
B17: 14 | C17: 43501 | D17: LOPEZ CORAZAO FRANS OMAR | F17: NOMBRAMIENTO DE ASESOR | H17: ..\RESOLUCIONES 2019 PDF\00014.pdf
A18: ENVIADO | B18: 15 | C18: 43501 | D18: QUISPE CCASA CELIA | F18: FIJAR FECHA Y HORA | G18: 43511 | H18: ..\RESOLUCIONES 2019 PDF\00015.pdf | J18: ..\RESOLUCIONES 2019 PDF\CARGOS 2019\0015-CARGO-1.pdf | K18: ..\RESOLUCIONES 2019 PDF\CARGOS 2019\0015-CARGO-2.pdf | L18: ..\RESOLUCIONES 2019 PDF\CARGOS 2019\0015-CARGO-3.pdf
A19: ENVIADO | B19: 16 | C19: 43501 | D19: LUYCHO HUAMAN ALBARO | F19: FIJAR FECHA Y HORA | G19: 43511 | H19: ..\RESOLUCIONES 2019 PDF\00016.pdf | J19: ..\RESOLUCIONES 2019 PDF\CARGOS 2019\0016-CARGO-1.pdf | K19: ..\RESOLUCIONES 2019 PDF\CARGOS 2019\0016-CARGO-2.pdf | L19: ..\RESOLUCIONES 2019 PDF\CARGOS 2019\0016-CARGO.pdf | M19: ..\RESOLUCIONES 2019 PDF\CARGOS 2019\0016-CARGO4.pdf
B20: 17 | C20: 43501 | D20: ARMINTA OCHOA JESUS KENYO | F20: NOMBRAMIENTO DE ASESOR | H20: ..\RESOLUCIONES 2019 PDF\00017.pdf
B21: 18 | C21: 43501 | D21: HUAMAN GOMEZ LIZETH | F21: NOMBRAMIENTO DE ASESOR | H21: ..\RESOLUCIONES 2019 PDF\00018.pdf
B22: 19 | C22: 43501 | D22: HUANACO HUANCA RAUL ANDY | F22: NOMBRAMIENTO DE ASESOR | H22: ..\RESOLUCIONES 2019 PDF\00019.pdf
B23: 20 | C23: 43501 | D23: QUISPE PACHECO WILMER FERNANDO | F23: NOMBRAMIENTO DE ASESOR | H23: ..\RESOLUCIONES 2019 PDF\00020.pdf
B24: 21 | C24: 43501 | D24: OCHOA SAIRE FREDY | F24: NOMBRAMIENTO DE ASESOR | H24: ..\RESOLUCIONES 2019 PDF\00021.pdf
B25: 22 | C25: 43501 | D25: ARRUNATEGUI MORENO ROSA ELVIRA | F25: NOMBRAMIENTO DE ASESOR | H25: ..\RESOLUCIONES 2019 PDF\00022.pdf
B26: 23 | C26: 43501 | D26: SANCHEZ TURPO VIDAL ORLANDO | F26: NOMBRAMIENTO DE ASESOR | H26: ..\RESOLUCIONES 2019 PDF\00023.pdf
B27: 24 | C27: 43501 | D27: BARRIONUEVO ALOSILLA PAMELA | F27: NOMBRAMIENTO DE ASESOR | G27: Pezua Vasquez | H27: ..\RESOLUCIONES 2019 PDF\00024.pdf
B28: 25 | C28: 43501 | D28: GONZALEZ ALVAREZ KELMA KARINNA | F28: NOMBRAMIENTO DE ASESOR | G28: Pezua Vasquez | H28: ..\RESOLUCIONES 2019 PDF\00025.pdf
B29: 26 | C29: 43501 | D29: HUAMAN AFAN JUAN | F29: NOMBRAMIENTO DE ASESOR | H29: ..\RESOLUCIONES 2019 PDF\00026.pdf
B30: 27 | C30: 43501 | D30: PIMENTEL ELGUERA MARCELINO | F30: NOMBRAMIENTO DE ASESOR | G30: Pezua Vasquez | H30: ..\RESOLUCIONES 2019 PDF\00027.pdf
B31: 28 | C31: 43501 | D31: HUACAC CARRILLO MIRIAN | F31: INSCRIPCION DE TEMA DE TESIS | H31: ..\RESOLUCIONES 2019 PDF\0028.pdf
B32: 29 | C32: 43501 | D32: NAYHUA ORMACHEA MARCO ANTONIO | F32: NOMBRAMIENTO DE ASESOR | H32: ..\RESOLUCIONES 2019 PDF\0029.pdf
B33: 30 | C33: 43501 | D33: AROHUANCA SOSA RODE LUZ | F33: NOMBRAMIENTO DE ASESOR | H33: ..\RESOLUCIONES 2019 PDF\0029.pdf
B34: 31 | C34: 43501 | D34: MONDALGO ALCARRAZ MARIA EUFEMIA | F34: NOMBRAMIENTO DE ASESOR | H34: ..\RESOLUCIONES 2019 PDF\0031.pdf
B35: 32 | C35: 43501 | D35: QUISPE QUISPE RAQUEL LUCIMAR | E35: 019200263F | F35: NOMBRAMIENTO DE ASESOR | H35: ..\RESOLUCIONES 2019 PDF\0032.pdf
B36: 33 | C36: 43502 | D36: VICENTE AGUILAR ALICIA NATALIA | F36: NOMBRAMIENTO DE ASESOR | G36: Pezua Vasquez | H36: ..\RESOLUCIONES 2019 PDF\0033.pdf
B37: 34 | C37: 43502 | D37: GUZMAN ALARCON KARLOS GORKI | F37: INSCRIPCION DE TEMA DE TESIS | H37: ..\RESOLUCIONES 2019 PDF\0034.pdf
B38: 35 | C38: 43502 | D38: RADO CESPEDES ISKRA | F38: NOMBRAMIENTO DE ASESOR | H38: ..\RESOLUCIONES 2019 PDF\0035.pdf
B39: 36 | C39: 43502 | D39: PANOCCA MERMA CLAUDIO ZENOBIO | F39: NOMBRAMIENTO DE ASESOR | H39: ..\RESOLUCIONES 2019 PDF\0036.pdf
B40: 37 | C40: 43502 | D40: CHULLO HUALLPA CELIA | F40: NOMBRAMIENTO DE ASESOR | H40: ..\RESOLUCIONES 2019 PDF\0037.pdf
B41: 38 | C41: 43502 | D41: HUAMAN FARFAN TAHIRI | F41: INSCRIPCION DE TEMA DE TESIS | H41: ..\RESOLUCIONES 2019 PDF\0038.pdf
B42: 39 | C42: 43502 | D42: ALCARCON VALDIVIA EDGAR ZACARIAS | F42: INSCRIPCION DE TEMA DE TESIS | H42: ..\RESOLUCIONES 2019 PDF\0039.pdf
B43: 40 | C43: 43502 | D43: ZAMALLOA MONCADA ALEX AURELIO | F43: NOMBRAMIENTO DE ASESOR | H43: ..\RESOLUCIONES 2019 PDF\0040.pdf
A44: ENVIADO | B44: 41 | C44: 43502 | D44: QUISPE TTITO JHONMY SNALDER | F44: RECONOCER NOTA SUBSANACION | H44: ..\RESOLUCIONES 2019 PDF\0041.pdf | J44: ..\RESOLUCIONES 2019 PDF\CARGOS 2019\0041-CARGO.pdf
A45: ENVIADO | B45: 42 | C45: 43502 | D45: SEGOVIA SOTO ROBERTO | F45: RECONOCER NOTA SUBSANACION | H45: ..\RESOLUCIONES 2019 PDF\0042.pdf | J45: ..\RESOLUCIONES 2019 PDF\CARGOS 2019\0042-CARGO.pdf
A46: ENVIADO | B46: 43 | C46: 43502 | D46: VELASCO MORON LARIZA | F46: ELEVAR AL VRAC | G46: Administracion de Negocios | H46: ..\RESOLUCIONES 2019 PDF\0043.pdf
B47: 44 | C47: 43502 | D47: AEDO VEGA CENTENO LUZ GUISELL | F47: ELEVAR AL VRAC | G47: Seguridad Industrial y Medio Ambiente | H47: ..\RESOLUCIONES 2019 PDF\0044.pdf
A48: ENVIADO | B48: 45 | C48: 43502 | D48: OLIVARES TORRE GRETEL ROXANA | F48: ELEVAR AL VRAC | G48: Docencia Universitaria | H48: ..\RESOLUCIONES 2019 PDF\0045.pdf
A49: ENVIADO | B49: 46 | C49: 43502 | D49: CAHUATA CABALLERO ADILSON | F49: AUTORIZAR SUBSANACION | H49: ..\RESOLUCIONES 2019 PDF\0046.pdf | J49: ..\RESOLUCIONES 2019 PDF\CARGOS 2019\0046-CARGO.pdf | K49: ..\RESOLUCIONES 2019 PDF\CARGOS 2019\0046-CARGO2.pdf
A50: ENVIADO | B50: 47 | C50: 43507 | D50: ANGLES ESCOBEDO YENY | F50: AUTORIZAR SUBSANACION | G50: ENVIADO VIA WEB | H50: ..\RESOLUCIONES 2019 PDF\0047.pdf | J50: ..\RESOLUCIONES 2019 PDF\CARGOS 2019\0047-CARGO.pdf | K50: ..\RESOLUCIONES 2019 PDF\CARGOS 2019\0047-CARGO1.pdf
B51: 48 | C51: 43507 | D51: SERRANO QUISPE MARCO | F51: NOMBRAMIENTO DE ASESOR | H51: ..\RESOLUCIONES 2019 PDF\0048.pdf
B52: 49 | C52: 43508 | D52: ANULADO
B53: 50 | C53: 43508 | D53: CONDORI CHACACANTA YESENIA MARICIELO | F53: RECONOCER NOTA SUBSANACION | H53: ..\RESOLUCIONES 2019 PDF\0050.pdf
B54: 51 | C54: 43508 | D54: CACERES MARISCAL YURI | F54: INSCRIPCION DE TEMA DE TESIS | H54: ..\RESOLUCIONES 2019 PDF\0051.pdf | J54: ..\RESOLUCIONES 2019 PDF\CARGOS 2019\0051-CARGO.pdf
B55: 52 | C55: 43508 | D55: MENDIZABAL DIAZ FERNANDO ARNOLDO | F55: NOMBRAMIENTO DE ASESOR | H55: ..\RESOLUCIONES 2019 PDF\0052.pdf
B56: 53 | C56: 43508 | D56: ZUÑIGA MORALES OMAR NILO | F56: NOMBRAMIENTO DE ASESOR | H56: ..\RESOLUCIONES 2019 PDF\0053.pdf
B57: 54 | C57: 43508 | D57: USCAMAYTA HUAYAPO ELVELYN | F57: NOMBRAMIENTO DE ASESOR | H57: ..\RESOLUCIONES 2019 PDF\0054.pdf
B58: 55 | C58: 43508 | D58: OBLEA SILVA CARLOS | F58: NOMBRAMIENTO DE ASESOR | H58: ..\RESOLUCIONES 2019 PDF\0055.pdf
B59: 56 | C59: 43508 | D59: ROZAS VERA MARCIA PILAR | F59: NOMBRAMIENTO DE ASESOR | H59: ..\RESOLUCIONES 2019 PDF\0056.pdf
B60: 57 | C60: 43508 | D60: MONTUFAR YEPEZ ALAIN | F60: NOMBRAMIENTO DE ASESOR | H60: ..\RESOLUCIONES 2019 PDF\0057.pdf
B61: 58 | C61: 43508 | D61: FLOREZ QQUESIHUALLPA LUZ VENUS | F61: NOMBRAMIENTO DE ASESOR | H61: ..\RESOLUCIONES 2019 PDF\0058.pdf
A62: ENVIADO | B62: 59 | C62: 43508 | D62: VELASQUEZ CURO MILTON JHON | F62: AUTORIZAR SUBSANACION | G62: ENVIADO VIA WEB | H62: ..\RESOLUCIONES 2019 PDF\0059.pdf | J62: ..\RESOLUCIONES 2019 PDF\CARGOS 2019\0059-CARGO.pdf | K62: ..\RESOLUCIONES 2019 PDF\CARGOS 2019\0059-CARGO2.pdf | L62: ..\RESOLUCIONES 2019 PDF\CARGOS 2019\0059.pdf
B63: 60 | C63: 43508 | D63: VERA MARMANILLO VERONIKA ISELA | F63: RECTIFICAR RESOL. 0445-2018 | H63: ..\RESOLUCIONES 2019 PDF\0060.pdf
A64: ENVIADO | B64: 61 | C64: 43508 | D64: VENEGAS ECHARRE JOSE ANGEL | F64: AUTORIZAR SUBSANACION | H64: ..\RESOLUCIONES 2019 PDF\0061.pdf | J64: ..\RESOLUCIONES 2019 PDF\CARGOS 2019\0061-CARGO.pdf | K64: ..\RESOLUCIONES 2019 PDF\CARGOS 2019\0061-CARGO2.pdf
A65: ENVIADO | B65: 62 | C65: 43508 | D65: NAJAR OBANDO ANAHI | F65: RECTIFICAR NOTA | H65: ..\RESOLUCIONES 2019 PDF\0062.pdf | J65: ..\RESOLUCIONES 2019 PDF\CARGOS 2019\0062.pdf
B66: 63 | C66: 43508 | D66: AZURIN DIAZ ELOY ANANIAS | F66: MODIFICAR RESOLUCION 219/EPG-UAC | H66: ..\RESOLUCIONES 2019 PDF\0062.pdf
B67: 64 | C67: 43510 | D67: MALATESTA CARBAJAL DENISSE NOELIA | F67: DECLARAR APTO EXPEDIENTE | H67: ..\RESOLUCIONES 2019 PDF\0064.pdf
B68: 65 | C68: 43510 | D68: CABALLERO CONDORI WILVER | F68: MODIFICAR RESOL-N°442-2015/EPG-UAC | H68: ..\RESOLUCIONES 2019 PDF\0065.pdf | J68: ..\RESOLUCIONES 2019 PDF\CARGOS 2019\0065-CARGO.pdf
B69: 66 | C69: 43502 | D69: MALDONADO ORTEGA SANDRA CAROLA | F69: INSCRIPCION DE TEMA DE TESIS | H69: ..\RESOLUCIONES 2019 PDF\0066.pdf
B70: 67 | C70: 43510 | D70: LUNA KJURO MARLENE | F70: MODIFICAR RESOL-N°004-2016/EPG-UAC | H70: ..\RESOLUCIONES 2019 PDF\0067.pdf
B71: 68 | C71: 43510 | D71: ANDONAYRE VELASCO ALEXANDRA STEFANY | F71: NOMBRAMIENTO DE ASESOR | G71: WALTER EDGAR GOMEZ GONZALES | H71: ..\RESOLUCIONES 2019 PDF\0068.pdf
B72: 69 | C72: 43510 | D72: PEREYRA ROCA MARIA DEL CARMEN | F72: NOMBRAMIENTO DE ASESOR | H72: ..\RESOLUCIONES 2019 PDF\0069.pdf
A73: ENVIADO | B73: 70 | C73: 43510 | D73: ALAGON MARTINEZ WUILLIAN | F73: DICTAMEN PROYECTO TESIS | H73: ..\RESOLUCIONES 2019 PDF\0070.pdf | J73: ..\RESOLUCIONES 2019 PDF\CARGOS 2019\0070.pdf | K73: ..\RESOLUCIONES 2019 PDF\CARGOS 2019\0070-2.pdf
A74: ENVIADO | B74: 71 | C74: 43510 | D74: COVARRUBIAS ALVAREZ CARLOS ISAURO | F74: DICTAMEN PROYECTO TESIS | H74: ..\RESOLUCIONES 2019 PDF\0071.pdf | J74: ..\RESOLUCIONES 2019 PDF\CARGOS 2019\0071.pdf | K74: ..\RESOLUCIONES 2019 PDF\CARGOS 2019\71.pdf
A75: ENVIADO | B75: 72 | C75: 43510 | F75: DICTAMEN PROYECTO TESIS | H75: ..\RESOLUCIONES 2019 PDF\0072.pdf | J75: ..\RESOLUCIONES 2019 PDF\CARGOS 2019\72.pdf | K75: ..\RESOLUCIONES 2019 PDF\CARGOS 2019\72-2.pdf
A76: ENVIADO | B76: 73 | C76: 43510 | D76: HUAMAN CUSIHUAMAN JULIO CESAR | F76: DICTAMEN PROYECTO TESIS | H76: ..\RESOLUCIONES 2019 PDF\0073.pdf | J76: ..\RESOLUCIONES 2019 PDF\CARGOS 2019\0073.pdf | K76: ..\RESOLUCIONES 2019 PDF\CARGOS 2019\0073-CARGO.pdf
B77: 74 | C77: 43510 | D77: ACUÑA PALOMINO FLOR DE MARIA | F77: MODIFICAR RESOL-N°1017-2018/EPG-UAC | H77: ..\RESOLUCIONES 2019 PDF\0074.pdf
B78: 75 | C78: 43511 | D78: ALVAREZ ALVAREZ PAOLA | F78: NOMBRAMIENTO DE ASESOR | H78: ..\RESOLUCIONES 2019 PDF\0075.pdf
B79: 76 | C79: 43511 | D79: VENERO AMABLE GLORIA | F79: NOMBRAMIENTO DE ASESOR | H79: ..\RESOLUCIONES 2019 PDF\0076.pdf | J79: ..\RESOLUCIONES 2019 PDF\CARGOS 2019\0076-CARGO.pdf
B80: 77 | C80: 43511 | D80: CUPI ZUNIGA ARMANDO | F80: PRORROGA UN AÑO | H80: ..\RESOLUCIONES 2019 PDF\0077.pdf | L80: ..\RESOLUCIONES 2019 PDF\CARGOS 2019\0077-CARGO3.pdf
A81: ENVIADO | B81: 78 | C81: 43511 | D81: DEL POZO AEDO MITZY | F81: AUTORIZAR SUBSANACION | H81: ..\RESOLUCIONES 2019 PDF\0078.pdf | J81: ..\RESOLUCIONES 2019 PDF\CARGOS 2019\78.pdf | K81: ..\RESOLUCIONES 2019 PDF\CARGOS 2019\78-2.pdf
B82: 79 | C82: 43511 | D82: GAMARRA VILLANUEVA WILFREDO | F82: ELEVAR AL VRAC | G82: Ciencias de la Educacion | H82: ..\RESOLUCIONES 2019 PDF\0079.pdf
A83: ENVIADO | B83: 80 | C83: 43514 | D83: LUYCHO HUAMAN ALBARO | F83: FIJAR FECHA Y HORA | G83: 43522 | H83: ..\RESOLUCIONES 2019 PDF\0080.pdf | J83: ..\RESOLUCIONES 2019 PDF\CARGOS 2019\0080-1.pdf | K83: ..\RESOLUCIONES 2019 PDF\CARGOS 2019\0080-2.pdf | L83: ..\RESOLUCIONES 2019 PDF\CARGOS 2019\0080-3.pdf | M83: ..\RESOLUCIONES 2019 PDF\CARGOS 2019\0080-CARGO.pdf | N83: ..\RESOLUCIONES 2019 PDF\CARGOS 2019\0080-CARGO4.pdf
A84: ENVIADO | B84: 81 | C84: 43514 | D84: ALAGON CANAHUIRE CENETH | F84: FIJAR FECHA Y HORA | G84: 43532 | H84: ..\RESOLUCIONES 2019 PDF\0081.pdf | J84: ..\RESOLUCIONES 2019 PDF\CARGOS 2019\0081-CARGO.pdf | K84: ..\RESOLUCIONES 2019 PDF\CARGOS 2019\0081-CARGO2.pdf | L84: ..\RESOLUCIONES 2019 PDF\CARGOS 2019\0081-CARGO3.pdf | M84: ..\RESOLUCIONES 2019 PDF\CARGOS 2019\0081-CARGO5.pdf | N84: ..\RESOLUCIONES 2019 PDF\CARGOS 2019\0081-CARGO6.pdf
A85: ENVIADO | B85: 82 | C85: 43514 | D85: PAUCCAR TIMPO SHARMELY ELIANA | F85: FIJAR FECHA Y HORA | G85: 43532 | H85: ..\RESOLUCIONES 2019 PDF\0082.pdf | J85: ..\RESOLUCIONES 2019 PDF\CARGOS 2019\0082-CARGO1.pdf | K85: ..\RESOLUCIONES 2019 PDF\CARGOS 2019\0082-CARGO2.pdf | L85: ..\RESOLUCIONES 2019 PDF\CARGOS 2019\0082-CARGO3.pdf | M85: ..\RESOLUCIONES 2019 PDF\CARGOS 2019\0082-CARGO4.pdf
B86: 83 | C86: 43514 | D86: ZAMBRANO SAYRE NILO | F86: DEJAR SIN DEFECTO RESOL. N° 0584-2018/EPG-UAC | H86: ..\RESOLUCIONES 2019 PDF\0083.pdf | O86: ..\RESOLUCIONES 2019 PDF\CARGOS 2019\0082-CARGO6.pdf
A87: ENVIADO | B87: 84 | C87: 43514 | D87: ZAMBRANO SAYRE NILO | F87: DICTAMEN PROYECTO TESIS | H87: ..\RESOLUCIONES 2019 PDF\0084.pdf | J87: ..\RESOLUCIONES 2019 PDF\CARGOS 2019\0084-CARGO.pdf | K87: ..\RESOLUCIONES 2019 PDF\CARGOS 2019\0084-CARGO1.pdf | L87: ..\RESOLUCIONES 2019 PDF\CARGOS 2019\0084-CARGO3.pdf
A88: ENVIADO | B88: 85 | C88: 43515 | D88: SAIRE YAÑEZ ELIDA | F88: FIJAR FECHA Y HORA | H88: ..\RESOLUCIONES 2019 PDF\0085.pdf | J88: ..\RESOLUCIONES 2019 PDF\CARGOS 2019\0085-CARGO.pdf | K88: ..\RESOLUCIONES 2019 PDF\CARGOS 2019\0085-CARGO2.pdf | L88: ..\RESOLUCIONES 2019 PDF\CARGOS 2019\0085-CARGO3.pdf | M88: ..\RESOLUCIONES 2019 PDF\CARGOS 2019\0085-CARGO5.pdf
B89: 86 | C89: 43515 | D89: JIMENEZ CARAZAS JEANETTE MIRELLA | F89: FIJAR FECHA Y HORA | H89: ..\RESOLUCIONES 2019 PDF\0086.pdf
B90: 87
B91: 88
B92: 89 | C92: 43518 | D92: CARTEZ PEÑA VADINHA YOLANDA | F92: NOMBRAMIENTO DE ASESOR | H92: ..\RESOLUCIONES 2019 PDF\0089.pdf
A93: ENVIADO | B93: 90 | C93: 43518 | D93: AZURIN DIAZ ELOY ANANIAS | F93: FIJAR FECHA Y HORA | G93: 43523 | H93: ..\RESOLUCIONES 2019 PDF\0090.pdf | J93: ..\RESOLUCIONES 2019 PDF\CARGOS 2019\0090-1.pdf | K93: ..\RESOLUCIONES 2019 PDF\CARGOS 2019\0090-2.pdf | L93: ..\RESOLUCIONES 2019 PDF\CARGOS 2019\0090-3.pdf | M93: ..\RESOLUCIONES 2019 PDF\CARGOS 2019\0090-4.pdf
A94: ENVIADO | B94: 91 | C94: 43519 | D94: ECHEA BOCANGEL MERY | F94: AUTORIZAR SUBSANACION | H94: ..\RESOLUCIONES 2019 PDF\0091.pdf | J94: ..\RESOLUCIONES 2019 PDF\CARGOS 2019\0091-CARGO.pdf | K94: ..\RESOLUCIONES 2019 PDF\CARGOS 2019\0091.pdf
A95: ENVIADO | B95: 92 | C95: 43519 | D95: OLIVERA OJEDA ANGELA | F95: AUTORIZAR SUBSANACION | H95: ..\RESOLUCIONES 2019 PDF\0092.pdf | J95: ..\RESOLUCIONES 2019 PDF\CARGOS 2019\0092-CARGO.pdf | K95: ..\RESOLUCIONES 2019 PDF\CARGOS 2019\0092.pdf
B96: 93 | C96: 43519 | D96: MAMANI TORRES ALFREDO | F96: DEJAR SIN DEFECTO RESOL. N° 056-2016/EPG-UAC | H96: ..\RESOLUCIONES 2019 PDF\0093.pdf
B97: 94 | C97: 43519 | D97: VALENCIA JIMENEZ JEAN CARLO | F97: NOMBRAMIENTO DE ASESOR | H97: ..\RESOLUCIONES 2019 PDF\0094.pdf
B98: 95 | C98: 43519 | D98: ACHANCCARAY BECERRA LIZ | F98: NOMBRAMIENTO DE ASESOR | H98: ..\RESOLUCIONES 2019 PDF\0095.pdf | J98: ..\RESOLUCIONES 2019 PDF\CARGOS 2019\0095-CARGO.pdf
B99: 96 | C99: 43521 | D99: RIVERA VARGAS KATERIN ROSS | F99: CAMBIO DE ASESOR | H99: ..\RESOLUCIONES 2019 PDF\0096.pdf
B100: 97 | C100: 43521 | D100: VALER SOSA MARTHA | F100: NOMBRAMIENTO DE ASESOR | H100: ..\RESOLUCIONES 2019 PDF\0097.pdf
...

Sheet RESOLUCIONES 2018
A1: RESOLUCIONES EMITIDAS 2018 | J1: CARGOS
A2: EXPED. | B2: RESOL. N° | C2: FECHA | D2: NOMBRE Y APELLIDO | E2: Codigo | F2: TIPO DE RESOLUCION | G2: Columna1 | H2: RESOLUCION 2 | I2: Estado | J2: CARGO 1 | K2: CARGO 2 | L2: CARGO 3 | M2: CARGO 4 | N2: CARGO 5
A3: X | B3: 1 | C3: 43132 | D3: NUÑEZ MEDINA RUTH | F3: NOMBRAMIENTO DE ASESOR | G3: DR.AGUIRRE ESPINOZA EDWARDS JESUS | H3: =HYPERLINK("\\Pc-informes\documentos informes\RESOLUCIONES\RESOLUCIONES 2018 PDF\1.PDF","..\RESOLUCIONES 2018 PDF\1.pdf") -> ..\RESOLUCIONES 2018 PDF\1.pdf
B4: 2 | C4: 43136 | D4: MUÑOZ HUAMANCCARI CELIS | F4: INSCRIPCION DE TEMA DE TESIS | H4: =HYPERLINK("\\Pc-informes\documentos informes\RESOLUCIONES\RESOLUCIONES 2018 PDF\2.PDF","..\RESOLUCIONES 2018 PDF\2.pdf") -> ..\RESOLUCIONES 2018 PDF\2.pdf
B5: 3 | C5: 43137 | D5: COAVOY ARAPA FANNY LIZBETH | F5: NOMBRAMIENTO DE ASESOR | G5: DRA.LATORRE RIVEROS LIDA | H5: =HYPERLINK("\\Pc-informes\documentos informes\RESOLUCIONES\RESOLUCIONES 2018 PDF\3.PDF","..\RESOLUCIONES 2018 PDF\3.pdf") -> ..\RESOLUCIONES 2018 PDF\3.pdf
B6: 4 | C6: 43137 | D6: QUILCA JIMENEZ JUAN CARLOS | F6: INSCRIPCION DE TEMA DE TESIS | H6: =HYPERLINK("\\Pc-informes\documentos informes\RESOLUCIONES\RESOLUCIONES 2018 PDF\4.PDF","..\RESOLUCIONES 2018 PDF\4.pdf") -> ..\RESOLUCIONES 2018 PDF\4.pdf
B7: 5 | C7: 43137 | D7: MELLADO ORMACHEA ZEIDA | F7: NOMBRAMIENTO DE ASESOR | G7: DRA.LEON VILLALOBOS YOLANDA VICTORIA | H7: =HYPERLINK("\\Pc-informes\documentos informes\RESOLUCIONES\RESOLUCIONES 2018 PDF\5.PDF","..\RESOLUCIONES 2018 PDF\5.pdf") -> ..\RESOLUCIONES 2018 PDF\5.pdf
B8: 6 | C8: 43138 | D8: ARRAYAN BONETT SAYDA MAGALY | F8: NOMBRAMIENTO DE ASESOR | G8: DRA.LEON VILLALOBOS YOLANDA VICTORIA | H8: =HYPERLINK("\\Pc-informes\documentos informes\RESOLUCIONES\RESOLUCIONES 2018 PDF\6.PDF","..\RESOLUCIONES 2018 PDF\6.pdf") -> ..\RESOLUCIONES 2018 PDF\6.pdf
B9: 7 | C9: 43138 | D9: ROJAS ZANABRIA MANUEL VALERIANO | F9: NOMBRAMIENTO DE ASESOR | G9: DR.AGUIRRE ESPINOZA EDWARDS JESUS | H9: =HYPERLINK("\\Pc-informes\documentos informes\RESOLUCIONES\RESOLUCIONES 2018 PDF\7.PDF","..\RESOLUCIONES 2018 PDF\7.pdf") -> ..\RESOLUCIONES 2018 PDF\7.pdf
B10: 8 | C10: 43138 | D10: NEGRON CALVO LISARDO | F10: NOMBRAMIENTO DE ASESOR | G10: DR.AGUIRRE ESPINOZA EDWARDS JESUS | H10: =HYPERLINK("\\Pc-informes\documentos informes\RESOLUCIONES\RESOLUCIONES 2018 PDF\8.PDF","..\RESOLUCIONES 2018 PDF\8.pdf") -> ..\RESOLUCIONES 2018 PDF\8.pdf
B11: 9 | C11: 43138 | D11: MARIACA BRAVO WELLINGTON HERMOGENES | F11: NOMBRAMIENTO DE ASESOR | G11: MGT.CAVERO PACHECO SHAILI JULIE | H11: =HYPERLINK("\\Pc-informes\documentos informes\RESOLUCIONES\RESOLUCIONES 2018 PDF\9.PDF","..\RESOLUCIONES 2018 PDF\9.pdf") -> ..\RESOLUCIONES 2018 PDF\9.pdf
B12: 10 | C12: 43139 | D12: REINOSO ZEBALLOS JENNY | F12: CORRESPONDENCIA DE ESTUDIOS | H12: =HYPERLINK("\\Pc-informes\documentos informes\RESOLUCIONES\RESOLUCIONES 2018 PDF\10.PDF","..\RESOLUCIONES 2018 PDF\10.pdf") -> ..\RESOLUCIONES 2018 PDF\10.pdf
B13: 11 | D13: NO HAY RESOLUCION
B14: 12 | C14: 43140 | D14: LIMACHI CHALLCO LUIS ANGEL | F14: NOMBRAMIENTO DE ASESOR | G14: MGT.CAVERO PACHECO SHAILI JULIE | H14: =HYPERLINK("\\Pc-informes\documentos informes\RESOLUCIONES\RESOLUCIONES 2018 PDF\12.PDF","..\RESOLUCIONES 2018 PDF\12.pdf") -> ..\RESOLUCIONES 2018 PDF\12.pdf
B15: 13 | C15: 43140 | D15: PALIZA TORRES KARINA LILIANA | F15: NOMBRAMIENTO DE ASESOR | G15: MGT.CAVERO PACHECO SHAILI JULIE | H15: =HYPERLINK("\\Pc-informes\documentos informes\RESOLUCIONES\RESOLUCIONES 2018 PDF\13.PDF","..\RESOLUCIONES 2018 PDF\13.pdf") -> ..\RESOLUCIONES 2018 PDF\13.pdf
B16: 14 | C16: 43140 | D16: VALENZA ARAGON MONICA | F16: NOMBRAMIENTO DE ASESOR | G16: DR.AGUIRRE ESPINOZA EDWARDS JESUS | H16: =HYPERLINK("\\Pc-informes\documentos informes\RESOLUCIONES\RESOLUCIONES 2018 PDF\14.PDF","..\RESOLUCIONES 2018 PDF\14.pdf") -> ..\RESOLUCIONES 2018 PDF\14.pdf
B17: 15 | C17: 43140 | D17: PACCO CCORAHUA ELEUTERIO | F17: NOMBRAMIENTO DE ASESOR | G17: DR.CAMERO HERMOZA PEDRO | H17: =HYPERLINK("\\Pc-informes\documentos informes\RESOLUCIONES\RESOLUCIONES 2018 PDF\15.PDF","..\RESOLUCIONES 2018 PDF\15.pdf") -> ..\RESOLUCIONES 2018 PDF\15.pdf
B18: 16 | C18: 43140 | D18: USCAPI VILLAVICENCIO ROMULO | F18: NOMBRAMIENTO DE ASESOR | G18: MGT.AGUIRRE ABARCA ANA ELlZABETH | H18: =HYPERLINK("\\Pc-informes\documentos informes\RESOLUCIONES\RESOLUCIONES 2018 PDF\16.PDF","..\RESOLUCIONES 2018 PDF\16.pdf") -> ..\RESOLUCIONES 2018 PDF\16.pdf
A19: ENVIADO | B19: 17 | C19: 43140 | D19: VARGAS LUNA EDUARDO | F19: RECONOCER NOTA SUBSANACION | G19: DR. HOLGUIN SEGOVIA | H19: =HYPERLINK("\\Pc-informes\documentos informes\RESOLUCIONES\RESOLUCIONES 2018 PDF\17.PDF","..\RESOLUCIONES 2018 PDF\17.pdf") -> ..\RESOLUCIONES 2018 PDF\17.pdf
B20: 18 | C20: 43140 | D20: PAREDES MANSILLA FREDDY | F20: NOMBRAMIENTO DE ASESOR | G20: MGT.MONTALVO TORRES MARCO ANTONIO | H20: =HYPERLINK("\\Pc-informes\documentos informes\RESOLUCIONES\RESOLUCIONES 2018 PDF\18.PDF","..\RESOLUCIONES 2018 PDF\18.pdf") -> ..\RESOLUCIONES 2018 PDF\18.pdf
B21: 19 | C21: 43140 | D21: AGUILAR ROJAS ELIAS | F21: NOMBRAMIENTO DE ASESOR | G21: DR.AGUIRRE ESPINOZA EDWARDS JESUS | H21: =HYPERLINK("\\Pc-informes\documentos informes\RESOLUCIONES\RESOLUCIONES 2018 PDF\19.PDF","..\RESOLUCIONES 2018 PDF\19.pdf") -> ..\RESOLUCIONES 2018 PDF\19.pdf
B22: 20 | C22: 43140 | D22: OVIEDO TAPIA JOHANSH | F22: AUTORIZAR SUBSANACION | G22: MG. CHACON SANCHEZ VICTOR | H22: =HYPERLINK("\\Pc-informes\documentos informes\RESOLUCIONES\RESOLUCIONES 2018 PDF\20.PDF","..\RESOLUCIONES 2018 PDF\20.pdf") -> ..\RESOLUCIONES 2018 PDF\20.pdf
B23: 21 | C23: 43143 | D23: HUAMAN GONZALES FREDY | F23: AUTORIZAR SUBSANACION | G23: MG. CHACON SANCHEZ VICTOR | H23: =HYPERLINK("\\Pc-informes\documentos informes\RESOLUCIONES\RESOLUCIONES 2018 PDF\21.PDF","..\RESOLUCIONES 2018 PDF\21.pdf") -> ..\RESOLUCIONES 2018 PDF\21.pdf
B24: 22 | C24: 43143 | D24: ZEVALLOS GUZMAN HERBERT JESUS | F24: NOMBRAMIENTO DE ASESOR | G24: MGT.PEREZ MONTESINOS JEAN FERNANDO | H24: =HYPERLINK("\\Pc-informes\documentos informes\RESOLUCIONES\RESOLUCIONES 2018 PDF\22.PDF","..\RESOLUCIONES 2018 PDF\22.pdf") -> ..\RESOLUCIONES 2018 PDF\22.pdf
B25: 23 | C25: 43144 | D25: MUÑIZ TAPIA FELIPE | F25: NOMBRAMIENTO DE ASESOR | G25: MGT.YEPES CAJIGAS YENNY ARASELI | H25: =HYPERLINK("\\Pc-informes\documentos informes\RESOLUCIONES\RESOLUCIONES 2018 PDF\23.PDF","..\RESOLUCIONES 2018 PDF\23.pdf") -> ..\RESOLUCIONES 2018 PDF\23.pdf | I25: Anular
B26: 24 | C26: 43144 | D26: CASTILLO MAMANI JULIO ASENCIO | F26: CAMBIO DE DICTAMINANTE | H26: =HYPERLINK("\\Pc-informes\documentos informes\RESOLUCIONES\RESOLUCIONES 2018 PDF\24.PDF","..\RESOLUCIONES 2018 PDF\24.pdf") -> ..\RESOLUCIONES 2018 PDF\24.pdf
B27: 25 | C27: 43145 | D27: ORTEGA RODRIGUEZ PATRICIA | F27: ELEVAR AL VRAC | G27: Docencia Universitaria | H27: =HYPERLINK("\\Pc-informes\documentos informes\RESOLUCIONES\RESOLUCIONES 2018 PDF\25.PDF","..\RESOLUCIONES 2018 PDF\25.pdf") -> ..\RESOLUCIONES 2018 PDF\25.pdf
B28: 26 | C28: 43146 | D28: HERRERA QUISPE GLENNY JUNNIOR | F28: RECTIFICAR NOTA | G28: DR. RENGIFO LOZANO RAUL ALBERTO | H28: =HYPERLINK("\\Pc-informes\documentos informes\RESOLUCIONES\RESOLUCIONES 2018 PDF\26.PDF","..\RESOLUCIONES 2018 PDF\26.pdf") -> ..\RESOLUCIONES 2018 PDF\26.pdf
B29: 27 | C29: 43147 | D29: ROJAS ANAYA YANINA | F29: DECLARAR APTO EL EXPEDIENTE | H29: =HYPERLINK("\\Pc-informes\documentos informes\RESOLUCIONES\RESOLUCIONES 2018 PDF\27.PDF","..\RESOLUCIONES 2018 PDF\27.pdf") -> ..\RESOLUCIONES 2018 PDF\27.pdf
B30: 28 | C30: 43147 | D30: AGUILAR VILLAFUERTE GEORGE LUIS | F30: NOMBRAMIENTO DE ASESOR | G30: EDWARS JESUS AGUIRRE ESPINOZA
A31: ENVIADO | B31: 29 | C31: 43150 | D31: VELASQUEZ HACHA IGNACIO | F31: ELEVAR AL VRAC | G31: Doctorado en Ciencias de la Educacion | H31: =HYPERLINK("\\Pc-informes\documentos informes\RESOLUCIONES\RESOLUCIONES 2018 PDF\29.PDF","..\RESOLUCIONES 2018 PDF\29.pdf") -> ..\RESOLUCIONES 2018 PDF\29.pdf
A32: ENVIADO | B32: 30 | C32: 43150 | D32: VERA HURTADO YORKI YINO | F32: ELEVAR AL VRAC | G32: Ciencias Estomatologicas | H32: =HYPERLINK("\\Pc-informes\documentos informes\RESOLUCIONES\RESOLUCIONES 2018 PDF\30.PDF","..\RESOLUCIONES 2018 PDF\30.pdf") -> ..\RESOLUCIONES 2018 PDF\30.pdf
B33: 31 | C33: 43150 | D33: CHILLITUPA BACA LISSETH | F33: CAMBIO DE DICTAMINANTE | H33: =HYPERLINK("\\Pc-informes\documentos informes\RESOLUCIONES\RESOLUCIONES 2018 PDF\31.PDF","..\RESOLUCIONES 2018 PDF\31.pdf") -> ..\RESOLUCIONES 2018 PDF\31.pdf
B34: 32 | C34: 43151 | D34: ROJAS PARIONA CARMEN ROSA | F34: INSCRIPCION DE TEMA DE TESIS | H34: ..\RESOLUCIONES 2018 PDF\32.pdf
B35: Proveido | C35: 43151 | D35: MONTOYA LIZARRAGA MANUEL ANDRES
B36: 33 | C36: 43151 | D36: SANCHEZ CHAVEZ CARLA SUSAN | F36: FIJAR FECHA Y HORA | H36: =HYPERLINK("\\Pc-informes\documentos informes\RESOLUCIONES\RESOLUCIONES 2018 PDF\33.PDF","..\RESOLUCIONES 2018 PDF\33.pdf") -> ..\RESOLUCIONES 2018 PDF\33.pdf
B37: 34 | C37: 43153 | D37: CALLA NINA MIGUEL ANGEL | F37: AUTORIZAR SUBSANACION | G37: DR. CASTRO CUBA BARINEZA | H37: =HYPERLINK("\\Pc-informes\documentos informes\RESOLUCIONES\RESOLUCIONES 2018 PDF\34.PDF","..\RESOLUCIONES 2018 PDF\34.pdf") -> ..\RESOLUCIONES 2018 PDF\34.pdf
B38: 35 | G38: anulado
B39: 36 | G39: anulado
B40: 37 | C40: 43157 | D40: COAVOY ARAPA LUZ ELIANA | F40: NOMBRAMIENTO DE ASESOR | G40: DRA. LA TORRE RIVEROS LYDA | H40: =HYPERLINK("\\Pc-informes\documentos informes\RESOLUCIONES\RESOLUCIONES 2018 PDF\37.PDF","..\RESOLUCIONES 2018 PDF\37.pdf") -> ..\RESOLUCIONES 2018 PDF\37.pdf
B41: 38 | G41: anulado
B42: 39 | G42: anulado
B43: 40 | G43: anulado
B44: 41 | G44: anulado
B45: 42 | G45: anulado
B46: 43 | G46: anulado
B47: 44 | G47: anulado
B48: 45 | G48: anulado
B49: 46 | G49: anulado
B50: 47 | G50: anulado
B51: 48 | C51: 43158 | D51: AGUILAR OBLITAS LAURA PRISCILLA | F51: FIJAR FECHA Y HORA | H51: ..\RESOLUCIONES 2018 PDF\48.pdf
B52: 49 | G52: anulado
B53: 50 | G53: anulado
B54: 51 | G54: anulado
B55: 52 | C55: 43159 | D55: CORBACHO CARPIO ISABEL | F55: CURSO DIRIGIDO | H55: =HYPERLINK("\\Pc-informes\documentos informes\RESOLUCIONES\RESOLUCIONES 2018 PDF\52.PDF","..\RESOLUCIONES 2018 PDF\52.pdf") -> ..\RESOLUCIONES 2018 PDF\52.pdf
A56: ENVIADO | B56: 53 | C56: 43160 | D56: DALGUER VIZCARRA SONIA | F56: RECONOCER NOTA SUBSANACION | G56: DR. HILDEBRANDO DIAZ | H56: ..\RESOLUCIONES 2018 PDF\53.pdf
A57: ENVIADO | B57: 54 | C57: 43160 | D57: PAUCAR HANCO JHOEL | F57: RECONOCER NOTA SUBSANACION | G57: DR. HILDEBRANDO DIAZ | H57: =HYPERLINK("\\Pc-informes\documentos informes\RESOLUCIONES\RESOLUCIONES 2018 PDF\54.PDF","..\RESOLUCIONES 2018 PDF\54.pdf") -> ..\RESOLUCIONES 2018 PDF\54.pdf
A58: ENVIADO | B58: 55 | C58: 43160 | D58: ALVAREZ VEGA VALERY SUCEL | F58: RECONOCER NOTA SUBSANACION | G58: DR. HILDEBRANDO DIAZ | H58: =HYPERLINK("\\Pc-informes\documentos informes\RESOLUCIONES\RESOLUCIONES 2018 PDF\55.PDF","..\RESOLUCIONES 2018 PDF\55.pdf") -> ..\RESOLUCIONES 2018 PDF\55.pdf
A59: DOC. MEDIO AMBIENTE | B59: 56 | C59: 43160 | D59: JAYO SILVA CARLOS EDUARDO | F59: AUTORIZAR SUBSANACION | G59: DR. SILVA SIERRA | H59: =HYPERLINK("\\Pc-informes\documentos informes\RESOLUCIONES\RESOLUCIONES 2018 PDF\56.PDF","..\RESOLUCIONES 2018 PDF\56.pdf") -> ..\RESOLUCIONES 2018 PDF\56.pdf
B60: 57 | C60: 43161 | D60: VELASQUEZ QUIROZ PILAR EMILCE | F60: AUTORIZAR SUBSANACION | G60: DR. CASTRO CUBA BARINEZA | H60: =HYPERLINK("\\Pc-informes\documentos informes\RESOLUCIONES\RESOLUCIONES 2018 PDF\57.PDF","..\RESOLUCIONES 2018 PDF\57.pdf") -> ..\RESOLUCIONES 2018 PDF\57.pdf
B61: 58 | C61: 43161 | D61: ATAYUPANQUI QUISPE JORGE AUGUSTO | F61: CURSO DIRIGIDO | G61: DR. CLETO DE LA TORRE | H61: =HYPERLINK("\\Pc-informes\documentos informes\RESOLUCIONES\RESOLUCIONES 2018 PDF\58.PDF","..\RESOLUCIONES 2018 PDF\58.pdf") -> ..\RESOLUCIONES 2018 PDF\58.pdf
B62: 59 | C62: 43161 | D62: PUMA ANCCO MIGUEL ALEJANDRO | F62: AUTORIZAR SUBSANACION | G62: MG. ASTETE SAMANEZ | H62: =HYPERLINK("\\Pc-informes\documentos informes\RESOLUCIONES\RESOLUCIONES 2018 PDF\59.PDF","..\RESOLUCIONES 2018 PDF\59.pdf") -> ..\RESOLUCIONES 2018 PDF\59.pdf
A63: 1321 | B63: 60 | C63: 43161 | D63: ZUBILETA CANSAYA MIJAEL YOAL | F63: AUTORIZAR SUBSANACION | G63: MG. CHACON SANCHEZ VICTOR | H63: =HYPERLINK("\\Pc-informes\documentos informes\RESOLUCIONES\RESOLUCIONES 2018 PDF\60.PDF","..\RESOLUCIONES 2018 PDF\60.pdf") -> ..\RESOLUCIONES 2018 PDF\60.pdf
B64: 61 | C64: 43161 | D64: OLIVARES TORRE GRETEL ROXANA | F64: DECLARAR APTO EL EXPEDIENTE | H64: =HYPERLINK("\\Pc-informes\documentos informes\RESOLUCIONES\RESOLUCIONES 2018 PDF\61.PDF","..\RESOLUCIONES 2018 PDF\61.pdf") -> ..\RESOLUCIONES 2018 PDF\61.pdf
B65: 62 | C65: 43161 | D65: VALLE ORTEGA GUYEN MARIO | F65: AUTORIZAR SUBSANACION | G65: MG. CHACON SANCHEZ VICTOR | H65: =HYPERLINK("\\Pc-informes\documentos informes\RESOLUCIONES\RESOLUCIONES 2018 PDF\62.PDF","..\RESOLUCIONES 2018 PDF\62.pdf") -> ..\RESOLUCIONES 2018 PDF\62.pdf
B66: 63 | C66: 43161 | D66: HILARES SOLIS EVELIO | F66: AUTORIZAR SUBSANACION | G66: MG. CHACON SANCHEZ VICTOR | H66: =HYPERLINK("\\Pc-informes\documentos informes\RESOLUCIONES\RESOLUCIONES 2018 PDF\63.PDF","..\RESOLUCIONES 2018 PDF\63.pdf") -> ..\RESOLUCIONES 2018 PDF\63.pdf
B67: 64 | C67: 43161 | D67: FARFAN GOMEZ ELIAS | F67: AUTORIZAR SUBSANACION | G67: DR. CLETO DE LA TORRE | H67: =HYPERLINK("\\Pc-informes\documentos informes\RESOLUCIONES\RESOLUCIONES 2018 PDF\64.PDF","..\RESOLUCIONES 2018 PDF\64.pdf") -> ..\RESOLUCIONES 2018 PDF\64.pdf
B68: 65 | C68: 43161 | D68: LLAVE HUAMAN LISET | F68: AUTORIZAR SUBSANACION | G68: DR. AVENDAÑO UCHUYA | H68: =HYPERLINK("\\Pc-informes\documentos informes\RESOLUCIONES\RESOLUCIONES 2018 PDF\65.PDF","..\RESOLUCIONES 2018 PDF\65.pdf") -> ..\RESOLUCIONES 2018 PDF\65.pdf
B69: 66 | C69: 43161 | D69: CHAFLOQUE RIVERA PAVEL CHRISTIAN RODOLFO | F69: CURSO DIRIGIDO | G69: DR. RIOS MAYORGA | H69: =HYPERLINK("\\Pc-informes\documentos informes\RESOLUCIONES\RESOLUCIONES 2018 PDF\66.PDF","..\RESOLUCIONES 2018 PDF\66.pdf") -> ..\RESOLUCIONES 2018 PDF\66.pdf
B70: 67 | C70: 43161 | D70: CHOQUE ROQUE GENARO ZEBEDEO | F70: AUTORIZAR SUBSANACION | G70: MG. CHACON SANCHEZ VICTOR | H70: =HYPERLINK("\\Pc-informes\documentos informes\RESOLUCIONES\RESOLUCIONES 2018 PDF\67.PDF","..\RESOLUCIONES 2018 PDF\67.pdf") -> ..\RESOLUCIONES 2018 PDF\67.pdf
B71: 68 | C71: 43161 | D71: HUAMANI PEREZ MARIA ISABEL | F71: ELEVAR AL VRAC | G71: Contabilidad con Mención en Auditoria y Control Interno | H71: =HYPERLINK("\\Pc-informes\documentos informes\RESOLUCIONES\RESOLUCIONES 2018 PDF\68.PDF","..\RESOLUCIONES 2018 PDF\68.pdf") -> ..\RESOLUCIONES 2018 PDF\68.pdf
B72: 69 | C72: 43164 | D72: REINOSO ZEBALLOS JENNY | F72: DECLARAR APTO EL EXPEDIENTE | H72: =HYPERLINK("\\Pc-informes\documentos informes\RESOLUCIONES\RESOLUCIONES 2018 PDF\69.PDF","..\RESOLUCIONES 2018 PDF\69.pdf") -> ..\RESOLUCIONES 2018 PDF\69.pdf
B73: 70 | C73: 43164 | D73: SAIRE YAÑEZ ELIDA | F73: DECLARAR APTO EL EXPEDIENTE | H73: =HYPERLINK("\\Pc-informes\documentos informes\RESOLUCIONES\RESOLUCIONES 2018 PDF\70.PDF","..\RESOLUCIONES 2018 PDF\70.pdf") -> ..\RESOLUCIONES 2018 PDF\70.pdf
B74: 71 | C74: 43164 | D74: MARCAVILLACA NUÑEZ HAYDEE MARUJA | F74: DECLARAR APTO EL EXPEDIENTE | H74: =HYPERLINK("\\Pc-informes\documentos informes\RESOLUCIONES\RESOLUCIONES 2018 PDF\71.PDF","..\RESOLUCIONES 2018 PDF\71.pdf") -> ..\RESOLUCIONES 2018 PDF\71.pdf
B75: 72 | C75: 43164 | D75: TARAZONA MORANTE MIGUEL JULIAN | F75: DECLARAR APTO EL EXPEDIENTE | H75: =HYPERLINK("\\Pc-informes\documentos informes\RESOLUCIONES\RESOLUCIONES 2018 PDF\72.PDF","..\RESOLUCIONES 2018 PDF\72.pdf") -> ..\RESOLUCIONES 2018 PDF\72.pdf
B76: 73 | C76: 43164 | D76: CAVERO PACHECO SHAILI JULIE | F76: DECLARAR APTO EL EXPEDIENTE | H76: =HYPERLINK("\\Pc-informes\documentos informes\RESOLUCIONES\RESOLUCIONES 2018 PDF\73.PDF","..\RESOLUCIONES 2018 PDF\73.pdf") -> ..\RESOLUCIONES 2018 PDF\73.pdf
B77: 74 | C77: 43164 | D77: MUÑOZ HUAMANCCARI CELIS | F77: DECLARAR APTO EL EXPEDIENTE | H77: =HYPERLINK("\\Pc-informes\documentos informes\RESOLUCIONES\RESOLUCIONES 2018 PDF\74.PDF","..\RESOLUCIONES 2018 PDF\74.pdf") -> ..\RESOLUCIONES 2018 PDF\74.pdf
A78: 10067 | B78: 75 | C78: 43164 | D78: JIMENEZ GARRIAZO MARIA CECILIA | F78: DECLARAR APTO EL EXPEDIENTE | H78: =HYPERLINK("\\Pc-informes\documentos informes\RESOLUCIONES\RESOLUCIONES 2018 PDF\75.PDF","..\RESOLUCIONES 2018 PDF\75.pdf") -> ..\RESOLUCIONES 2018 PDF\75.pdf
A79: 9880 | B79: 76 | C79: 43164 | D79: GAMARRA VILLANUEVA WILFREDO | F79: DECLARAR APTO EL EXPEDIENTE | H79: =HYPERLINK("\\Pc-informes\documentos informes\RESOLUCIONES\RESOLUCIONES 2018 PDF\76.PDF","..\RESOLUCIONES 2018 PDF\76.pdf") -> ..\RESOLUCIONES 2018 PDF\76.pdf
B80: 77 | C80: 43164 | D80: YANARICO OCHOA GLADYS | F80: DECLARAR APTO EL EXPEDIENTE | H80: =HYPERLINK("\\Pc-informes\documentos informes\RESOLUCIONES\RESOLUCIONES 2018 PDF\77.PDF","..\RESOLUCIONES 2018 PDF\77.pdf") -> ..\RESOLUCIONES 2018 PDF\77.pdf
B81: 78 | C81: 43164 | D81: ZURITA CHURA DAVID HELMER | F81: DICTAMEN DE TESIS | H81: =HYPERLINK("\\Pc-informes\documentos informes\RESOLUCIONES\RESOLUCIONES 2018 PDF\78.PDF","..\RESOLUCIONES 2018 PDF\78.pdf") -> ..\RESOLUCIONES 2018 PDF\78.pdf
B82: 79 | C82: 43164 | D82: BAZALAR SEQUEIROS YESSICA ROSARIO | F82: DICTAMEN DE TESIS | H82: =HYPERLINK("\\Pc-informes\documentos informes\RESOLUCIONES\RESOLUCIONES 2018 PDF\79.PDF","..\RESOLUCIONES 2018 PDF\79.pdf") -> ..\RESOLUCIONES 2018 PDF\79.pdf
B83: 80 | C83: 43164 | D83: ALAGON CANAHUIRE CENETH | F83: DICTAMEN DE TESIS | H83: =HYPERLINK("\\Pc-informes\documentos informes\RESOLUCIONES\RESOLUCIONES 2018 PDF\80.PDF","..\RESOLUCIONES 2018 PDF\80.pdf") -> ..\RESOLUCIONES 2018 PDF\80.pdf
B84: 81 | C84: 43164 | D84: CARRASCO ARAOZ JOSCA IRINOVA | F84: DICTAMEN DE TESIS | H84: =HYPERLINK("\\Pc-informes\documentos informes\RESOLUCIONES\RESOLUCIONES 2018 PDF\81.PDF","..\RESOLUCIONES 2018 PDF\81.pdf") -> ..\RESOLUCIONES 2018 PDF\81.pdf
B85: 82 | C85: 43164 | D85: GUEVARA CANDIA RAFAEL FERNANDO | F85: DICTAMEN DE TESIS | H85: =HYPERLINK("\\Pc-informes\documentos informes\RESOLUCIONES\RESOLUCIONES 2018 PDF\82.PDF","..\RESOLUCIONES 2018 PDF\82.pdf") -> ..\RESOLUCIONES 2018 PDF\82.pdf
B86: 83 | C86: 43164 | D86: MARTINEZ CORAZAO SANDRA LISETTE | F86: DICTAMEN DE TESIS | H86: =HYPERLINK("\\Pc-informes\documentos informes\RESOLUCIONES\RESOLUCIONES 2018 PDF\83.PDF","..\RESOLUCIONES 2018 PDF\83.pdf") -> ..\RESOLUCIONES 2018 PDF\83.pdf
B87: 84 | C87: 43164 | D87: MANSILLA PIZARRO PATRICIA | F87: DICTAMEN DE TESIS | H87: ..\RESOLUCIONES 2018 PDF\84.pdf
B88: 85 | C88: 43164 | D88: DEL CASTILLO RIVAS ANGEL | F88: DICTAMEN DE TESIS | H88: ..\RESOLUCIONES 2018 PDF\85.pdf
B89: 86 | C89: 43164 | D89: VERA MARMANILLO VERONIKA ISELA | F89: DICTAMEN DE TESIS | H89: =HYPERLINK("\\Pc-informes\documentos informes\RESOLUCIONES\RESOLUCIONES 2018 PDF\86.PDF","..\RESOLUCIONES 2018 PDF\86.pdf") -> ..\RESOLUCIONES 2018 PDF\86.pdf
B90: 87 | C90: 43164 | D90: HERRERA CENTENO YUDRIEL | E90: 016201379K | F90: DICTAMEN DE PROYECTO TESIS | H90: =HYPERLINK("\\Pc-informes\documentos informes\RESOLUCIONES\RESOLUCIONES 2018 PDF\87.PDF","..\RESOLUCIONES 2018 PDF\87.pdf") -> ..\RESOLUCIONES 2018 PDF\87.pdf
B91: 88 | C91: 43164 | D91: COAVOY ARAPA LUZ ELIANA | F91: DICTAMEN DE TESIS | H91: =HYPERLINK("\\Pc-informes\documentos informes\RESOLUCIONES\RESOLUCIONES 2018 PDF\88.PDF","..\RESOLUCIONES 2018 PDF\88.pdf") -> ..\RESOLUCIONES 2018 PDF\88.pdf
B92: 89 | C92: 43164 | D92: MERMA PALACIOS RUTH | F92: DICTAMEN DE TESIS | H92: =HYPERLINK("\\Pc-informes\documentos informes\RESOLUCIONES\RESOLUCIONES 2018 PDF\89.PDF","..\RESOLUCIONES 2018 PDF\89.pdf") -> ..\RESOLUCIONES 2018 PDF\89.pdf
B93: 90 | C93: 43164 | D93: TORRE AYALA ZINDHY LIZBETH | F93: DICTAMEN DE TESIS | H93: =HYPERLINK("\\Pc-informes\documentos informes\RESOLUCIONES\RESOLUCIONES 2018 PDF\90.PDF","..\RESOLUCIONES 2018 PDF\90.pdf") -> ..\RESOLUCIONES 2018 PDF\90.pdf
B94: 91 | C94: 43164 | D94: ARRARTE VERA FEDERICO | F94: DICTAMEN DE TESIS | H94: =HYPERLINK("\\Pc-informes\documentos informes\RESOLUCIONES\RESOLUCIONES 2018 PDF\91.PDF","..\RESOLUCIONES 2018 PDF\91.pdf") -> ..\RESOLUCIONES 2018 PDF\91.pdf
B95: 92 | C95: 43164 | D95: ORELLANA ECHEGARAY MACX ARTHUR | F95: DICTAMEN DE TESIS | H95: =HYPERLINK("\\Pc-informes\documentos informes\RESOLUCIONES\RESOLUCIONES 2018 PDF\92.PDF","..\RESOLUCIONES 2018 PDF\92.pdf") -> ..\RESOLUCIONES 2018 PDF\92.pdf
B96: 93 | C96: 43167 | D96: ESTRADA SANCHEZ AMERICO | F96: INSCRIPCION DE TEMA DE TESIS | H96: =HYPERLINK("\\Pc-informes\documentos informes\RESOLUCIONES\RESOLUCIONES 2018 PDF\93.PDF","..\RESOLUCIONES 2018 PDF\93.pdf") -> ..\RESOLUCIONES 2018 PDF\93.pdf
A97: 9825 | B97: 94 | C97: 43167 | D97: CARDENAS VELASQUEZ LILIANA | F97: INSCRIPCION DE TEMA DE TESIS | H97: =HYPERLINK("\\Pc-informes\documentos informes\RESOLUCIONES\RESOLUCIONES 2018 PDF\94.PDF","..\RESOLUCIONES 2018 PDF\94.pdf") -> ..\RESOLUCIONES 2018 PDF\94.pdf
A98: 10331 | B98: 95 | C98: 43167 | D98: CASA GUTIERREZ PAOLA YAZMIN | F98: INSCRIPCION DE TEMA DE TESIS | H98: =HYPERLINK("\\Pc-informes\documentos informes\RESOLUCIONES\RESOLUCIONES 2018 PDF\95.PDF","..\RESOLUCIONES 2018 PDF\95.pdf") -> ..\RESOLUCIONES 2018 PDF\95.pdf
